Workbook

Sheet schedule_1 
A1: Year | B1: Ore (t) | C1: Grade (g/t) | D1: Recovery (override, optional) | E1: Metal Price (override, optional) | F1: Metal Produced (oz) | G1: Revenue (USD) | H1: Severance Tax (USD) | I1: Discount Factor | J1: PV(Severance Tax) (USD) | K1: Cumulative Revenue (USD) | L1: Payable Metal (oz) | M1: NSR ($) | N1: Royalty ($) | O1: PV(Royalty)
A2: 1 | B2: 13000000 | C2: 2.02 | D2: 0.82 | E2: 1600 | F2: =IFERROR(B2*C2*IF(D2="", Parameters!$B$2, D2)/Parameters!$B$6, 0) -> 692307.94 | G2: =F2*IF(E2="", Parameters!$B$2, E2) -> 1.1076927e+09 | H2: =G2*Parameters!$B$4 -> 28800010 | I2: =1/POWER(1+Parameters!$B$5, A2) -> 0.90909091 | J2: =H2*I2 -> 26181828 | K2: =SUM($G$2:G2) -> 1.1076927e+09 | L2: =F2*0.95 -> 657692.54 | M2: =L2*IF(E2="",Parameters!$B$2,E2) -> 1.0523081e+09 | N2: =M2*0.0251 -> 26412933 | O2: =N2*I2 -> 24011757
A3: 2 | B3: 13000000 | C3: 2.02 | D3: 0.82 | E3: 1600 | F3: =IFERROR(B3*C3*IF(D3="", Parameters!$B$2, D3)/Parameters!$B$6, 0) -> 692307.94 | G3: =F3*IF(E3="", Parameters!$B$2, E3) -> 1.1076927e+09 | H3: =G3*Parameters!$B$4 -> 28800010 | I3: =1/POWER(1+Parameters!$B$5, A3) -> 0.82644628 | J3: =H3*I3 -> 23801661 | K3: =SUM($G$2:G3) -> 2.2153854e+09 | L3: =F3*0.95 -> 657692.54 | M3: =L3*IF(E3="",Parameters!$B$2,E3) -> 1.0523081e+09 | N3: =M3*0.0251 -> 26412933 | O3: =N3*I3 -> 21828870
A4: 3 | B4: 13000000 | C4: 2.02 | D4: 0.82 | E4: 1600 | F4: =IFERROR(B4*C4*IF(D4="", Parameters!$B$2, D4)/Parameters!$B$6, 0) -> 692307.94 | G4: =F4*IF(E4="", Parameters!$B$2, E4) -> 1.1076927e+09 | H4: =G4*Parameters!$B$4 -> 28800010 | I4: =1/POWER(1+Parameters!$B$5, A4) -> 0.7513148 | J4: =H4*I4 -> 21637874 | K4: =SUM($G$2:G4) -> 3.3230781e+09 | L4: =F4*0.95 -> 657692.54 | M4: =L4*IF(E4="",Parameters!$B$2,E4) -> 1.0523081e+09 | N4: =M4*0.0251 -> 26412933 | O4: =N4*I4 -> 19844427
A5: 4 | B5: 13000000 | C5: 2.02 | D5: 0.82 | E5: 1600 | F5: =IFERROR(B5*C5*IF(D5="", Parameters!$B$2, D5)/Parameters!$B$6, 0) -> 692307.94 | G5: =F5*IF(E5="", Parameters!$B$2, E5) -> 1.1076927e+09 | H5: =G5*Parameters!$B$4 -> 28800010 | I5: =1/POWER(1+Parameters!$B$5, A5) -> 0.68301346 | J5: =H5*I5 -> 19670795 | K5: =SUM($G$2:G5) -> 4.4307708e+09 | L5: =F5*0.95 -> 657692.54 | M5: =L5*IF(E5="",Parameters!$B$2,E5) -> 1.0523081e+09 | N5: =M5*0.0251 -> 26412933 | O5: =N5*I5 -> 18040388
A6: 5 | B6: 13000000 | C6: 2.02 | D6: 0.82 | E6: 1600 | F6: =IFERROR(B6*C6*IF(D6="", Parameters!$B$2, D6)/Parameters!$B$6, 0) -> 692307.94 | G6: =F6*IF(E6="", Parameters!$B$2, E6) -> 1.1076927e+09 | H6: =G6*Parameters!$B$4 -> 28800010 | I6: =1/POWER(1+Parameters!$B$5, A6) -> 0.62092132 | J6: =H6*I6 -> 17882540 | K6: =SUM($G$2:G6) -> 5.5384635e+09 | L6: =F6*0.95 -> 657692.54 | M6: =L6*IF(E6="",Parameters!$B$2,E6) -> 1.0523081e+09 | N6: =M6*0.0251 -> 26412933 | O6: =N6*I6 -> 16400353
A7: 6 | B7: 13000000 | C7: 2.02 | D7: 0.82 | E7: 1600 | F7: =IFERROR(B7*C7*IF(D7="", Parameters!$B$2, D7)/Parameters!$B$6, 0) -> 692307.94 | G7: =F7*IF(E7="", Parameters!$B$2, E7) -> 1.1076927e+09 | H7: =G7*Parameters!$B$4 -> 28800010 | I7: =1/POWER(1+Parameters!$B$5, A7) -> 0.56447393 | J7: =H7*I7 -> 16256855 | K7: =SUM($G$2:G7) -> 6.6461562e+09 | L7: =F7*0.95 -> 657692.54 | M7: =L7*IF(E7="",Parameters!$B$2,E7) -> 1.0523081e+09 | N7: =M7*0.0251 -> 26412933 | O7: =N7*I7 -> 14909412
A8: 7 | B8: 13000000 | C8: 2.02 | D8: 0.82 | E8: 1600 | F8: =IFERROR(B8*C8*IF(D8="", Parameters!$B$2, D8)/Parameters!$B$6, 0) -> 692307.94 | G8: =F8*IF(E8="", Parameters!$B$2, E8) -> 1.1076927e+09 | H8: =G8*Parameters!$B$4 -> 28800010 | I8: =1/POWER(1+Parameters!$B$5, A8) -> 0.51315812 | J8: =H8*I8 -> 14778959 | K8: =SUM($G$2:G8) -> 7.7538489e+09 | L8: =F8*0.95 -> 657692.54 | M8: =L8*IF(E8="",Parameters!$B$2,E8) -> 1.0523081e+09 | N8: =M8*0.0251 -> 26412933 | O8: =N8*I8 -> 13554011
A9: 8 | B9: 13000000 | C9: 2.02 | D9: 0.82 | E9: 1600 | F9: =IFERROR(B9*C9*IF(D9="", Parameters!$B$2, D9)/Parameters!$B$6, 0) -> 692307.94 | G9: =F9*IF(E9="", Parameters!$B$2, E9) -> 1.1076927e+09 | H9: =G9*Parameters!$B$4 -> 28800010 | I9: =1/POWER(1+Parameters!$B$5, A9) -> 0.46650738 | J9: =H9*I9 -> 13435417 | K9: =SUM($G$2:G9) -> 8.8615416e+09 | L9: =F9*0.95 -> 657692.54 | M9: =L9*IF(E9="",Parameters!$B$2,E9) -> 1.0523081e+09 | N9: =M9*0.0251 -> 26412933 | O9: =N9*I9 -> 12321828
A10: 9 | B10: 13000000 | C10: 2.02 | D10: 0.82 | E10: 1600 | F10: =IFERROR(B10*C10*IF(D10="", Parameters!$B$2, D10)/Parameters!$B$6, 0) -> 692307.94 | G10: =F10*IF(E10="", Parameters!$B$2, E10) -> 1.1076927e+09 | H10: =G10*Parameters!$B$4 -> 28800010 | I10: =1/POWER(1+Parameters!$B$5, A10) -> 0.42409762 | J10: =H10*I10 -> 12214016 | K10: =SUM($G$2:G10) -> 9.9692343e+09 | L10: =F10*0.95 -> 657692.54 | M10: =L10*IF(E10="",Parameters!$B$2,E10) -> 1.0523081e+09 | N10: =M10*0.0251 -> 26412933 | O10: =N10*I10 -> 11201662
A11: 10 | B11: 13000000 | C11: 2.02 | D11: 0.82 | E11: 1600 | F11: =IFERROR(B11*C11*IF(D11="", Parameters!$B$2, D11)/Parameters!$B$6, 0) -> 692307.94 | G11: =F11*IF(E11="", Parameters!$B$2, E11) -> 1.1076927e+09 | H11: =G11*Parameters!$B$4 -> 28800010 | I11: =1/POWER(1+Parameters!$B$5, A11) -> 0.38554329 | J11: =H11*I11 -> 11103651 | K11: =SUM($G$2:G11) -> 1.1076927e+10 | L11: =F11*0.95 -> 657692.54 | M11: =L11*IF(E11="",Parameters!$B$2,E11) -> 1.0523081e+09 | N11: =M11*0.0251 -> 26412933 | O11: =N11*I11 -> 10183329
A12: 11 | B12: 13000000 | C12: 2.02 | D12: 0.82 | E12: 1600 | F12: =IFERROR(B12*C12*IF(D12="", Parameters!$B$2, D12)/Parameters!$B$6, 0) -> 692307.94 | G12: =F12*IF(E12="", Parameters!$B$2, E12) -> 1.1076927e+09 | H12: =G12*Parameters!$B$4 -> 28800010 | I12: =1/POWER(1+Parameters!$B$5, A12) -> 0.3504939 | J12: =H12*I12 -> 10094228 | K12: =SUM($G$2:G12) -> 1.218462e+10 | L12: =F12*0.95 -> 657692.54 | M12: =L12*IF(E12="",Parameters!$B$2,E12) -> 1.0523081e+09 | N12: =M12*0.0251 -> 26412933 | O12: =N12*I12 -> 9257571.7
A13: 12 | B13: 13000000 | C13: 2.02 | D13: 0.82 | E13: 1600 | F13: =IFERROR(B13*C13*IF(D13="", Parameters!$B$2, D13)/Parameters!$B$6, 0) -> 692307.94 | G13: =F13*IF(E13="", Parameters!$B$2, E13) -> 1.1076927e+09 | H13: =G13*Parameters!$B$4 -> 28800010 | I13: =1/POWER(1+Parameters!$B$5, A13) -> 0.31863082 | J13: =H13*I13 -> 9176570.8 | K13: =SUM($G$2:G13) -> 1.3292312e+10 | L13: =F13*0.95 -> 657692.54 | M13: =L13*IF(E13="",Parameters!$B$2,E13) -> 1.0523081e+09 | N13: =M13*0.0251 -> 26412933 | O13: =N13*I13 -> 8415974.3
... A33: 32 | B33: 13000000 | C33: 2.02 | D33: 0.82 | E33: 1600 | F33: =IFERROR(B33*C33*IF(D33="", Parameters!$B$2, D33)/Parameters!$B$6, 0) -> 692307.94 | G33: =F33*IF(E33="", Parameters!$B$2, E33) -> 1.1076927e+09 | H33: =G33*Parameters!$B$4 -> 28800010 | I33: =1/POWER(1+Parameters!$B$5, A33) -> 0.047362441 | J33: =H33*I33 -> 1364038.8 | K33: =SUM($G$2:G33) -> 3.5446167e+10 | L33: =F33*0.95 -> 657692.54 | M33: =L33*IF(E33="",Parameters!$B$2,E33) -> 1.0523081e+09 | N33: =M33*0.0251 -> 26412933 | O33: =N33*I33 -> 1250981
F39: Totals / Key Outputs | G39: =SUM(G2:G33) -> 3.5446167e+10 | H39: =SUM(H2:H33) -> 9.2160033e+08 | J39: =SUM(J2:J33) -> 2.7435972e+08 | O39: =SUM(O2:O33) -> 2.5161952e+08
F40: Total Revenue (USD) | G40: =G39 -> 3.5446167e+10
F41: Total Severance Tax (USD) | G41: =H39 -> 9.2160033e+08
F42: PV(Severance Tax) (USD) | G42: =J39 -> 2.7435972e+08

Sheet schedule_2
A1: Year | B1: Ore (t) | C1: Grade (g/t) | D1: Recovery (override, optional) | E1: Metal Price (override, optional) | F1: Metal Produced (oz) | G1: Revenue (USD) | H1: Severance Tax (USD) | I1: Discount Factor | J1: PV(Severance Tax) (USD) | K1: Cumulative Revenue (USD) | L1: Payable Metal (oz) | M1: NSR ($) | N1: Royalty ($) | O1: PV(Royalty)
A2: 1 | B2: 14000000 | C2: 1.952 | D2: 0.82 | E2: 1600 | F2: =IFERROR(B2*C2*IF(D2="", Parameters!$B$2, D2)/Parameters!$B$6, 0) -> 720464.26 | G2: =F2*IF(E2="", Parameters!$B$2, E2) -> 1.1527428e+09 | H2: =G2*Parameters!$B$4 -> 29971313 | I2: =1/POWER(1+Parameters!$B$5, A2) -> 0.90909091 | J2: =H2*I2 -> 27246648 | K2: =SUM($G$2:G2) -> 1.1527428e+09 | L2: =F2*0.95 -> 684441.04 | M2: =L2*IF(E2="",Parameters!$B$2,E2) -> 1.0951057e+09 | N2: =M2*0.0251 -> 27487152 | O2: =N2*I2 -> 24988320
A3: 2 | B3: 14000000 | C3: 1.952 | D3: 0.82 | E3: 1600 | F3: =IFERROR(B3*C3*IF(D3="", Parameters!$B$2, D3)/Parameters!$B$6, 0) -> 720464.26 | G3: =F3*IF(E3="", Parameters!$B$2, E3) -> 1.1527428e+09 | H3: =G3*Parameters!$B$4 -> 29971313 | I3: =1/POWER(1+Parameters!$B$5, A3) -> 0.82644628 | J3: =H3*I3 -> 24769680 | K3: =SUM($G$2:G3) -> 2.3054856e+09 | L3: =F3*0.95 -> 684441.04 | M3: =L3*IF(E3="",Parameters!$B$2,E3) -> 1.0951057e+09 | N3: =M3*0.0251 -> 27487152 | O3: =N3*I3 -> 22716655
A4: 3 | B4: 14000000 | C4: 1.952 | D4: 0.82 | E4: 1600 | F4: =IFERROR(B4*C4*IF(D4="", Parameters!$B$2, D4)/Parameters!$B$6, 0) -> 720464.26 | G4: =F4*IF(E4="", Parameters!$B$2, E4) -> 1.1527428e+09 | H4: =G4*Parameters!$B$4 -> 29971313 | I4: =1/POWER(1+Parameters!$B$5, A4) -> 0.7513148 | J4: =H4*I4 -> 22517891 | K4: =SUM($G$2:G4) -> 3.4582284e+09 | L4: =F4*0.95 -> 684441.04 | M4: =L4*IF(E4="",Parameters!$B$2,E4) -> 1.0951057e+09 | N4: =M4*0.0251 -> 27487152 | O4: =N4*I4 -> 20651504
A5: 4 | B5: 14000000 | C5: 1.952 | D5: 0.82 | E5: 1600 | F5: =IFERROR(B5*C5*IF(D5="", Parameters!$B$2, D5)/Parameters!$B$6, 0) -> 720464.26 | G5: =F5*IF(E5="", Parameters!$B$2, E5) -> 1.1527428e+09 | H5: =G5*Parameters!$B$4 -> 29971313 | I5: =1/POWER(1+Parameters!$B$5, A5) -> 0.68301346 | J5: =H5*I5 -> 20470810 | K5: =SUM($G$2:G5) -> 4.6109712e+09 | L5: =F5*0.95 -> 684441.04 | M5: =L5*IF(E5="",Parameters!$B$2,E5) -> 1.0951057e+09 | N5: =M5*0.0251 -> 27487152 | O5: =N5*I5 -> 18774095
A6: 5 | B6: 14000000 | C6: 1.952 | D6: 0.82 | E6: 1600 | F6: =IFERROR(B6*C6*IF(D6="", Parameters!$B$2, D6)/Parameters!$B$6, 0) -> 720464.26 | G6: =F6*IF(E6="", Parameters!$B$2, E6) -> 1.1527428e+09 | H6: =G6*Parameters!$B$4 -> 29971313 | I6: =1/POWER(1+Parameters!$B$5, A6) -> 0.62092132 | J6: =H6*I6 -> 18609827 | K6: =SUM($G$2:G6) -> 5.7637141e+09 | L6: =F6*0.95 -> 684441.04 | M6: =L6*IF(E6="",Parameters!$B$2,E6) -> 1.0951057e+09 | N6: =M6*0.0251 -> 27487152 | O6: =N6*I6 -> 17067359
A7: 6 | B7: 14000000 | C7: 1.952 | D7: 0.82 | E7: 1600 | F7: =IFERROR(B7*C7*IF(D7="", Parameters!$B$2, D7)/Parameters!$B$6, 0) -> 720464.26 | G7: =F7*IF(E7="", Parameters!$B$2, E7) -> 1.1527428e+09 | H7: =G7*Parameters!$B$4 -> 29971313 | I7: =1/POWER(1+Parameters!$B$5, A7) -> 0.56447393 | J7: =H7*I7 -> 16918025 | K7: =SUM($G$2:G7) -> 6.9164569e+09 | L7: =F7*0.95 -> 684441.04 | M7: =L7*IF(E7="",Parameters!$B$2,E7) -> 1.0951057e+09 | N7: =M7*0.0251 -> 27487152 | O7: =N7*I7 -> 15515781
A8: 7 | B8: 14000000 | C8: 1.952 | D8: 0.82 | E8: 1600 | F8: =IFERROR(B8*C8*IF(D8="", Parameters!$B$2, D8)/Parameters!$B$6, 0) -> 720464.26 | G8: =F8*IF(E8="", Parameters!$B$2, E8) -> 1.1527428e+09 | H8: =G8*Parameters!$B$4 -> 29971313 | I8: =1/POWER(1+Parameters!$B$5, A8) -> 0.51315812 | J8: =H8*I8 -> 15380023 | K8: =SUM($G$2:G8) -> 8.0691997e+09 | L8: =F8*0.95 -> 684441.04 | M8: =L8*IF(E8="",Parameters!$B$2,E8) -> 1.0951057e+09 | N8: =M8*0.0251 -> 27487152 | O8: =N8*I8 -> 14105255
A9: 8 | B9: 14000000 | C9: 1.952 | D9: 0.82 | E9: 1600 | F9: =IFERROR(B9*C9*IF(D9="", Parameters!$B$2, D9)/Parameters!$B$6, 0) -> 720464.26 | G9: =F9*IF(E9="", Parameters!$B$2, E9) -> 1.1527428e+09 | H9: =G9*Parameters!$B$4 -> 29971313 | I9: =1/POWER(1+Parameters!$B$5, A9) -> 0.46650738 | J9: =H9*I9 -> 13981839 | K9: =SUM($G$2:G9) -> 9.2219425e+09 | L9: =F9*0.95 -> 684441.04 | M9: =L9*IF(E9="",Parameters!$B$2,E9) -> 1.0951057e+09 | N9: =M9*0.0251 -> 27487152 | O9: =N9*I9 -> 12822959
A10: 9 | B10: 14000000 | C10: 1.952 | D10: 0.82 | E10: 1600 | F10: =IFERROR(B10*C10*IF(D10="", Parameters!$B$2, D10)/Parameters!$B$6, 0) -> 720464.26 | G10: =F10*IF(E10="", Parameters!$B$2, E10) -> 1.1527428e+09 | H10: =G10*Parameters!$B$4 -> 29971313 | I10: =1/POWER(1+Parameters!$B$5, A10) -> 0.42409762 | J10: =H10*I10 -> 12710762 | K10: =SUM($G$2:G10) -> 1.0374685e+10 | L10: =F10*0.95 -> 684441.04 | M10: =L10*IF(E10="",Parameters!$B$2,E10) -> 1.0951057e+09 | N10: =M10*0.0251 -> 27487152 | O10: =N10*I10 -> 11657236
A11: 10 | B11: 14000000 | C11: 1.952 | D11: 0.82 | E11: 1600 | F11: =IFERROR(B11*C11*IF(D11="", Parameters!$B$2, D11)/Parameters!$B$6, 0) -> 720464.26 | G11: =F11*IF(E11="", Parameters!$B$2, E11) -> 1.1527428e+09 | H11: =G11*Parameters!$B$4 -> 29971313 | I11: =1/POWER(1+Parameters!$B$5, A11) -> 0.38554329 | J11: =H11*I11 -> 11555239 | K11: =SUM($G$2:G11) -> 1.1527428e+10 | L11: =F11*0.95 -> 684441.04 | M11: =L11*IF(E11="",Parameters!$B$2,E11) -> 1.0951057e+09 | N11: =M11*0.0251 -> 27487152 | O11: =N11*I11 -> 10597487
A12: 11 | B12: 14000000 | C12: 1.952 | D12: 0.82 | E12: 1600 | F12: =IFERROR(B12*C12*IF(D12="", Parameters!$B$2, D12)/Parameters!$B$6, 0) -> 720464.26 | G12: =F12*IF(E12="", Parameters!$B$2, E12) -> 1.1527428e+09 | H12: =G12*Parameters!$B$4 -> 29971313 | I12: =1/POWER(1+Parameters!$B$5, A12) -> 0.3504939 | J12: =H12*I12 -> 10504762 | K12: =SUM($G$2:G12) -> 1.2680171e+10 | L12: =F12*0.95 -> 684441.04 | M12: =L12*IF(E12="",Parameters!$B$2,E12) -> 1.0951057e+09 | N12: =M12*0.0251 -> 27487152 | O12: =N12*I12 -> 9634079.2
A13: 12 | B13: 14000000 | C13: 1.952 | D13: 0.82 | E13: 1600 | F13: =IFERROR(B13*C13*IF(D13="", Parameters!$B$2, D13)/Parameters!$B$6, 0) -> 720464.26 | G13: =F13*IF(E13="", Parameters!$B$2, E13) -> 1.1527428e+09 | H13: =G13*Parameters!$B$4 -> 29971313 | I13: =1/POWER(1+Parameters!$B$5, A13) -> 0.31863082 | J13: =H13*I13 -> 9549784 | K13: =SUM($G$2:G13) -> 1.3832914e+10 | L13: =F13*0.95 -> 684441.04 | M13: =L13*IF(E13="",Parameters!$B$2,E13) -> 1.0951057e+09 | N13: =M13*0.0251 -> 27487152 | O13: =N13*I13 -> 8758253.8
... A34: 33 | B34: 14000000 | C34: 1.952 | D34: 0.82 | E34: 1600 | F34: =IFERROR(B34*C34*IF(D34="", Parameters!$B$2, D34)/Parameters!$B$6, 0) -> 720464.26 | G34: =F34*IF(E34="", Parameters!$B$2, E34) -> 1.1527428e+09 | H34: =G34*Parameters!$B$4 -> 29971313 | I34: =1/POWER(1+Parameters!$B$5, A34) -> 0.043056764 | J34: =H34*I34 -> 1290467.8 | K34: =SUM($G$2:G34) -> 3.8040513e+10 | L34: =F34*0.95 -> 684441.04 | M34: =L34*IF(E34="",Parameters!$B$2,E34) -> 1.0951057e+09 | N34: =M34*0.0251 -> 27487152 | O34: =N34*I34 -> 1183507.8
F39: Totals / Key Outputs | G39: =SUM(G2:G34) -> 3.8040513e+10 | H39: =SUM(H2:H34) -> 9.8905333e+08 | J39: =SUM(J2:J34) -> 2.8680845e+08 | O39: =SUM(O2:O34) -> 2.6303644e+08
F40: Total Revenue (USD) | G40: =G39 -> 3.8040513e+10
F41: Total Severance Tax (USD) | G41: =H39 -> 9.8905333e+08
F42: PV(Severance Tax) (USD) | G42: =J39 -> 2.8680845e+08

Sheet schedule_3
A1: Year | B1: Ore (t) | C1: Grade (g/t) | D1: Recovery (override, optional) | E1: Metal Price (override, optional) | F1: Metal Produced (oz) | G1: Revenue (USD) | H1: Severance Tax (USD) | I1: Discount Factor | J1: PV(Severance Tax) (USD) | K1: Cumulative Revenue (USD) | L1: Payable Metal (oz) | M1: NSR ($) | N1: Royalty ($) | O1: PV(Royalty)
A2: 1 | B2: 15000000 | C2: 1.941 | D2: 0.82 | E2: 1600 | F2: =IFERROR(B2*C2*IF(D2="", Parameters!$B$2, D2)/Parameters!$B$6, 0) -> 767576 | G2: =F2*IF(E2="", Parameters!$B$2, E2) -> 1.2281216e+09 | H2: =G2*Parameters!$B$4 -> 31931161 | I2: =1/POWER(1+Parameters!$B$5, A2) -> 0.90909091 | J2: =H2*I2 -> 29028329 | K2: =SUM($G$2:G2) -> 1.2281216e+09 | L2: =F2*0.95 -> 729197.2 | M2: =L2*IF(E2="",Parameters!$B$2,E2) -> 1.1667155e+09 | N2: =M2*0.0251 -> 29284559 | O2: =N2*I2 -> 26622327
A3: 2 | B3: 15000000 | C3: 1.941 | D3: 0.82 | E3: 1600 | F3: =IFERROR(B3*C3*IF(D3="", Parameters!$B$2, D3)/Parameters!$B$6, 0) -> 767576 | G3: =F3*IF(E3="", Parameters!$B$2, E3) -> 1.2281216e+09 | H3: =G3*Parameters!$B$4 -> 31931161 | I3: =1/POWER(1+Parameters!$B$5, A3) -> 0.82644628 | J3: =H3*I3 -> 26389390 | K3: =SUM($G$2:G3) -> 2.4562432e+09 | L3: =F3*0.95 -> 729197.2 | M3: =L3*IF(E3="",Parameters!$B$2,E3) -> 1.1667155e+09 | N3: =M3*0.0251 -> 29284559 | O3: =N3*I3 -> 24202115
A4: 3 | B4: 15000000 | C4: 1.941 | D4: 0.82 | E4: 1600 | F4: =IFERROR(B4*C4*IF(D4="", Parameters!$B$2, D4)/Parameters!$B$6, 0) -> 767576 | G4: =F4*IF(E4="", Parameters!$B$2, E4) -> 1.2281216e+09 | H4: =G4*Parameters!$B$4 -> 31931161 | I4: =1/POWER(1+Parameters!$B$5, A4) -> 0.7513148 | J4: =H4*I4 -> 23990354 | K4: =SUM($G$2:G4) -> 3.6843648e+09 | L4: =F4*0.95 -> 729197.2 | M4: =L4*IF(E4="",Parameters!$B$2,E4) -> 1.1667155e+09 | N4: =M4*0.0251 -> 29284559 | O4: =N4*I4 -> 22001923
A5: 4 | B5: 15000000 | C5: 1.941 | D5: 0.82 | E5: 1600 | F5: =IFERROR(B5*C5*IF(D5="", Parameters!$B$2, D5)/Parameters!$B$6, 0) -> 767576 | G5: =F5*IF(E5="", Parameters!$B$2, E5) -> 1.2281216e+09 | H5: =G5*Parameters!$B$4 -> 31931161 | I5: =1/POWER(1+Parameters!$B$5, A5) -> 0.68301346 | J5: =H5*I5 -> 21809413 | K5: =SUM($G$2:G5) -> 4.9124864e+09 | L5: =F5*0.95 -> 729197.2 | M5: =L5*IF(E5="",Parameters!$B$2,E5) -> 1.1667155e+09 | N5: =M5*0.0251 -> 29284559 | O5: =N5*I5 -> 20001748
A6: 5 | B6: 15000000 | C6: 1.941 | D6: 0.82 | E6: 1600 | F6: =IFERROR(B6*C6*IF(D6="", Parameters!$B$2, D6)/Parameters!$B$6, 0) -> 767576 | G6: =F6*IF(E6="", Parameters!$B$2, E6) -> 1.2281216e+09 | H6: =G6*Parameters!$B$4 -> 31931161 | I6: =1/POWER(1+Parameters!$B$5, A6) -> 0.62092132 | J6: =H6*I6 -> 19826739 | K6: =SUM($G$2:G6) -> 6.140608e+09 | L6: =F6*0.95 -> 729197.2 | M6: =L6*IF(E6="",Parameters!$B$2,E6) -> 1.1667155e+09 | N6: =M6*0.0251 -> 29284559 | O6: =N6*I6 -> 18183407
A7: 6 | B7: 15000000 | C7: 1.941 | D7: 0.82 | E7: 1600 | F7: =IFERROR(B7*C7*IF(D7="", Parameters!$B$2, D7)/Parameters!$B$6, 0) -> 767576 | G7: =F7*IF(E7="", Parameters!$B$2, E7) -> 1.2281216e+09 | H7: =G7*Parameters!$B$4 -> 31931161 | I7: =1/POWER(1+Parameters!$B$5, A7) -> 0.56447393 | J7: =H7*I7 -> 18024308 | K7: =SUM($G$2:G7) -> 7.3687296e+09 | L7: =F7*0.95 -> 729197.2 | M7: =L7*IF(E7="",Parameters!$B$2,E7) -> 1.1667155e+09 | N7: =M7*0.0251 -> 29284559 | O7: =N7*I7 -> 16530370
A8: 7 | B8: 15000000 | C8: 1.941 | D8: 0.82 | E8: 1600 | F8: =IFERROR(B8*C8*IF(D8="", Parameters!$B$2, D8)/Parameters!$B$6, 0) -> 767576 | G8: =F8*IF(E8="", Parameters!$B$2, E8) -> 1.2281216e+09 | H8: =G8*Parameters!$B$4 -> 31931161 | I8: =1/POWER(1+Parameters!$B$5, A8) -> 0.51315812 | J8: =H8*I8 -> 16385735 | K8: =SUM($G$2:G8) -> 8.5968512e+09 | L8: =F8*0.95 -> 729197.2 | M8: =L8*IF(E8="",Parameters!$B$2,E8) -> 1.1667155e+09 | N8: =M8*0.0251 -> 29284559 | O8: =N8*I8 -> 15027609
A9: 8 | B9: 15000000 | C9: 1.941 | D9: 0.82 | E9: 1600 | F9: =IFERROR(B9*C9*IF(D9="", Parameters!$B$2, D9)/Parameters!$B$6, 0) -> 767576 | G9: =F9*IF(E9="", Parameters!$B$2, E9) -> 1.2281216e+09 | H9: =G9*Parameters!$B$4 -> 31931161 | I9: =1/POWER(1+Parameters!$B$5, A9) -> 0.46650738 | J9: =H9*I9 -> 14896122 | K9: =SUM($G$2:G9) -> 9.8249728e+09 | L9: =F9*0.95 -> 729197.2 | M9: =L9*IF(E9="",Parameters!$B$2,E9) -> 1.1667155e+09 | N9: =M9*0.0251 -> 29284559 | O9: =N9*I9 -> 13661463
A10: 9 | B10: 15000000 | C10: 1.941 | D10: 0.82 | E10: 1600 | F10: =IFERROR(B10*C10*IF(D10="", Parameters!$B$2, D10)/Parameters!$B$6, 0) -> 767576 | G10: =F10*IF(E10="", Parameters!$B$2, E10) -> 1.2281216e+09 | H10: =G10*Parameters!$B$4 -> 31931161 | I10: =1/POWER(1+Parameters!$B$5, A10) -> 0.42409762 | J10: =H10*I10 -> 13541930 | K10: =SUM($G$2:G10) -> 1.1053094e+10 | L10: =F10*0.95 -> 729197.2 | M10: =L10*IF(E10="",Parameters!$B$2,E10) -> 1.1667155e+09 | N10: =M10*0.0251 -> 29284559 | O10: =N10*I10 -> 12419512
A11: 10 | B11: 15000000 | C11: 1.941 | D11: 0.82 | E11: 1600 | F11: =IFERROR(B11*C11*IF(D11="", Parameters!$B$2, D11)/Parameters!$B$6, 0) -> 767576 | G11: =F11*IF(E11="", Parameters!$B$2, E11) -> 1.2281216e+09 | H11: =G11*Parameters!$B$4 -> 31931161 | I11: =1/POWER(1+Parameters!$B$5, A11) -> 0.38554329 | J11: =H11*I11 -> 12310845 | K11: =SUM($G$2:G11) -> 1.2281216e+10 | L11: =F11*0.95 -> 729197.2 | M11: =L11*IF(E11="",Parameters!$B$2,E11) -> 1.1667155e+09 | N11: =M11*0.0251 -> 29284559 | O11: =N11*I11 -> 11290465
A12: 11 | B12: 15000000 | C12: 1.941 | D12: 0.82 | E12: 1600 | F12: =IFERROR(B12*C12*IF(D12="", Parameters!$B$2, D12)/Parameters!$B$6, 0) -> 767576 | G12: =F12*IF(E12="", Parameters!$B$2, E12) -> 1.2281216e+09 | H12: =G12*Parameters!$B$4 -> 31931161 | I12: =1/POWER(1+Parameters!$B$5, A12) -> 0.3504939 | J12: =H12*I12 -> 11191677 | K12: =SUM($G$2:G12) -> 1.3509338e+10 | L12: =F12*0.95 -> 729197.2 | M12: =L12*IF(E12="",Parameters!$B$2,E12) -> 1.1667155e+09 | N12: =M12*0.0251 -> 29284559 | O12: =N12*I12 -> 10264059
A13: 12 | B13: 15000000 | C13: 1.941 | D13: 0.82 | E13: 1600 | F13: =IFERROR(B13*C13*IF(D13="", Parameters!$B$2, D13)/Parameters!$B$6, 0) -> 767576 | G13: =F13*IF(E13="", Parameters!$B$2, E13) -> 1.2281216e+09 | H13: =G13*Parameters!$B$4 -> 31931161 | I13: =1/POWER(1+Parameters!$B$5, A13) -> 0.31863082 | J13: =H13*I13 -> 10174252 | K13: =SUM($G$2:G13) -> 1.4737459e+10 | L13: =F13*0.95 -> 729197.2 | M13: =L13*IF(E13="",Parameters!$B$2,E13) -> 1.1667155e+09 | N13: =M13*0.0251 -> 29284559 | O13: =N13*I13 -> 9330963.1
... A33: 32 | B33: 15000000 | C33: 1.941 | D33: 0.82 | E33: 1600 | F33: =IFERROR(B33*C33*IF(D33="", Parameters!$B$2, D33)/Parameters!$B$6, 0) -> 767576 | G33: =F33*IF(E33="", Parameters!$B$2, E33) -> 1.2281216e+09 | H33: =G33*Parameters!$B$4 -> 31931161 | I33: =1/POWER(1+Parameters!$B$5, A33) -> 0.047362441 | J33: =H33*I33 -> 1512337.7 | K33: =SUM($G$2:G33) -> 3.9299891e+10 | L33: =F33*0.95 -> 729197.2 | M33: =L33*IF(E33="",Parameters!$B$2,E33) -> 1.1667155e+09 | N33: =M33*0.0251 -> 29284559 | O33: =N33*I33 -> 1386988.2
F39: Totals / Key Outputs | G39: =SUM(G2:G33) -> 3.9299891e+10 | H39: =SUM(H2:H33) -> 1.0217972e+09 | J39: =SUM(J2:J33) -> 3.0418824e+08 | O39: =SUM(O2:O33) -> 2.7897571e+08
F40: Total Revenue (USD) | G40: =G39 -> 3.9299891e+10
F41: Total Severance Tax (USD) | G41: =H39 -> 1.0217972e+09
F42: PV(Severance Tax) (USD) | G42: =J39 -> 3.0418824e+08

Sheet schedule_4
A1: Year | B1: Ore (t) | C1: Grade (g/t) | D1: Recovery (override, optional) | E1: Metal Price (override, optional) | F1: Metal Produced (oz) | G1: Revenue (USD) | H1: Severance Tax (USD) | I1: Discount Factor | J1: PV(Severance Tax) (USD) | K1: Cumulative Revenue (USD) | L1: Payable Metal (oz) | M1: NSR ($) | N1: Royalty ($) | O1: PV(Royalty)
A2: 1 | B2: 16000000 | C2: 1.959 | D2: 0.82 | E2: 1600 | F2: =IFERROR(B2*C2*IF(D2="", Parameters!$B$2, D2)/Parameters!$B$6, 0) -> 826340.44 | G2: =F2*IF(E2="", Parameters!$B$2, E2) -> 1.3221447e+09 | H2: =G2*Parameters!$B$4 -> 34375762 | I2: =1/POWER(1+Parameters!$B$5, A2) -> 0.90909091 | J2: =H2*I2 -> 31250693 | K2: =SUM($G$2:G2) -> 1.3221447e+09 | L2: =F2*0.95 -> 785023.42 | M2: =L2*IF(E2="",Parameters!$B$2,E2) -> 1.2560375e+09 | N2: =M2*0.0251 -> 31526541 | O2: =N2*I2 -> 28660491
A3: 2 | B3: 16000000 | C3: 1.959 | D3: 0.82 | E3: 1600 | F3: =IFERROR(B3*C3*IF(D3="", Parameters!$B$2, D3)/Parameters!$B$6, 0) -> 826340.44 | G3: =F3*IF(E3="", Parameters!$B$2, E3) -> 1.3221447e+09 | H3: =G3*Parameters!$B$4 -> 34375762 | I3: =1/POWER(1+Parameters!$B$5, A3) -> 0.82644628 | J3: =H3*I3 -> 28409721 | K3: =SUM($G$2:G3) -> 2.6442894e+09 | L3: =F3*0.95 -> 785023.42 | M3: =L3*IF(E3="",Parameters!$B$2,E3) -> 1.2560375e+09 | N3: =M3*0.0251 -> 31526541 | O3: =N3*I3 -> 26054992
A4: 3 | B4: 16000000 | C4: 1.959 | D4: 0.82 | E4: 1600 | F4: =IFERROR(B4*C4*IF(D4="", Parameters!$B$2, D4)/Parameters!$B$6, 0) -> 826340.44 | G4: =F4*IF(E4="", Parameters!$B$2, E4) -> 1.3221447e+09 | H4: =G4*Parameters!$B$4 -> 34375762 | I4: =1/POWER(1+Parameters!$B$5, A4) -> 0.7513148 | J4: =H4*I4 -> 25827019 | K4: =SUM($G$2:G4) -> 3.9664341e+09 | L4: =F4*0.95 -> 785023.42 | M4: =L4*IF(E4="",Parameters!$B$2,E4) -> 1.2560375e+09 | N4: =M4*0.0251 -> 31526541 | O4: =N4*I4 -> 23686357
A5: 4 | B5: 16000000 | C5: 1.959 | D5: 0.82 | E5: 1600 | F5: =IFERROR(B5*C5*IF(D5="", Parameters!$B$2, D5)/Parameters!$B$6, 0) -> 826340.44 | G5: =F5*IF(E5="", Parameters!$B$2, E5) -> 1.3221447e+09 | H5: =G5*Parameters!$B$4 -> 34375762 | I5: =1/POWER(1+Parameters!$B$5, A5) -> 0.68301346 | J5: =H5*I5 -> 23479108 | K5: =SUM($G$2:G5) -> 5.2885788e+09 | L5: =F5*0.95 -> 785023.42 | M5: =L5*IF(E5="",Parameters!$B$2,E5) -> 1.2560375e+09 | N5: =M5*0.0251 -> 31526541 | O5: =N5*I5 -> 21533051
A6: 5 | B6: 16000000 | C6: 1.959 | D6: 0.82 | E6: 1600 | F6: =IFERROR(B6*C6*IF(D6="", Parameters!$B$2, D6)/Parameters!$B$6, 0) -> 826340.44 | G6: =F6*IF(E6="", Parameters!$B$2, E6) -> 1.3221447e+09 | H6: =G6*Parameters!$B$4 -> 34375762 | I6: =1/POWER(1+Parameters!$B$5, A6) -> 0.62092132 | J6: =H6*I6 -> 21344644 | K6: =SUM($G$2:G6) -> 6.6107236e+09 | L6: =F6*0.95 -> 785023.42 | M6: =L6*IF(E6="",Parameters!$B$2,E6) -> 1.2560375e+09 | N6: =M6*0.0251 -> 31526541 | O6: =N6*I6 -> 19575501
A7: 6 | B7: 16000000 | C7: 1.959 | D7: 0.82 | E7: 1600 | F7: =IFERROR(B7*C7*IF(D7="", Parameters!$B$2, D7)/Parameters!$B$6, 0) -> 826340.44 | G7: =F7*IF(E7="", Parameters!$B$2, E7) -> 1.3221447e+09 | H7: =G7*Parameters!$B$4 -> 34375762 | I7: =1/POWER(1+Parameters!$B$5, A7) -> 0.56447393 | J7: =H7*I7 -> 19404222 | K7: =SUM($G$2:G7) -> 7.9328683e+09 | L7: =F7*0.95 -> 785023.42 | M7: =L7*IF(E7="",Parameters!$B$2,E7) -> 1.2560375e+09 | N7: =M7*0.0251 -> 31526541 | O7: =N7*I7 -> 17795910
A8: 7 | B8: 16000000 | C8: 1.959 | D8: 0.82 | E8: 1600 | F8: =IFERROR(B8*C8*IF(D8="", Parameters!$B$2, D8)/Parameters!$B$6, 0) -> 826340.44 | G8: =F8*IF(E8="", Parameters!$B$2, E8) -> 1.3221447e+09 | H8: =G8*Parameters!$B$4 -> 34375762 | I8: =1/POWER(1+Parameters!$B$5, A8) -> 0.51315812 | J8: =H8*I8 -> 17640202 | K8: =SUM($G$2:G8) -> 9.255013e+09 | L8: =F8*0.95 -> 785023.42 | M8: =L8*IF(E8="",Parameters!$B$2,E8) -> 1.2560375e+09 | N8: =M8*0.0251 -> 31526541 | O8: =N8*I8 -> 16178100
A9: 8 | B9: 16000000 | C9: 1.959 | D9: 0.82 | E9: 1600 | F9: =IFERROR(B9*C9*IF(D9="", Parameters!$B$2, D9)/Parameters!$B$6, 0) -> 826340.44 | G9: =F9*IF(E9="", Parameters!$B$2, E9) -> 1.3221447e+09 | H9: =G9*Parameters!$B$4 -> 34375762 | I9: =1/POWER(1+Parameters!$B$5, A9) -> 0.46650738 | J9: =H9*I9 -> 16036547 | K9: =SUM($G$2:G9) -> 1.0577158e+10 | L9: =F9*0.95 -> 785023.42 | M9: =L9*IF(E9="",Parameters!$B$2,E9) -> 1.2560375e+09 | N9: =M9*0.0251 -> 31526541 | O9: =N9*I9 -> 14707364
A10: 9 | B10: 16000000 | C10: 1.959 | D10: 0.82 | E10: 1600 | F10: =IFERROR(B10*C10*IF(D10="", Parameters!$B$2, D10)/Parameters!$B$6, 0) -> 826340.44 | G10: =F10*IF(E10="", Parameters!$B$2, E10) -> 1.3221447e+09 | H10: =G10*Parameters!$B$4 -> 34375762 | I10: =1/POWER(1+Parameters!$B$5, A10) -> 0.42409762 | J10: =H10*I10 -> 14578679 | K10: =SUM($G$2:G10) -> 1.1899302e+10 | L10: =F10*0.95 -> 785023.42 | M10: =L10*IF(E10="",Parameters!$B$2,E10) -> 1.2560375e+09 | N10: =M10*0.0251 -> 31526541 | O10: =N10*I10 -> 13370331
A11: 10 | B11: 16000000 | C11: 1.959 | D11: 0.82 | E11: 1600 | F11: =IFERROR(B11*C11*IF(D11="", Parameters!$B$2, D11)/Parameters!$B$6, 0) -> 826340.44 | G11: =F11*IF(E11="", Parameters!$B$2, E11) -> 1.3221447e+09 | H11: =G11*Parameters!$B$4 -> 34375762 | I11: =1/POWER(1+Parameters!$B$5, A11) -> 0.38554329 | J11: =H11*I11 -> 13253345 | K11: =SUM($G$2:G11) -> 1.3221447e+10 | L11: =F11*0.95 -> 785023.42 | M11: =L11*IF(E11="",Parameters!$B$2,E11) -> 1.2560375e+09 | N11: =M11*0.0251 -> 31526541 | O11: =N11*I11 -> 12154846
A12: 11 | B12: 16000000 | C12: 1.959 | D12: 0.82 | E12: 1600 | F12: =IFERROR(B12*C12*IF(D12="", Parameters!$B$2, D12)/Parameters!$B$6, 0) -> 826340.44 | G12: =F12*IF(E12="", Parameters!$B$2, E12) -> 1.3221447e+09 | H12: =G12*Parameters!$B$4 -> 34375762 | I12: =1/POWER(1+Parameters!$B$5, A12) -> 0.3504939 | J12: =H12*I12 -> 12048495 | K12: =SUM($G$2:G12) -> 1.4543592e+10 | L12: =F12*0.95 -> 785023.42 | M12: =L12*IF(E12="",Parameters!$B$2,E12) -> 1.2560375e+09 | N12: =M12*0.0251 -> 31526541 | O12: =N12*I12 -> 11049860
A13: 12 | B13: 16000000 | C13: 1.959 | D13: 0.82 | E13: 1600 | F13: =IFERROR(B13*C13*IF(D13="", Parameters!$B$2, D13)/Parameters!$B$6, 0) -> 826340.44 | G13: =F13*IF(E13="", Parameters!$B$2, E13) -> 1.3221447e+09 | H13: =G13*Parameters!$B$4 -> 34375762 | I13: =1/POWER(1+Parameters!$B$5, A13) -> 0.31863082 | J13: =H13*I13 -> 10953177 | K13: =SUM($G$2:G13) -> 1.5865737e+10 | L13: =F13*0.95 -> 785023.42 | M13: =L13*IF(E13="",Parameters!$B$2,E13) -> 1.2560375e+09 | N13: =M13*0.0251 -> 31526541 | O13: =N13*I13 -> 10045327
... A30: 29 | B30: 16000000 | C30: 1.959 | D30: 0.82 | E30: 1600 | F30: =IFERROR(B30*C30*IF(D30="", Parameters!$B$2, D30)/Parameters!$B$6, 0) -> 826340.44 | G30: =F30*IF(E30="", Parameters!$B$2, E30) -> 1.3221447e+09 | H30: =G30*Parameters!$B$4 -> 34375762 | I30: =1/POWER(1+Parameters!$B$5, A30) -> 0.063039409 | J30: =H30*I30 -> 2167027.7 | K30: =SUM($G$2:G30) -> 3.8342197e+10 | L30: =F30*0.95 -> 785023.42 | M30: =L30*IF(E30="",Parameters!$B$2,E30) -> 1.2560375e+09 | N30: =M30*0.0251 -> 31526541 | O30: =N30*I30 -> 1987414.5
F39: Totals / Key Outputs | G39: =SUM(G2:G33) -> 3.8342197e+10 | H39: =SUM(H2:H33) -> 9.9689711e+08 | J39: =SUM(J2:J30) -> 3.2208735e+08 | O39: =SUM(O2:O30) -> 2.9539126e+08
F40: Total Revenue (USD) | G40: =G39 -> 3.8342197e+10
F41: Total Severance Tax (USD) | G41: =H39 -> 9.9689711e+08
F42: PV(Severance Tax) (USD) | G42: =J39 -> 3.2208735e+08

Sheet schedule_5
A1: Year | B1: Ore (t) | C1: Grade (g/t) | D1: Recovery (override, optional) | E1: Metal Price (override, optional) | F1: Metal Produced (oz) | G1: Revenue (USD) | H1: Severance Tax (USD) | I1: Discount Factor | J1: PV(Severance Tax) (USD) | K1: Cumulative Revenue (USD) | L1: Payable Metal (oz) | M1: NSR ($) | N1: Royalty ($) | O1: PV(Royalty)
A2: 1 | B2: 17000000 | C2: 2.02 | D2: 0.82 | E2: 1600 | F2: =IFERROR(B2*C2*IF(D2="", Parameters!$B$2, D2)/Parameters!$B$6, 0) -> 905325.77 | G2: =F2*IF(E2="", Parameters!$B$2, E2) -> 1.4485212e+09 | H2: =G2*Parameters!$B$4 -> 37661552 | I2: =1/POWER(1+Parameters!$B$5, A2) -> 0.90909091 | J2: =H2*I2 -> 34237774 | K2: =SUM($G$2:G2) -> 1.4485212e+09 | L2: =F2*0.95 -> 860059.48 | M2: =L2*IF(E2="",Parameters!$B$2,E2) -> 1.3760952e+09 | N2: =M2*0.0251 -> 34539989 | O2: =N2*I2 -> 31399990
A3: 2 | B3: 17000000 | C3: 2.02 | D3: 0.82 | E3: 1600 | F3: =IFERROR(B3*C3*IF(D3="", Parameters!$B$2, D3)/Parameters!$B$6, 0) -> 905325.77 | G3: =F3*IF(E3="", Parameters!$B$2, E3) -> 1.4485212e+09 | H3: =G3*Parameters!$B$4 -> 37661552 | I3: =1/POWER(1+Parameters!$B$5, A3) -> 0.82644628 | J3: =H3*I3 -> 31125250 | K3: =SUM($G$2:G3) -> 2.8970425e+09 | L3: =F3*0.95 -> 860059.48 | M3: =L3*IF(E3="",Parameters!$B$2,E3) -> 1.3760952e+09 | N3: =M3*0.0251 -> 34539989 | O3: =N3*I3 -> 28545445
A4: 3 | B4: 17000000 | C4: 2.02 | D4: 0.82 | E4: 1600 | F4: =IFERROR(B4*C4*IF(D4="", Parameters!$B$2, D4)/Parameters!$B$6, 0) -> 905325.77 | G4: =F4*IF(E4="", Parameters!$B$2, E4) -> 1.4485212e+09 | H4: =G4*Parameters!$B$4 -> 37661552 | I4: =1/POWER(1+Parameters!$B$5, A4) -> 0.7513148 | J4: =H4*I4 -> 28295681 | K4: =SUM($G$2:G4) -> 4.3455637e+09 | L4: =F4*0.95 -> 860059.48 | M4: =L4*IF(E4="",Parameters!$B$2,E4) -> 1.3760952e+09 | N4: =M4*0.0251 -> 34539989 | O4: =N4*I4 -> 25950405
A5: 4 | B5: 17000000 | C5: 2.02 | D5: 0.82 | E5: 1600 | F5: =IFERROR(B5*C5*IF(D5="", Parameters!$B$2, D5)/Parameters!$B$6, 0) -> 905325.77 | G5: =F5*IF(E5="", Parameters!$B$2, E5) -> 1.4485212e+09 | H5: =G5*Parameters!$B$4 -> 37661552 | I5: =1/POWER(1+Parameters!$B$5, A5) -> 0.68301346 | J5: =H5*I5 -> 25723347 | K5: =SUM($G$2:G5) -> 5.7940849e+09 | L5: =F5*0.95 -> 860059.48 | M5: =L5*IF(E5="",Parameters!$B$2,E5) -> 1.3760952e+09 | N5: =M5*0.0251 -> 34539989 | O5: =N5*I5 -> 23591277
A6: 5 | B6: 17000000 | C6: 2.02 | D6: 0.82 | E6: 1600 | F6: =IFERROR(B6*C6*IF(D6="", Parameters!$B$2, D6)/Parameters!$B$6, 0) -> 905325.77 | G6: =F6*IF(E6="", Parameters!$B$2, E6) -> 1.4485212e+09 | H6: =G6*Parameters!$B$4 -> 37661552 | I6: =1/POWER(1+Parameters!$B$5, A6) -> 0.62092132 | J6: =H6*I6 -> 23384861 | K6: =SUM($G$2:G6) -> 7.2426061e+09 | L6: =F6*0.95 -> 860059.48 | M6: =L6*IF(E6="",Parameters!$B$2,E6) -> 1.3760952e+09 | N6: =M6*0.0251 -> 34539989 | O6: =N6*I6 -> 21446615
A7: 6 | B7: 17000000 | C7: 2.02 | D7: 0.82 | E7: 1600 | F7: =IFERROR(B7*C7*IF(D7="", Parameters!$B$2, D7)/Parameters!$B$6, 0) -> 905325.77 | G7: =F7*IF(E7="", Parameters!$B$2, E7) -> 1.4485212e+09 | H7: =G7*Parameters!$B$4 -> 37661552 | I7: =1/POWER(1+Parameters!$B$5, A7) -> 0.56447393 | J7: =H7*I7 -> 21258964 | K7: =SUM($G$2:G7) -> 8.6911274e+09 | L7: =F7*0.95 -> 860059.48 | M7: =L7*IF(E7="",Parameters!$B$2,E7) -> 1.3760952e+09 | N7: =M7*0.0251 -> 34539989 | O7: =N7*I7 -> 19496923
A8: 7 | B8: 17000000 | C8: 2.02 | D8: 0.82 | E8: 1600 | F8: =IFERROR(B8*C8*IF(D8="", Parameters!$B$2, D8)/Parameters!$B$6, 0) -> 905325.77 | G8: =F8*IF(E8="", Parameters!$B$2, E8) -> 1.4485212e+09 | H8: =G8*Parameters!$B$4 -> 37661552 | I8: =1/POWER(1+Parameters!$B$5, A8) -> 0.51315812 | J8: =H8*I8 -> 19326331 | K8: =SUM($G$2:G8) -> 1.0139649e+10 | L8: =F8*0.95 -> 860059.48 | M8: =L8*IF(E8="",Parameters!$B$2,E8) -> 1.3760952e+09 | N8: =M8*0.0251 -> 34539989 | O8: =N8*I8 -> 17724476
A9: 8 | B9: 17000000 | C9: 2.02 | D9: 0.82 | E9: 1600 | F9: =IFERROR(B9*C9*IF(D9="", Parameters!$B$2, D9)/Parameters!$B$6, 0) -> 905325.77 | G9: =F9*IF(E9="", Parameters!$B$2, E9) -> 1.4485212e+09 | H9: =G9*Parameters!$B$4 -> 37661552 | I9: =1/POWER(1+Parameters!$B$5, A9) -> 0.46650738 | J9: =H9*I9 -> 17569392 | K9: =SUM($G$2:G9) -> 1.158817e+10 | L9: =F9*0.95 -> 860059.48 | M9: =L9*IF(E9="",Parameters!$B$2,E9) -> 1.3760952e+09 | N9: =M9*0.0251 -> 34539989 | O9: =N9*I9 -> 16113160
A10: 9 | B10: 17000000 | C10: 2.02 | D10: 0.82 | E10: 1600 | F10: =IFERROR(B10*C10*IF(D10="", Parameters!$B$2, D10)/Parameters!$B$6, 0) -> 905325.77 | G10: =F10*IF(E10="", Parameters!$B$2, E10) -> 1.4485212e+09 | H10: =G10*Parameters!$B$4 -> 37661552 | I10: =1/POWER(1+Parameters!$B$5, A10) -> 0.42409762 | J10: =H10*I10 -> 15972174 | K10: =SUM($G$2:G10) -> 1.3036691e+10 | L10: =F10*0.95 -> 860059.48 | M10: =L10*IF(E10="",Parameters!$B$2,E10) -> 1.3760952e+09 | N10: =M10*0.0251 -> 34539989 | O10: =N10*I10 -> 14648327
A11: 10 | B11: 17000000 | C11: 2.02 | D11: 0.82 | E11: 1600 | F11: =IFERROR(B11*C11*IF(D11="", Parameters!$B$2, D11)/Parameters!$B$6, 0) -> 905325.77 | G11: =F11*IF(E11="", Parameters!$B$2, E11) -> 1.4485212e+09 | H11: =G11*Parameters!$B$4 -> 37661552 | I11: =1/POWER(1+Parameters!$B$5, A11) -> 0.38554329 | J11: =H11*I11 -> 14520159 | K11: =SUM($G$2:G11) -> 1.4485212e+10 | L11: =F11*0.95 -> 860059.48 | M11: =L11*IF(E11="",Parameters!$B$2,E11) -> 1.3760952e+09 | N11: =M11*0.0251 -> 34539989 | O11: =N11*I11 -> 13316661
A12: 11 | B12: 17000000 | C12: 2.02 | D12: 0.82 | E12: 1600 | F12: =IFERROR(B12*C12*IF(D12="", Parameters!$B$2, D12)/Parameters!$B$6, 0) -> 905325.77 | G12: =F12*IF(E12="", Parameters!$B$2, E12) -> 1.4485212e+09 | H12: =G12*Parameters!$B$4 -> 37661552 | I12: =1/POWER(1+Parameters!$B$5, A12) -> 0.3504939 | J12: =H12*I12 -> 13200144 | K12: =SUM($G$2:G12) -> 1.5933734e+10 | L12: =F12*0.95 -> 860059.48 | M12: =L12*IF(E12="",Parameters!$B$2,E12) -> 1.3760952e+09 | N12: =M12*0.0251 -> 34539989 | O12: =N12*I12 -> 12106055
A13: 12 | B13: 17000000 | C13: 2.02 | D13: 0.82 | E13: 1600 | F13: =IFERROR(B13*C13*IF(D13="", Parameters!$B$2, D13)/Parameters!$B$6, 0) -> 905325.77 | G13: =F13*IF(E13="", Parameters!$B$2, E13) -> 1.4485212e+09 | H13: =G13*Parameters!$B$4 -> 37661552 | I13: =1/POWER(1+Parameters!$B$5, A13) -> 0.31863082 | J13: =H13*I13 -> 12000131 | K13: =SUM($G$2:G13) -> 1.7382255e+10 | L13: =F13*0.95 -> 860059.48 | M13: =L13*IF(E13="",Parameters!$B$2,E13) -> 1.3760952e+09 | N13: =M13*0.0251 -> 34539989 | O13: =N13*I13 -> 11005505
... A26: 25 | B26: 17000000 | C26: 2.02 | D26: 0.82 | E26: 1600 | F26: =IFERROR(B26*C26*IF(D26="", Parameters!$B$2, D26)/Parameters!$B$6, 0) -> 905325.77 | G26: =F26*IF(E26="", Parameters!$B$2, E26) -> 1.4485212e+09 | H26: =G26*Parameters!$B$4 -> 37661552 | I26: =1/POWER(1+Parameters!$B$5, A26) -> 0.092295998 | J26: =H26*I26 -> 3476010.5 | K26: =SUM($G$2:G26) -> 3.6213031e+10 | L26: =F26*0.95 -> 860059.48 | M26: =L26*IF(E26="",Parameters!$B$2,E26) -> 1.3760952e+09 | N26: =M26*0.0251 -> 34539989 | O26: =N26*I26 -> 3187902.7
F39: Totals / Key Outputs | G39: =SUM(G2:G33) -> 3.6213031e+10 | H39: =SUM(H2:H33) -> 9.415388e+08 | J39: =SUM(J2:J26) -> 3.4185541e+08 | O39: =SUM(O2:O26) -> 3.1352086e+08
F40: Total Revenue (USD) | G40: =G39 -> 3.6213031e+10
F41: Total Severance Tax (USD) | G41: =H39 -> 9.415388e+08
F42: PV(Severance Tax) (USD) | G42: =J39 -> 3.4185541e+08

Sheet schedule_6
A1: Year | B1: Ore (t) | C1: Grade (g/t) | D1: Recovery (override, optional) | E1: Metal Price (override, optional) | F1: Metal Produced (oz) | G1: Revenue (USD) | H1: Severance Tax (USD) | I1: Discount Factor | J1: PV(Severance Tax) (USD) | K1: Cumulative Revenue (USD) | L1: Payable Metal (oz) | M1: NSR ($) | N1: Royalty ($) | O1: PV(Royalty)
A2: 1 | B2: 18000000 | C2: 1.995 | D2: 0.82 | E2: 1600 | F2: =IFERROR(B2*C2*IF(D2="", Parameters!$B$2, D2)/Parameters!$B$6, 0) -> 946716.61 | G2: =F2*IF(E2="", Parameters!$B$2, E2) -> 1.5147466e+09 | H2: =G2*Parameters!$B$4 -> 39383411 | I2: =1/POWER(1+Parameters!$B$5, A2) -> 0.90909091 | J2: =H2*I2 -> 35803101 | K2: =SUM($G$2:G2) -> 1.5147466e+09 | L2: =F2*0.95 -> 899380.78 | M2: =L2*IF(E2="",Parameters!$B$2,E2) -> 1.4390092e+09 | N2: =M2*0.0251 -> 36119132 | O2: =N2*I2 -> 32835575
A3: 2 | B3: 18000000 | C3: 1.995 | D3: 0.82 | E3: 1600 | F3: =IFERROR(B3*C3*IF(D3="", Parameters!$B$2, D3)/Parameters!$B$6, 0) -> 946716.61 | G3: =F3*IF(E3="", Parameters!$B$2, E3) -> 1.5147466e+09 | H3: =G3*Parameters!$B$4 -> 39383411 | I3: =1/POWER(1+Parameters!$B$5, A3) -> 0.82644628 | J3: =H3*I3 -> 32548273 | K3: =SUM($G$2:G3) -> 3.0294931e+09 | L3: =F3*0.95 -> 899380.78 | M3: =L3*IF(E3="",Parameters!$B$2,E3) -> 1.4390092e+09 | N3: =M3*0.0251 -> 36119132 | O3: =N3*I3 -> 29850522
A4: 3 | B4: 18000000 | C4: 1.995 | D4: 0.82 | E4: 1600 | F4: =IFERROR(B4*C4*IF(D4="", Parameters!$B$2, D4)/Parameters!$B$6, 0) -> 946716.61 | G4: =F4*IF(E4="", Parameters!$B$2, E4) -> 1.5147466e+09 | H4: =G4*Parameters!$B$4 -> 39383411 | I4: =1/POWER(1+Parameters!$B$5, A4) -> 0.7513148 | J4: =H4*I4 -> 29589339 | K4: =SUM($G$2:G4) -> 4.5442397e+09 | L4: =F4*0.95 -> 899380.78 | M4: =L4*IF(E4="",Parameters!$B$2,E4) -> 1.4390092e+09 | N4: =M4*0.0251 -> 36119132 | O4: =N4*I4 -> 27136838
A5: 4 | B5: 18000000 | C5: 1.995 | D5: 0.82 | E5: 1600 | F5: =IFERROR(B5*C5*IF(D5="", Parameters!$B$2, D5)/Parameters!$B$6, 0) -> 946716.61 | G5: =F5*IF(E5="", Parameters!$B$2, E5) -> 1.5147466e+09 | H5: =G5*Parameters!$B$4 -> 39383411 | I5: =1/POWER(1+Parameters!$B$5, A5) -> 0.68301346 | J5: =H5*I5 -> 26899400 | K5: =SUM($G$2:G5) -> 6.0589863e+09 | L5: =F5*0.95 -> 899380.78 | M5: =L5*IF(E5="",Parameters!$B$2,E5) -> 1.4390092e+09 | N5: =M5*0.0251 -> 36119132 | O5: =N5*I5 -> 24669853
A6: 5 | B6: 18000000 | C6: 1.995 | D6: 0.82 | E6: 1600 | F6: =IFERROR(B6*C6*IF(D6="", Parameters!$B$2, D6)/Parameters!$B$6, 0) -> 946716.61 | G6: =F6*IF(E6="", Parameters!$B$2, E6) -> 1.5147466e+09 | H6: =G6*Parameters!$B$4 -> 39383411 | I6: =1/POWER(1+Parameters!$B$5, A6) -> 0.62092132 | J6: =H6*I6 -> 24454000 | K6: =SUM($G$2:G6) -> 7.5737329e+09 | L6: =F6*0.95 -> 899380.78 | M6: =L6*IF(E6="",Parameters!$B$2,E6) -> 1.4390092e+09 | N6: =M6*0.0251 -> 36119132 | O6: =N6*I6 -> 22427139
A7: 6 | B7: 18000000 | C7: 1.995 | D7: 0.82 | E7: 1600 | F7: =IFERROR(B7*C7*IF(D7="", Parameters!$B$2, D7)/Parameters!$B$6, 0) -> 946716.61 | G7: =F7*IF(E7="", Parameters!$B$2, E7) -> 1.5147466e+09 | H7: =G7*Parameters!$B$4 -> 39383411 | I7: =1/POWER(1+Parameters!$B$5, A7) -> 0.56447393 | J7: =H7*I7 -> 22230909 | K7: =SUM($G$2:G7) -> 9.0884794e+09 | L7: =F7*0.95 -> 899380.78 | M7: =L7*IF(E7="",Parameters!$B$2,E7) -> 1.4390092e+09 | N7: =M7*0.0251 -> 36119132 | O7: =N7*I7 -> 20388308
A8: 7 | B8: 18000000 | C8: 1.995 | D8: 0.82 | E8: 1600 | F8: =IFERROR(B8*C8*IF(D8="", Parameters!$B$2, D8)/Parameters!$B$6, 0) -> 946716.61 | G8: =F8*IF(E8="", Parameters!$B$2, E8) -> 1.5147466e+09 | H8: =G8*Parameters!$B$4 -> 39383411 | I8: =1/POWER(1+Parameters!$B$5, A8) -> 0.51315812 | J8: =H8*I8 -> 20209917 | K8: =SUM($G$2:G8) -> 1.0603226e+10 | L8: =F8*0.95 -> 899380.78 | M8: =L8*IF(E8="",Parameters!$B$2,E8) -> 1.4390092e+09 | N8: =M8*0.0251 -> 36119132 | O8: =N8*I8 -> 18534826
A9: 8 | B9: 18000000 | C9: 1.995 | D9: 0.82 | E9: 1600 | F9: =IFERROR(B9*C9*IF(D9="", Parameters!$B$2, D9)/Parameters!$B$6, 0) -> 946716.61 | G9: =F9*IF(E9="", Parameters!$B$2, E9) -> 1.5147466e+09 | H9: =G9*Parameters!$B$4 -> 39383411 | I9: =1/POWER(1+Parameters!$B$5, A9) -> 0.46650738 | J9: =H9*I9 -> 18372652 | K9: =SUM($G$2:G9) -> 1.2117973e+10 | L9: =F9*0.95 -> 899380.78 | M9: =L9*IF(E9="",Parameters!$B$2,E9) -> 1.4390092e+09 | N9: =M9*0.0251 -> 36119132 | O9: =N9*I9 -> 16849842
A10: 9 | B10: 18000000 | C10: 1.995 | D10: 0.82 | E10: 1600 | F10: =IFERROR(B10*C10*IF(D10="", Parameters!$B$2, D10)/Parameters!$B$6, 0) -> 946716.61 | G10: =F10*IF(E10="", Parameters!$B$2, E10) -> 1.5147466e+09 | H10: =G10*Parameters!$B$4 -> 39383411 | I10: =1/POWER(1+Parameters!$B$5, A10) -> 0.42409762 | J10: =H10*I10 -> 16702411 | K10: =SUM($G$2:G10) -> 1.3632719e+10 | L10: =F10*0.95 -> 899380.78 | M10: =L10*IF(E10="",Parameters!$B$2,E10) -> 1.4390092e+09 | N10: =M10*0.0251 -> 36119132 | O10: =N10*I10 -> 15318038
A11: 10 | B11: 18000000 | C11: 1.995 | D11: 0.82 | E11: 1600 | F11: =IFERROR(B11*C11*IF(D11="", Parameters!$B$2, D11)/Parameters!$B$6, 0) -> 946716.61 | G11: =F11*IF(E11="", Parameters!$B$2, E11) -> 1.5147466e+09 | H11: =G11*Parameters!$B$4 -> 39383411 | I11: =1/POWER(1+Parameters!$B$5, A11) -> 0.38554329 | J11: =H11*I11 -> 15184010 | K11: =SUM($G$2:G11) -> 1.5147466e+10 | L11: =F11*0.95 -> 899380.78 | M11: =L11*IF(E11="",Parameters!$B$2,E11) -> 1.4390092e+09 | N11: =M11*0.0251 -> 36119132 | O11: =N11*I11 -> 13925489
A12: 11 | B12: 18000000 | C12: 1.995 | D12: 0.82 | E12: 1600 | F12: =IFERROR(B12*C12*IF(D12="", Parameters!$B$2, D12)/Parameters!$B$6, 0) -> 946716.61 | G12: =F12*IF(E12="", Parameters!$B$2, E12) -> 1.5147466e+09 | H12: =G12*Parameters!$B$4 -> 39383411 | I12: =1/POWER(1+Parameters!$B$5, A12) -> 0.3504939 | J12: =H12*I12 -> 13803645 | K12: =SUM($G$2:G12) -> 1.6662212e+10 | L12: =F12*0.95 -> 899380.78 | M12: =L12*IF(E12="",Parameters!$B$2,E12) -> 1.4390092e+09 | N12: =M12*0.0251 -> 36119132 | O12: =N12*I12 -> 12659535
A13: 12 | B13: 18000000 | C13: 1.995 | D13: 0.82 | E13: 1600 | F13: =IFERROR(B13*C13*IF(D13="", Parameters!$B$2, D13)/Parameters!$B$6, 0) -> 946716.61 | G13: =F13*IF(E13="", Parameters!$B$2, E13) -> 1.5147466e+09 | H13: =G13*Parameters!$B$4 -> 39383411 | I13: =1/POWER(1+Parameters!$B$5, A13) -> 0.31863082 | J13: =H13*I13 -> 12548768 | K13: =SUM($G$2:G13) -> 1.8176959e+10 | L13: =F13*0.95 -> 899380.78 | M13: =L13*IF(E13="",Parameters!$B$2,E13) -> 1.4390092e+09 | N13: =M13*0.0251 -> 36119132 | O13: =N13*I13 -> 11508669
... A28: 27 | B28: 18000000 | C28: 1.995 | D28: 0.82 | E28: 1600 | F28: =IFERROR(B28*C28*IF(D28="", Parameters!$B$2, D28)/Parameters!$B$6, 0) -> 946716.61 | G28: =F28*IF(E28="", Parameters!$B$2, E28) -> 1.5147466e+09 | H28: =G28*Parameters!$B$4 -> 39383411 | I28: =1/POWER(1+Parameters!$B$5, A28) -> 0.076277684 | J28: =H28*I28 -> 3004075.4 | K28: =SUM($G$2:G28) -> 4.0898157e+10 | L28: =F28*0.95 -> 899380.78 | M28: =L28*IF(E28="",Parameters!$B$2,E28) -> 1.4390092e+09 | N28: =M28*0.0251 -> 36119132 | O28: =N28*I28 -> 2755083.8
F39: Totals / Key Outputs | G39: =SUM(G2:G33) -> 4.0898157e+10 | H39: =SUM(H2:H33) -> 1.0633521e+09 | J39: =SUM(J2:J28) -> 3.6379335e+08 | O39: =SUM(O2:O28) -> 3.3364048e+08
F40: Total Revenue (USD) | G40: =G39 -> 4.0898157e+10
F41: Total Severance Tax (USD) | G41: =H39 -> 1.0633521e+09
F42: PV(Severance Tax) (USD) | G42: =J39 -> 3.6379335e+08

Sheet schedule_7
A1: Year | B1: Ore (t) | C1: Grade (g/t) | D1: Recovery (override, optional) | E1: Metal Price (override, optional) | F1: Metal Produced (oz) | G1: Revenue (USD) | H1: Severance Tax (USD) | I1: Discount Factor | J1: PV(Severance Tax) (USD) | K1: Cumulative Revenue (USD) | L1: Payable Metal (oz) | M1: NSR ($) | N1: Royalty ($) | O1: PV(Royalty)
A2: 1 | B2: 19000000 | C2: 1.929 | D2: 0.82 | E2: 1600 | F2: =IFERROR(B2*C2*IF(D2="", Parameters!$B$2, D2)/Parameters!$B$6, 0) -> 966252.03 | G2: =F2*IF(E2="", Parameters!$B$2, E2) -> 1.5460032e+09 | H2: =G2*Parameters!$B$4 -> 40196084 | I2: =1/POWER(1+Parameters!$B$5, A2) -> 0.90909091 | J2: =H2*I2 -> 36541895 | K2: =SUM($G$2:G2) -> 1.5460032e+09 | L2: =F2*0.95 -> 917939.43 | M2: =L2*IF(E2="",Parameters!$B$2,E2) -> 1.4687031e+09 | N2: =M2*0.0251 -> 36864447 | O2: =N2*I2 -> 33513134
A3: 2 | B3: 19000000 | C3: 1.929 | D3: 0.82 | E3: 1600 | F3: =IFERROR(B3*C3*IF(D3="", Parameters!$B$2, D3)/Parameters!$B$6, 0) -> 966252.03 | G3: =F3*IF(E3="", Parameters!$B$2, E3) -> 1.5460032e+09 | H3: =G3*Parameters!$B$4 -> 40196084 | I3: =1/POWER(1+Parameters!$B$5, A3) -> 0.82644628 | J3: =H3*I3 -> 33219904 | K3: =SUM($G$2:G3) -> 3.0920065e+09 | L3: =F3*0.95 -> 917939.43 | M3: =L3*IF(E3="",Parameters!$B$2,E3) -> 1.4687031e+09 | N3: =M3*0.0251 -> 36864447 | O3: =N3*I3 -> 30466485
A4: 3 | B4: 19000000 | C4: 1.929 | D4: 0.82 | E4: 1600 | F4: =IFERROR(B4*C4*IF(D4="", Parameters!$B$2, D4)/Parameters!$B$6, 0) -> 966252.03 | G4: =F4*IF(E4="", Parameters!$B$2, E4) -> 1.5460032e+09 | H4: =G4*Parameters!$B$4 -> 40196084 | I4: =1/POWER(1+Parameters!$B$5, A4) -> 0.7513148 | J4: =H4*I4 -> 30199913 | K4: =SUM($G$2:G4) -> 4.6380097e+09 | L4: =F4*0.95 -> 917939.43 | M4: =L4*IF(E4="",Parameters!$B$2,E4) -> 1.4687031e+09 | N4: =M4*0.0251 -> 36864447 | O4: =N4*I4 -> 27696805
A5: 4 | B5: 19000000 | C5: 1.929 | D5: 0.82 | E5: 1600 | F5: =IFERROR(B5*C5*IF(D5="", Parameters!$B$2, D5)/Parameters!$B$6, 0) -> 966252.03 | G5: =F5*IF(E5="", Parameters!$B$2, E5) -> 1.5460032e+09 | H5: =G5*Parameters!$B$4 -> 40196084 | I5: =1/POWER(1+Parameters!$B$5, A5) -> 0.68301346 | J5: =H5*I5 -> 27454467 | K5: =SUM($G$2:G5) -> 6.184013e+09 | L5: =F5*0.95 -> 917939.43 | M5: =L5*IF(E5="",Parameters!$B$2,E5) -> 1.4687031e+09 | N5: =M5*0.0251 -> 36864447 | O5: =N5*I5 -> 25178914
A6: 5 | B6: 19000000 | C6: 1.929 | D6: 0.82 | E6: 1600 | F6: =IFERROR(B6*C6*IF(D6="", Parameters!$B$2, D6)/Parameters!$B$6, 0) -> 966252.03 | G6: =F6*IF(E6="", Parameters!$B$2, E6) -> 1.5460032e+09 | H6: =G6*Parameters!$B$4 -> 40196084 | I6: =1/POWER(1+Parameters!$B$5, A6) -> 0.62092132 | J6: =H6*I6 -> 24958606 | K6: =SUM($G$2:G6) -> 7.7300162e+09 | L6: =F6*0.95 -> 917939.43 | M6: =L6*IF(E6="",Parameters!$B$2,E6) -> 1.4687031e+09 | N6: =M6*0.0251 -> 36864447 | O6: =N6*I6 -> 22889921
A7: 6 | B7: 19000000 | C7: 1.929 | D7: 0.82 | E7: 1600 | F7: =IFERROR(B7*C7*IF(D7="", Parameters!$B$2, D7)/Parameters!$B$6, 0) -> 966252.03 | G7: =F7*IF(E7="", Parameters!$B$2, E7) -> 1.5460032e+09 | H7: =G7*Parameters!$B$4 -> 40196084 | I7: =1/POWER(1+Parameters!$B$5, A7) -> 0.56447393 | J7: =H7*I7 -> 22689642 | K7: =SUM($G$2:G7) -> 9.2760195e+09 | L7: =F7*0.95 -> 917939.43 | M7: =L7*IF(E7="",Parameters!$B$2,E7) -> 1.4687031e+09 | N7: =M7*0.0251 -> 36864447 | O7: =N7*I7 -> 20809020
A8: 7 | B8: 19000000 | C8: 1.929 | D8: 0.82 | E8: 1600 | F8: =IFERROR(B8*C8*IF(D8="", Parameters!$B$2, D8)/Parameters!$B$6, 0) -> 966252.03 | G8: =F8*IF(E8="", Parameters!$B$2, E8) -> 1.5460032e+09 | H8: =G8*Parameters!$B$4 -> 40196084 | I8: =1/POWER(1+Parameters!$B$5, A8) -> 0.51315812 | J8: =H8*I8 -> 20626947 | K8: =SUM($G$2:G8) -> 1.0822023e+10 | L8: =F8*0.95 -> 917939.43 | M8: =L8*IF(E8="",Parameters!$B$2,E8) -> 1.4687031e+09 | N8: =M8*0.0251 -> 36864447 | O8: =N8*I8 -> 18917290
A9: 8 | B9: 19000000 | C9: 1.929 | D9: 0.82 | E9: 1600 | F9: =IFERROR(B9*C9*IF(D9="", Parameters!$B$2, D9)/Parameters!$B$6, 0) -> 966252.03 | G9: =F9*IF(E9="", Parameters!$B$2, E9) -> 1.5460032e+09 | H9: =G9*Parameters!$B$4 -> 40196084 | I9: =1/POWER(1+Parameters!$B$5, A9) -> 0.46650738 | J9: =H9*I9 -> 18751770 | K9: =SUM($G$2:G9) -> 1.2368026e+10 | L9: =F9*0.95 -> 917939.43 | M9: =L9*IF(E9="",Parameters!$B$2,E9) -> 1.4687031e+09 | N9: =M9*0.0251 -> 36864447 | O9: =N9*I9 -> 17197537
A10: 9 | B10: 19000000 | C10: 1.929 | D10: 0.82 | E10: 1600 | F10: =IFERROR(B10*C10*IF(D10="", Parameters!$B$2, D10)/Parameters!$B$6, 0) -> 966252.03 | G10: =F10*IF(E10="", Parameters!$B$2, E10) -> 1.5460032e+09 | H10: =G10*Parameters!$B$4 -> 40196084 | I10: =1/POWER(1+Parameters!$B$5, A10) -> 0.42409762 | J10: =H10*I10 -> 17047064 | K10: =SUM($G$2:G10) -> 1.3914029e+10 | L10: =F10*0.95 -> 917939.43 | M10: =L10*IF(E10="",Parameters!$B$2,E10) -> 1.4687031e+09 | N10: =M10*0.0251 -> 36864447 | O10: =N10*I10 -> 15634124
A11: 10 | B11: 19000000 | C11: 1.929 | D11: 0.82 | E11: 1600 | F11: =IFERROR(B11*C11*IF(D11="", Parameters!$B$2, D11)/Parameters!$B$6, 0) -> 966252.03 | G11: =F11*IF(E11="", Parameters!$B$2, E11) -> 1.5460032e+09 | H11: =G11*Parameters!$B$4 -> 40196084 | I11: =1/POWER(1+Parameters!$B$5, A11) -> 0.38554329 | J11: =H11*I11 -> 15497331 | K11: =SUM($G$2:G11) -> 1.5460032e+10 | L11: =F11*0.95 -> 917939.43 | M11: =L11*IF(E11="",Parameters!$B$2,E11) -> 1.4687031e+09 | N11: =M11*0.0251 -> 36864447 | O11: =N11*I11 -> 14212840
A12: 11 | B12: 19000000 | C12: 1.929 | D12: 0.82 | E12: 1600 | F12: =IFERROR(B12*C12*IF(D12="", Parameters!$B$2, D12)/Parameters!$B$6, 0) -> 966252.03 | G12: =F12*IF(E12="", Parameters!$B$2, E12) -> 1.5460032e+09 | H12: =G12*Parameters!$B$4 -> 40196084 | I12: =1/POWER(1+Parameters!$B$5, A12) -> 0.3504939 | J12: =H12*I12 -> 14088482 | K12: =SUM($G$2:G12) -> 1.7006036e+10 | L12: =F12*0.95 -> 917939.43 | M12: =L12*IF(E12="",Parameters!$B$2,E12) -> 1.4687031e+09 | N12: =M12*0.0251 -> 36864447 | O12: =N12*I12 -> 12920764
A13: 12 | B13: 19000000 | C13: 1.929 | D13: 0.82 | E13: 1600 | F13: =IFERROR(B13*C13*IF(D13="", Parameters!$B$2, D13)/Parameters!$B$6, 0) -> 966252.03 | G13: =F13*IF(E13="", Parameters!$B$2, E13) -> 1.5460032e+09 | H13: =G13*Parameters!$B$4 -> 40196084 | I13: =1/POWER(1+Parameters!$B$5, A13) -> 0.31863082 | J13: =H13*I13 -> 12807711 | K13: =SUM($G$2:G13) -> 1.8552039e+10 | L13: =F13*0.95 -> 917939.43 | M13: =L13*IF(E13="",Parameters!$B$2,E13) -> 1.4687031e+09 | N13: =M13*0.0251 -> 36864447 | O13: =N13*I13 -> 11746149
... A27: 26 | B27: 19000000 | C27: 1.929 | D27: 0.82 | E27: 1600 | F27: =IFERROR(B27*C27*IF(D27="", Parameters!$B$2, D27)/Parameters!$B$6, 0) -> 966252.03 | G27: =F27*IF(E27="", Parameters!$B$2, E27) -> 1.5460032e+09 | H27: =G27*Parameters!$B$4 -> 40196084 | I27: =1/POWER(1+Parameters!$B$5, A27) -> 0.083905453 | J27: =H27*I27 -> 3372670.7 | K27: =SUM($G$2:G27) -> 4.0196084e+10 | L27: =F27*0.95 -> 917939.43 | M27: =L27*IF(E27="",Parameters!$B$2,E27) -> 1.4687031e+09 | N27: =M27*0.0251 -> 36864447 | O27: =N27*I27 -> 3093128.2
F39: Totals / Key Outputs | G39: =SUM(G2:G33) -> 4.0196084e+10 | H39: =SUM(H2:H33) -> 1.0450982e+09 | J39: =SUM(J2:J27) -> 3.6823414e+08 | O39: =SUM(O2:O27) -> 3.3771319e+08
F40: Total Revenue (USD) | G40: =G39 -> 4.0196084e+10
F41: Total Severance Tax (USD) | G41: =H39 -> 1.0450982e+09
F42: PV(Severance Tax) (USD) | G42: =J39 -> 3.6823414e+08

Sheet schedule_8
A1: Year | B1: Ore (t) | C1: Grade (g/t) | D1: Recovery (override, optional) | E1: Metal Price (override, optional) | F1: Metal Produced (oz) | G1: Revenue (USD) | H1: Severance Tax (USD) | I1: Discount Factor | J1: PV(Severance Tax) (USD) | K1: Cumulative Revenue (USD) | L1: Payable Metal (oz) | M1: NSR ($) | N1: Royalty ($) | O1: PV(Royalty)
A2: 1 | B2: 16000000 | C2: 1.981 | D2: 0.82 | E2: 1600 | F2: =IFERROR(B2*C2*IF(D2="", Parameters!$B$2, D2)/Parameters!$B$6, 0) -> 835620.43 | G2: =F2*IF(E2="", Parameters!$B$2, E2) -> 1.3369927e+09 | H2: =G2*Parameters!$B$4 -> 34761810 | I2: =1/POWER(1+Parameters!$B$5, A2) -> 0.90909091 | J2: =H2*I2 -> 31601645 | K2: =SUM($G$2:G2) -> 1.3369927e+09 | L2: =F2*0.95 -> 793839.41 | M2: =L2*IF(E2="",Parameters!$B$2,E2) -> 1.2701431e+09 | N2: =M2*0.0251 -> 31880591 | O2: =N2*I2 -> 28982355
A3: 2 | B3: 16000000 | C3: 1.981 | D3: 0.82 | E3: 1600 | F3: =IFERROR(B3*C3*IF(D3="", Parameters!$B$2, D3)/Parameters!$B$6, 0) -> 835620.43 | G3: =F3*IF(E3="", Parameters!$B$2, E3) -> 1.3369927e+09 | H3: =G3*Parameters!$B$4 -> 34761810 | I3: =1/POWER(1+Parameters!$B$5, A3) -> 0.82644628 | J3: =H3*I3 -> 28728768 | K3: =SUM($G$2:G3) -> 2.6739854e+09 | L3: =F3*0.95 -> 793839.41 | M3: =L3*IF(E3="",Parameters!$B$2,E3) -> 1.2701431e+09 | N3: =M3*0.0251 -> 31880591 | O3: =N3*I3 -> 26347596
A4: 3 | B4: 16000000 | C4: 1.981 | D4: 0.82 | E4: 1600 | F4: =IFERROR(B4*C4*IF(D4="", Parameters!$B$2, D4)/Parameters!$B$6, 0) -> 835620.43 | G4: =F4*IF(E4="", Parameters!$B$2, E4) -> 1.3369927e+09 | H4: =G4*Parameters!$B$4 -> 34761810 | I4: =1/POWER(1+Parameters!$B$5, A4) -> 0.7513148 | J4: =H4*I4 -> 26117062 | K4: =SUM($G$2:G4) -> 4.0109781e+09 | L4: =F4*0.95 -> 793839.41 | M4: =L4*IF(E4="",Parameters!$B$2,E4) -> 1.2701431e+09 | N4: =M4*0.0251 -> 31880591 | O4: =N4*I4 -> 23952360
A5: 4 | B5: 16000000 | C5: 1.981 | D5: 0.82 | E5: 1600 | F5: =IFERROR(B5*C5*IF(D5="", Parameters!$B$2, D5)/Parameters!$B$6, 0) -> 835620.43 | G5: =F5*IF(E5="", Parameters!$B$2, E5) -> 1.3369927e+09 | H5: =G5*Parameters!$B$4 -> 34761810 | I5: =1/POWER(1+Parameters!$B$5, A5) -> 0.68301346 | J5: =H5*I5 -> 23742784 | K5: =SUM($G$2:G5) -> 5.3479707e+09 | L5: =F5*0.95 -> 793839.41 | M5: =L5*IF(E5="",Parameters!$B$2,E5) -> 1.2701431e+09 | N5: =M5*0.0251 -> 31880591 | O5: =N5*I5 -> 21774872
A6: 5 | B6: 16000000 | C6: 1.981 | D6: 0.82 | E6: 1600 | F6: =IFERROR(B6*C6*IF(D6="", Parameters!$B$2, D6)/Parameters!$B$6, 0) -> 835620.43 | G6: =F6*IF(E6="", Parameters!$B$2, E6) -> 1.3369927e+09 | H6: =G6*Parameters!$B$4 -> 34761810 | I6: =1/POWER(1+Parameters!$B$5, A6) -> 0.62092132 | J6: =H6*I6 -> 21584349 | K6: =SUM($G$2:G6) -> 6.6849634e+09 | L6: =F6*0.95 -> 793839.41 | M6: =L6*IF(E6="",Parameters!$B$2,E6) -> 1.2701431e+09 | N6: =M6*0.0251 -> 31880591 | O6: =N6*I6 -> 19795338
A7: 6 | B7: 16000000 | C7: 1.981 | D7: 0.82 | E7: 1600 | F7: =IFERROR(B7*C7*IF(D7="", Parameters!$B$2, D7)/Parameters!$B$6, 0) -> 835620.43 | G7: =F7*IF(E7="", Parameters!$B$2, E7) -> 1.3369927e+09 | H7: =G7*Parameters!$B$4 -> 34761810 | I7: =1/POWER(1+Parameters!$B$5, A7) -> 0.56447393 | J7: =H7*I7 -> 19622135 | K7: =SUM($G$2:G7) -> 8.0219561e+09 | L7: =F7*0.95 -> 793839.41 | M7: =L7*IF(E7="",Parameters!$B$2,E7) -> 1.2701431e+09 | N7: =M7*0.0251 -> 31880591 | O7: =N7*I7 -> 17995762
A8: 7 | B8: 16000000 | C8: 1.981 | D8: 0.82 | E8: 1600 | F8: =IFERROR(B8*C8*IF(D8="", Parameters!$B$2, D8)/Parameters!$B$6, 0) -> 835620.43 | G8: =F8*IF(E8="", Parameters!$B$2, E8) -> 1.3369927e+09 | H8: =G8*Parameters!$B$4 -> 34761810 | I8: =1/POWER(1+Parameters!$B$5, A8) -> 0.51315812 | J8: =H8*I8 -> 17838305 | K8: =SUM($G$2:G8) -> 9.3589488e+09 | L8: =F8*0.95 -> 793839.41 | M8: =L8*IF(E8="",Parameters!$B$2,E8) -> 1.2701431e+09 | N8: =M8*0.0251 -> 31880591 | O8: =N8*I8 -> 16359784
A9: 8 | B9: 16000000 | C9: 1.981 | D9: 0.82 | E9: 1600 | F9: =IFERROR(B9*C9*IF(D9="", Parameters!$B$2, D9)/Parameters!$B$6, 0) -> 835620.43 | G9: =F9*IF(E9="", Parameters!$B$2, E9) -> 1.3369927e+09 | H9: =G9*Parameters!$B$4 -> 34761810 | I9: =1/POWER(1+Parameters!$B$5, A9) -> 0.46650738 | J9: =H9*I9 -> 16216641 | K9: =SUM($G$2:G9) -> 1.0695941e+10 | L9: =F9*0.95 -> 793839.41 | M9: =L9*IF(E9="",Parameters!$B$2,E9) -> 1.2701431e+09 | N9: =M9*0.0251 -> 31880591 | O9: =N9*I9 -> 14872531
A10: 9 | B10: 16000000 | C10: 1.981 | D10: 0.82 | E10: 1600 | F10: =IFERROR(B10*C10*IF(D10="", Parameters!$B$2, D10)/Parameters!$B$6, 0) -> 835620.43 | G10: =F10*IF(E10="", Parameters!$B$2, E10) -> 1.3369927e+09 | H10: =G10*Parameters!$B$4 -> 34761810 | I10: =1/POWER(1+Parameters!$B$5, A10) -> 0.42409762 | J10: =H10*I10 -> 14742401 | K10: =SUM($G$2:G10) -> 1.2032934e+10 | L10: =F10*0.95 -> 793839.41 | M10: =L10*IF(E10="",Parameters!$B$2,E10) -> 1.2701431e+09 | N10: =M10*0.0251 -> 31880591 | O10: =N10*I10 -> 13520483
A11: 10 | B11: 16000000 | C11: 1.981 | D11: 0.82 | E11: 1600 | F11: =IFERROR(B11*C11*IF(D11="", Parameters!$B$2, D11)/Parameters!$B$6, 0) -> 835620.43 | G11: =F11*IF(E11="", Parameters!$B$2, E11) -> 1.3369927e+09 | H11: =G11*Parameters!$B$4 -> 34761810 | I11: =1/POWER(1+Parameters!$B$5, A11) -> 0.38554329 | J11: =H11*I11 -> 13402183 | K11: =SUM($G$2:G11) -> 1.3369927e+10 | L11: =F11*0.95 -> 793839.41 | M11: =L11*IF(E11="",Parameters!$B$2,E11) -> 1.2701431e+09 | N11: =M11*0.0251 -> 31880591 | O11: =N11*I11 -> 12291348
A12: 11 | B12: 16000000 | C12: 1.981 | D12: 0.82 | E12: 1600 | F12: =IFERROR(B12*C12*IF(D12="", Parameters!$B$2, D12)/Parameters!$B$6, 0) -> 835620.43 | G12: =F12*IF(E12="", Parameters!$B$2, E12) -> 1.3369927e+09 | H12: =G12*Parameters!$B$4 -> 34761810 | I12: =1/POWER(1+Parameters!$B$5, A12) -> 0.3504939 | J12: =H12*I12 -> 12183802 | K12: =SUM($G$2:G12) -> 1.470692e+10 | L12: =F12*0.95 -> 793839.41 | M12: =L12*IF(E12="",Parameters!$B$2,E12) -> 1.2701431e+09 | N12: =M12*0.0251 -> 31880591 | O12: =N12*I12 -> 11173953
A13: 12 | B13: 16000000 | C13: 1.981 | D13: 0.82 | E13: 1600 | F13: =IFERROR(B13*C13*IF(D13="", Parameters!$B$2, D13)/Parameters!$B$6, 0) -> 835620.43 | G13: =F13*IF(E13="", Parameters!$B$2, E13) -> 1.3369927e+09 | H13: =G13*Parameters!$B$4 -> 34761810 | I13: =1/POWER(1+Parameters!$B$5, A13) -> 0.31863082 | J13: =H13*I13 -> 11076184 | K13: =SUM($G$2:G13) -> 1.6043912e+10 | L13: =F13*0.95 -> 793839.41 | M13: =L13*IF(E13="",Parameters!$B$2,E13) -> 1.2701431e+09 | N13: =M13*0.0251 -> 31880591 | O13: =N13*I13 -> 10158139
... A29: 28 | B29: 16000000 | C29: 1.981 | D29: 0.82 | E29: 1600 | F29: =IFERROR(B29*C29*IF(D29="", Parameters!$B$2, D29)/Parameters!$B$6, 0) -> 835620.43 | G29: =F29*IF(E29="", Parameters!$B$2, E29) -> 1.3369927e+09 | H29: =G29*Parameters!$B$4 -> 34761810 | I29: =1/POWER(1+Parameters!$B$5, A29) -> 0.069343349 | J29: =H29*I29 -> 2410500.3 | K29: =SUM($G$2:G29) -> 3.7435795e+10 | L29: =F29*0.95 -> 793839.41 | M29: =L29*IF(E29="",Parameters!$B$2,E29) -> 1.2701431e+09 | N29: =M29*0.0251 -> 31880591 | O29: =N29*I29 -> 2210706.9
F39: Totals / Key Outputs | G39: =SUM(G2:G33) -> 3.7435795e+10 | H39: =SUM(H2:H33) -> 9.7333068e+08 | J39: =SUM(J2:J29) -> 3.235131e+08 | O39: =SUM(O2:O29) -> 2.9669884e+08
F40: Total Revenue (USD) | G40: =G39 -> 3.7435795e+10
F41: Total Severance Tax (USD) | G41: =H39 -> 9.7333068e+08
F42: PV(Severance Tax) (USD) | G42: =J39 -> 3.235131e+08

Sheet schedule_9
A1: Year | B1: Ore (t) | C1: Grade (g/t) | D1: Recovery (override, optional) | E1: Metal Price (override, optional) | F1: Metal Produced (oz) | G1: Revenue (USD) | H1: Severance Tax (USD) | I1: Discount Factor | J1: PV(Severance Tax) (USD) | K1: Cumulative Revenue (USD) | L1: Payable Metal (oz) | M1: NSR ($) | N1: Royalty ($) | O1: PV(Royalty)
A2: 1 | B2: 17000000 | C2: 1.928 | D2: 0.82 | E2: 1600 | F2: =IFERROR(B2*C2*IF(D2="", Parameters!$B$2, D2)/Parameters!$B$6, 0) -> 864093.11 | G2: =F2*IF(E2="", Parameters!$B$2, E2) -> 1.382549e+09 | H2: =G2*Parameters!$B$4 -> 35946273 | I2: =1/POWER(1+Parameters!$B$5, A2) -> 0.90909091 | J2: =H2*I2 -> 32678430 | K2: =SUM($G$2:G2) -> 1.382549e+09 | L2: =F2*0.95 -> 820888.45 | M2: =L2*IF(E2="",Parameters!$B$2,E2) -> 1.3134215e+09 | N2: =M2*0.0251 -> 32966880 | O2: =N2*I2 -> 29969891
A3: 2 | B3: 17000000 | C3: 1.928 | D3: 0.82 | E3: 1600 | F3: =IFERROR(B3*C3*IF(D3="", Parameters!$B$2, D3)/Parameters!$B$6, 0) -> 864093.11 | G3: =F3*IF(E3="", Parameters!$B$2, E3) -> 1.382549e+09 | H3: =G3*Parameters!$B$4 -> 35946273 | I3: =1/POWER(1+Parameters!$B$5, A3) -> 0.82644628 | J3: =H3*I3 -> 29707664 | K3: =SUM($G$2:G3) -> 2.7650979e+09 | L3: =F3*0.95 -> 820888.45 | M3: =L3*IF(E3="",Parameters!$B$2,E3) -> 1.3134215e+09 | N3: =M3*0.0251 -> 32966880 | O3: =N3*I3 -> 27245356
A4: 3 | B4: 17000000 | C4: 1.928 | D4: 0.82 | E4: 1600 | F4: =IFERROR(B4*C4*IF(D4="", Parameters!$B$2, D4)/Parameters!$B$6, 0) -> 864093.11 | G4: =F4*IF(E4="", Parameters!$B$2, E4) -> 1.382549e+09 | H4: =G4*Parameters!$B$4 -> 35946273 | I4: =1/POWER(1+Parameters!$B$5, A4) -> 0.7513148 | J4: =H4*I4 -> 27006967 | K4: =SUM($G$2:G4) -> 4.1476469e+09 | L4: =F4*0.95 -> 820888.45 | M4: =L4*IF(E4="",Parameters!$B$2,E4) -> 1.3134215e+09 | N4: =M4*0.0251 -> 32966880 | O4: =N4*I4 -> 24768505
A5: 4 | B5: 17000000 | C5: 1.928 | D5: 0.82 | E5: 1600 | F5: =IFERROR(B5*C5*IF(D5="", Parameters!$B$2, D5)/Parameters!$B$6, 0) -> 864093.11 | G5: =F5*IF(E5="", Parameters!$B$2, E5) -> 1.382549e+09 | H5: =G5*Parameters!$B$4 -> 35946273 | I5: =1/POWER(1+Parameters!$B$5, A5) -> 0.68301346 | J5: =H5*I5 -> 24551788 | K5: =SUM($G$2:G5) -> 5.5301959e+09 | L5: =F5*0.95 -> 820888.45 | M5: =L5*IF(E5="",Parameters!$B$2,E5) -> 1.3134215e+09 | N5: =M5*0.0251 -> 32966880 | O5: =N5*I5 -> 22516823
A6: 5 | B6: 17000000 | C6: 1.928 | D6: 0.82 | E6: 1600 | F6: =IFERROR(B6*C6*IF(D6="", Parameters!$B$2, D6)/Parameters!$B$6, 0) -> 864093.11 | G6: =F6*IF(E6="", Parameters!$B$2, E6) -> 1.382549e+09 | H6: =G6*Parameters!$B$4 -> 35946273 | I6: =1/POWER(1+Parameters!$B$5, A6) -> 0.62092132 | J6: =H6*I6 -> 22319808 | K6: =SUM($G$2:G6) -> 6.9127449e+09 | L6: =F6*0.95 -> 820888.45 | M6: =L6*IF(E6="",Parameters!$B$2,E6) -> 1.3134215e+09 | N6: =M6*0.0251 -> 32966880 | O6: =N6*I6 -> 20469839
A7: 6 | B7: 17000000 | C7: 1.928 | D7: 0.82 | E7: 1600 | F7: =IFERROR(B7*C7*IF(D7="", Parameters!$B$2, D7)/Parameters!$B$6, 0) -> 864093.11 | G7: =F7*IF(E7="", Parameters!$B$2, E7) -> 1.382549e+09 | H7: =G7*Parameters!$B$4 -> 35946273 | I7: =1/POWER(1+Parameters!$B$5, A7) -> 0.56447393 | J7: =H7*I7 -> 20290734 | K7: =SUM($G$2:G7) -> 8.2952938e+09 | L7: =F7*0.95 -> 820888.45 | M7: =L7*IF(E7="",Parameters!$B$2,E7) -> 1.3134215e+09 | N7: =M7*0.0251 -> 32966880 | O7: =N7*I7 -> 18608944
A8: 7 | B8: 17000000 | C8: 1.928 | D8: 0.82 | E8: 1600 | F8: =IFERROR(B8*C8*IF(D8="", Parameters!$B$2, D8)/Parameters!$B$6, 0) -> 864093.11 | G8: =F8*IF(E8="", Parameters!$B$2, E8) -> 1.382549e+09 | H8: =G8*Parameters!$B$4 -> 35946273 | I8: =1/POWER(1+Parameters!$B$5, A8) -> 0.51315812 | J8: =H8*I8 -> 18446122 | K8: =SUM($G$2:G8) -> 9.6778428e+09 | L8: =F8*0.95 -> 820888.45 | M8: =L8*IF(E8="",Parameters!$B$2,E8) -> 1.3134215e+09 | N8: =M8*0.0251 -> 32966880 | O8: =N8*I8 -> 16917222
A9: 8 | B9: 17000000 | C9: 1.928 | D9: 0.82 | E9: 1600 | F9: =IFERROR(B9*C9*IF(D9="", Parameters!$B$2, D9)/Parameters!$B$6, 0) -> 864093.11 | G9: =F9*IF(E9="", Parameters!$B$2, E9) -> 1.382549e+09 | H9: =G9*Parameters!$B$4 -> 35946273 | I9: =1/POWER(1+Parameters!$B$5, A9) -> 0.46650738 | J9: =H9*I9 -> 16769202 | K9: =SUM($G$2:G9) -> 1.1060392e+10 | L9: =F9*0.95 -> 820888.45 | M9: =L9*IF(E9="",Parameters!$B$2,E9) -> 1.3134215e+09 | N9: =M9*0.0251 -> 32966880 | O9: =N9*I9 -> 15379293
A10: 9 | B10: 17000000 | C10: 1.928 | D10: 0.82 | E10: 1600 | F10: =IFERROR(B10*C10*IF(D10="", Parameters!$B$2, D10)/Parameters!$B$6, 0) -> 864093.11 | G10: =F10*IF(E10="", Parameters!$B$2, E10) -> 1.382549e+09 | H10: =G10*Parameters!$B$4 -> 35946273 | I10: =1/POWER(1+Parameters!$B$5, A10) -> 0.42409762 | J10: =H10*I10 -> 15244729 | K10: =SUM($G$2:G10) -> 1.2442941e+10 | L10: =F10*0.95 -> 820888.45 | M10: =L10*IF(E10="",Parameters!$B$2,E10) -> 1.3134215e+09 | N10: =M10*0.0251 -> 32966880 | O10: =N10*I10 -> 13981175
A11: 10 | B11: 17000000 | C11: 1.928 | D11: 0.82 | E11: 1600 | F11: =IFERROR(B11*C11*IF(D11="", Parameters!$B$2, D11)/Parameters!$B$6, 0) -> 864093.11 | G11: =F11*IF(E11="", Parameters!$B$2, E11) -> 1.382549e+09 | H11: =G11*Parameters!$B$4 -> 35946273 | I11: =1/POWER(1+Parameters!$B$5, A11) -> 0.38554329 | J11: =H11*I11 -> 13858844 | K11: =SUM($G$2:G11) -> 1.382549e+10 | L11: =F11*0.95 -> 820888.45 | M11: =L11*IF(E11="",Parameters!$B$2,E11) -> 1.3134215e+09 | N11: =M11*0.0251 -> 32966880 | O11: =N11*I11 -> 12710159
A12: 11 | B12: 17000000 | C12: 1.928 | D12: 0.82 | E12: 1600 | F12: =IFERROR(B12*C12*IF(D12="", Parameters!$B$2, D12)/Parameters!$B$6, 0) -> 864093.11 | G12: =F12*IF(E12="", Parameters!$B$2, E12) -> 1.382549e+09 | H12: =G12*Parameters!$B$4 -> 35946273 | I12: =1/POWER(1+Parameters!$B$5, A12) -> 0.3504939 | J12: =H12*I12 -> 12598950 | K12: =SUM($G$2:G12) -> 1.5208039e+10 | L12: =F12*0.95 -> 820888.45 | M12: =L12*IF(E12="",Parameters!$B$2,E12) -> 1.3134215e+09 | N12: =M12*0.0251 -> 32966880 | O12: =N12*I12 -> 11554690
A13: 12 | B13: 17000000 | C13: 1.928 | D13: 0.82 | E13: 1600 | F13: =IFERROR(B13*C13*IF(D13="", Parameters!$B$2, D13)/Parameters!$B$6, 0) -> 864093.11 | G13: =F13*IF(E13="", Parameters!$B$2, E13) -> 1.382549e+09 | H13: =G13*Parameters!$B$4 -> 35946273 | I13: =1/POWER(1+Parameters!$B$5, A13) -> 0.31863082 | J13: =H13*I13 -> 11453590 | K13: =SUM($G$2:G13) -> 1.6590588e+10 | L13: =F13*0.95 -> 820888.45 | M13: =L13*IF(E13="",Parameters!$B$2,E13) -> 1.3134215e+09 | N13: =M13*0.0251 -> 32966880 | O13: =N13*I13 -> 10504264
... A29: 28 | B29: 17000000 | C29: 1.928 | D29: 0.82 | E29: 1600 | F29: =IFERROR(B29*C29*IF(D29="", Parameters!$B$2, D29)/Parameters!$B$6, 0) -> 864093.11 | G29: =F29*IF(E29="", Parameters!$B$2, E29) -> 1.382549e+09 | H29: =G29*Parameters!$B$4 -> 35946273 | I29: =1/POWER(1+Parameters!$B$5, A29) -> 0.069343349 | J29: =H29*I29 -> 2492635 | K29: =SUM($G$2:G29) -> 3.8711371e+10 | L29: =F29*0.95 -> 820888.45 | M29: =L29*IF(E29="",Parameters!$B$2,E29) -> 1.3134215e+09 | N29: =M29*0.0251 -> 32966880 | O29: =N29*I29 -> 2286033.9
F39: Totals / Key Outputs | G39: =SUM(G2:G33) -> 3.8711371e+10 | H39: =SUM(H2:H33) -> 1.0064957e+09 | J39: =SUM(J2:J29) -> 3.3453638e+08 | O39: =SUM(O2:O29) -> 3.0680846e+08
F40: Total Revenue (USD) | G40: =G39 -> 3.8711371e+10
F41: Total Severance Tax (USD) | G41: =H39 -> 1.0064957e+09
F42: PV(Severance Tax) (USD) | G42: =J39 -> 3.3453638e+08

Sheet schedule_10
A1: Year | B1: Ore (t) | C1: Grade (g/t) | D1: Recovery (override, optional) | E1: Metal Price (override, optional) | F1: Metal Produced (oz) | G1: Revenue (USD) | H1: Severance Tax (USD) | I1: Discount Factor | J1: PV(Severance Tax) (USD) | K1: Cumulative Revenue (USD) | L1: Payable Metal (oz) | M1: NSR ($) | N1: Royalty ($) | O1: PV(Royalty)
A2: 1 | B2: 19000000 | C2: 1.917 | D2: 0.82 | E2: 1600 | F2: =IFERROR(B2*C2*IF(D2="", Parameters!$B$2, D2)/Parameters!$B$6, 0) -> 960241.13 | G2: =F2*IF(E2="", Parameters!$B$2, E2) -> 1.5363858e+09 | H2: =G2*Parameters!$B$4 -> 39946031 | I2: =1/POWER(1+Parameters!$B$5, A2) -> 0.90909091 | J2: =H2*I2 -> 36314574 | K2: =SUM($G$2:G2) -> 1.5363858e+09 | L2: =F2*0.95 -> 912229.07 | M2: =L2*IF(E2="",Parameters!$B$2,E2) -> 1.4595665e+09 | N2: =M2*0.0251 -> 36635120 | O2: =N2*I2 -> 33304654
A3: 2 | B3: 19000000 | C3: 1.917 | D3: 0.82 | E3: 1600 | F3: =IFERROR(B3*C3*IF(D3="", Parameters!$B$2, D3)/Parameters!$B$6, 0) -> 960241.13 | G3: =F3*IF(E3="", Parameters!$B$2, E3) -> 1.5363858e+09 | H3: =G3*Parameters!$B$4 -> 39946031 | I3: =1/POWER(1+Parameters!$B$5, A3) -> 0.82644628 | J3: =H3*I3 -> 33013249 | K3: =SUM($G$2:G3) -> 3.0727716e+09 | L3: =F3*0.95 -> 912229.07 | M3: =L3*IF(E3="",Parameters!$B$2,E3) -> 1.4595665e+09 | N3: =M3*0.0251 -> 36635120 | O3: =N3*I3 -> 30276958
A4: 3 | B4: 19000000 | C4: 1.917 | D4: 0.82 | E4: 1600 | F4: =IFERROR(B4*C4*IF(D4="", Parameters!$B$2, D4)/Parameters!$B$6, 0) -> 960241.13 | G4: =F4*IF(E4="", Parameters!$B$2, E4) -> 1.5363858e+09 | H4: =G4*Parameters!$B$4 -> 39946031 | I4: =1/POWER(1+Parameters!$B$5, A4) -> 0.7513148 | J4: =H4*I4 -> 30012044 | K4: =SUM($G$2:G4) -> 4.6091574e+09 | L4: =F4*0.95 -> 912229.07 | M4: =L4*IF(E4="",Parameters!$B$2,E4) -> 1.4595665e+09 | N4: =M4*0.0251 -> 36635120 | O4: =N4*I4 -> 27524508
A5: 4 | B5: 19000000 | C5: 1.917 | D5: 0.82 | E5: 1600 | F5: =IFERROR(B5*C5*IF(D5="", Parameters!$B$2, D5)/Parameters!$B$6, 0) -> 960241.13 | G5: =F5*IF(E5="", Parameters!$B$2, E5) -> 1.5363858e+09 | H5: =G5*Parameters!$B$4 -> 39946031 | I5: =1/POWER(1+Parameters!$B$5, A5) -> 0.68301346 | J5: =H5*I5 -> 27283677 | K5: =SUM($G$2:G5) -> 6.1455432e+09 | L5: =F5*0.95 -> 912229.07 | M5: =L5*IF(E5="",Parameters!$B$2,E5) -> 1.4595665e+09 | N5: =M5*0.0251 -> 36635120 | O5: =N5*I5 -> 25022280
A6: 5 | B6: 19000000 | C6: 1.917 | D6: 0.82 | E6: 1600 | F6: =IFERROR(B6*C6*IF(D6="", Parameters!$B$2, D6)/Parameters!$B$6, 0) -> 960241.13 | G6: =F6*IF(E6="", Parameters!$B$2, E6) -> 1.5363858e+09 | H6: =G6*Parameters!$B$4 -> 39946031 | I6: =1/POWER(1+Parameters!$B$5, A6) -> 0.62092132 | J6: =H6*I6 -> 24803342 | K6: =SUM($G$2:G6) -> 7.681929e+09 | L6: =F6*0.95 -> 912229.07 | M6: =L6*IF(E6="",Parameters!$B$2,E6) -> 1.4595665e+09 | N6: =M6*0.0251 -> 36635120 | O6: =N6*I6 -> 22747527
A7: 6 | B7: 19000000 | C7: 1.917 | D7: 0.82 | E7: 1600 | F7: =IFERROR(B7*C7*IF(D7="", Parameters!$B$2, D7)/Parameters!$B$6, 0) -> 960241.13 | G7: =F7*IF(E7="", Parameters!$B$2, E7) -> 1.5363858e+09 | H7: =G7*Parameters!$B$4 -> 39946031 | I7: =1/POWER(1+Parameters!$B$5, A7) -> 0.56447393 | J7: =H7*I7 -> 22548493 | K7: =SUM($G$2:G7) -> 9.2183149e+09 | L7: =F7*0.95 -> 912229.07 | M7: =L7*IF(E7="",Parameters!$B$2,E7) -> 1.4595665e+09 | N7: =M7*0.0251 -> 36635120 | O7: =N7*I7 -> 20679570
A8: 7 | B8: 19000000 | C8: 1.917 | D8: 0.82 | E8: 1600 | F8: =IFERROR(B8*C8*IF(D8="", Parameters!$B$2, D8)/Parameters!$B$6, 0) -> 960241.13 | G8: =F8*IF(E8="", Parameters!$B$2, E8) -> 1.5363858e+09 | H8: =G8*Parameters!$B$4 -> 39946031 | I8: =1/POWER(1+Parameters!$B$5, A8) -> 0.51315812 | J8: =H8*I8 -> 20498630 | K8: =SUM($G$2:G8) -> 1.0754701e+10 | L8: =F8*0.95 -> 912229.07 | M8: =L8*IF(E8="",Parameters!$B$2,E8) -> 1.4595665e+09 | N8: =M8*0.0251 -> 36635120 | O8: =N8*I8 -> 18799609
A9: 8 | B9: 19000000 | C9: 1.917 | D9: 0.82 | E9: 1600 | F9: =IFERROR(B9*C9*IF(D9="", Parameters!$B$2, D9)/Parameters!$B$6, 0) -> 960241.13 | G9: =F9*IF(E9="", Parameters!$B$2, E9) -> 1.5363858e+09 | H9: =G9*Parameters!$B$4 -> 39946031 | I9: =1/POWER(1+Parameters!$B$5, A9) -> 0.46650738 | J9: =H9*I9 -> 18635118 | K9: =SUM($G$2:G9) -> 1.2291086e+10 | L9: =F9*0.95 -> 912229.07 | M9: =L9*IF(E9="",Parameters!$B$2,E9) -> 1.4595665e+09 | N9: =M9*0.0251 -> 36635120 | O9: =N9*I9 -> 17090554
A10: 9 | B10: 19000000 | C10: 1.917 | D10: 0.82 | E10: 1600 | F10: =IFERROR(B10*C10*IF(D10="", Parameters!$B$2, D10)/Parameters!$B$6, 0) -> 960241.13 | G10: =F10*IF(E10="", Parameters!$B$2, E10) -> 1.5363858e+09 | H10: =G10*Parameters!$B$4 -> 39946031 | I10: =1/POWER(1+Parameters!$B$5, A10) -> 0.42409762 | J10: =H10*I10 -> 16941017 | K10: =SUM($G$2:G10) -> 1.3827472e+10 | L10: =F10*0.95 -> 912229.07 | M10: =L10*IF(E10="",Parameters!$B$2,E10) -> 1.4595665e+09 | N10: =M10*0.0251 -> 36635120 | O10: =N10*I10 -> 15536867
A11: 10 | B11: 19000000 | C11: 1.917 | D11: 0.82 | E11: 1600 | F11: =IFERROR(B11*C11*IF(D11="", Parameters!$B$2, D11)/Parameters!$B$6, 0) -> 960241.13 | G11: =F11*IF(E11="", Parameters!$B$2, E11) -> 1.5363858e+09 | H11: =G11*Parameters!$B$4 -> 39946031 | I11: =1/POWER(1+Parameters!$B$5, A11) -> 0.38554329 | J11: =H11*I11 -> 15400924 | K11: =SUM($G$2:G11) -> 1.5363858e+10 | L11: =F11*0.95 -> 912229.07 | M11: =L11*IF(E11="",Parameters!$B$2,E11) -> 1.4595665e+09 | N11: =M11*0.0251 -> 36635120 | O11: =N11*I11 -> 14124425
A12: 11 | B12: 19000000 | C12: 1.917 | D12: 0.82 | E12: 1600 | F12: =IFERROR(B12*C12*IF(D12="", Parameters!$B$2, D12)/Parameters!$B$6, 0) -> 960241.13 | G12: =F12*IF(E12="", Parameters!$B$2, E12) -> 1.5363858e+09 | H12: =G12*Parameters!$B$4 -> 39946031 | I12: =1/POWER(1+Parameters!$B$5, A12) -> 0.3504939 | J12: =H12*I12 -> 14000840 | K12: =SUM($G$2:G12) -> 1.6900244e+10 | L12: =F12*0.95 -> 912229.07 | M12: =L12*IF(E12="",Parameters!$B$2,E12) -> 1.4595665e+09 | N12: =M12*0.0251 -> 36635120 | O12: =N12*I12 -> 12840386
A13: 12 | B13: 19000000 | C13: 1.917 | D13: 0.82 | E13: 1600 | F13: =IFERROR(B13*C13*IF(D13="", Parameters!$B$2, D13)/Parameters!$B$6, 0) -> 960241.13 | G13: =F13*IF(E13="", Parameters!$B$2, E13) -> 1.5363858e+09 | H13: =G13*Parameters!$B$4 -> 39946031 | I13: =1/POWER(1+Parameters!$B$5, A13) -> 0.31863082 | J13: =H13*I13 -> 12728037 | K13: =SUM($G$2:G13) -> 1.843663e+10 | L13: =F13*0.95 -> 912229.07 | M13: =L13*IF(E13="",Parameters!$B$2,E13) -> 1.4595665e+09 | N13: =M13*0.0251 -> 36635120 | O13: =N13*I13 -> 11673078
... A28: 27 | B28: 19000000 | C28: 1.917 | D28: 0.82 | E28: 1600 | F28: =IFERROR(B28*C28*IF(D28="", Parameters!$B$2, D28)/Parameters!$B$6, 0) -> 960241.13 | G28: =F28*IF(E28="", Parameters!$B$2, E28) -> 1.5363858e+09 | H28: =G28*Parameters!$B$4 -> 39946031 | I28: =1/POWER(1+Parameters!$B$5, A28) -> 0.076277684 | J28: =H28*I28 -> 3046990.7 | K28: =SUM($G$2:G28) -> 4.1482417e+10 | L28: =F28*0.95 -> 912229.07 | M28: =L28*IF(E28="",Parameters!$B$2,E28) -> 1.4595665e+09 | N28: =M28*0.0251 -> 36635120 | O28: =N28*I28 -> 2794442.1
F39: Totals / Key Outputs | G39: =SUM(G2:G33) -> 4.1482417e+10 | H39: =SUM(H2:H33) -> 1.0785428e+09 | J39: =SUM(J2:J28) -> 3.689904e+08 | O39: =SUM(O2:O28) -> 3.3840678e+08
F40: Total Revenue (USD) | G40: =G39 -> 4.1482417e+10
F41: Total Severance Tax (USD) | G41: =H39 -> 1.0785428e+09
F42: PV(Severance Tax) (USD) | G42: =J39 -> 3.689904e+08

Sheet schedule_11
A1: Year | B1: Ore (t) | C1: Grade (g/t) | D1: Recovery (override, optional) | E1: Metal Price (override, optional) | F1: Metal Produced (oz) | G1: Revenue (USD) | H1: Severance Tax (USD) | I1: Discount Factor | J1: PV(Severance Tax) (USD) | K1: Cumulative Revenue (USD) | L1: Payable Metal (oz) | M1: NSR ($) | N1: Royalty ($) | O1: PV(Royalty)
A2: 1 | B2: 21000000 | C2: 1.988 | D2: 0.82 | E2: 1600 | F2: =IFERROR(B2*C2*IF(D2="", Parameters!$B$2, D2)/Parameters!$B$6, 0) -> 1100627.3 | G2: =F2*IF(E2="", Parameters!$B$2, E2) -> 1.7610036e+09 | H2: =G2*Parameters!$B$4 -> 45786094 | I2: =1/POWER(1+Parameters!$B$5, A2) -> 0.90909091 | J2: =H2*I2 -> 41623722 | K2: =SUM($G$2:G2) -> 1.7610036e+09 | L2: =F2*0.95 -> 1045595.9 | M2: =L2*IF(E2="",Parameters!$B$2,E2) -> 1.6729534e+09 | N2: =M2*0.0251 -> 41991131 | O2: =N2*I2 -> 38173756
A3: 2 | B3: 21000000 | C3: 1.988 | D3: 0.82 | E3: 1600 | F3: =IFERROR(B3*C3*IF(D3="", Parameters!$B$2, D3)/Parameters!$B$6, 0) -> 1100627.3 | G3: =F3*IF(E3="", Parameters!$B$2, E3) -> 1.7610036e+09 | H3: =G3*Parameters!$B$4 -> 45786094 | I3: =1/POWER(1+Parameters!$B$5, A3) -> 0.82644628 | J3: =H3*I3 -> 37839747 | K3: =SUM($G$2:G3) -> 3.5220072e+09 | L3: =F3*0.95 -> 1045595.9 | M3: =L3*IF(E3="",Parameters!$B$2,E3) -> 1.6729534e+09 | N3: =M3*0.0251 -> 41991131 | O3: =N3*I3 -> 34703414
A4: 3 | B4: 21000000 | C4: 1.988 | D4: 0.82 | E4: 1600 | F4: =IFERROR(B4*C4*IF(D4="", Parameters!$B$2, D4)/Parameters!$B$6, 0) -> 1100627.3 | G4: =F4*IF(E4="", Parameters!$B$2, E4) -> 1.7610036e+09 | H4: =G4*Parameters!$B$4 -> 45786094 | I4: =1/POWER(1+Parameters!$B$5, A4) -> 0.7513148 | J4: =H4*I4 -> 34399770 | K4: =SUM($G$2:G4) -> 5.2830109e+09 | L4: =F4*0.95 -> 1045595.9 | M4: =L4*IF(E4="",Parameters!$B$2,E4) -> 1.6729534e+09 | N4: =M4*0.0251 -> 41991131 | O4: =N4*I4 -> 31548558
A5: 4 | B5: 21000000 | C5: 1.988 | D5: 0.82 | E5: 1600 | F5: =IFERROR(B5*C5*IF(D5="", Parameters!$B$2, D5)/Parameters!$B$6, 0) -> 1100627.3 | G5: =F5*IF(E5="", Parameters!$B$2, E5) -> 1.7610036e+09 | H5: =G5*Parameters!$B$4 -> 45786094 | I5: =1/POWER(1+Parameters!$B$5, A5) -> 0.68301346 | J5: =H5*I5 -> 31272518 | K5: =SUM($G$2:G5) -> 7.0440145e+09 | L5: =F5*0.95 -> 1045595.9 | M5: =L5*IF(E5="",Parameters!$B$2,E5) -> 1.6729534e+09 | N5: =M5*0.0251 -> 41991131 | O5: =N5*I5 -> 28680508
A6: 5 | B6: 21000000 | C6: 1.988 | D6: 0.82 | E6: 1600 | F6: =IFERROR(B6*C6*IF(D6="", Parameters!$B$2, D6)/Parameters!$B$6, 0) -> 1100627.3 | G6: =F6*IF(E6="", Parameters!$B$2, E6) -> 1.7610036e+09 | H6: =G6*Parameters!$B$4 -> 45786094 | I6: =1/POWER(1+Parameters!$B$5, A6) -> 0.62092132 | J6: =H6*I6 -> 28429562 | K6: =SUM($G$2:G6) -> 8.8050181e+09 | L6: =F6*0.95 -> 1045595.9 | M6: =L6*IF(E6="",Parameters!$B$2,E6) -> 1.6729534e+09 | N6: =M6*0.0251 -> 41991131 | O6: =N6*I6 -> 26073189
A7: 6 | B7: 21000000 | C7: 1.988 | D7: 0.82 | E7: 1600 | F7: =IFERROR(B7*C7*IF(D7="", Parameters!$B$2, D7)/Parameters!$B$6, 0) -> 1100627.3 | G7: =F7*IF(E7="", Parameters!$B$2, E7) -> 1.7610036e+09 | H7: =G7*Parameters!$B$4 -> 45786094 | I7: =1/POWER(1+Parameters!$B$5, A7) -> 0.56447393 | J7: =H7*I7 -> 25845056 | K7: =SUM($G$2:G7) -> 1.0566022e+10 | L7: =F7*0.95 -> 1045595.9 | M7: =L7*IF(E7="",Parameters!$B$2,E7) -> 1.6729534e+09 | N7: =M7*0.0251 -> 41991131 | O7: =N7*I7 -> 23702899
A8: 7 | B8: 21000000 | C8: 1.988 | D8: 0.82 | E8: 1600 | F8: =IFERROR(B8*C8*IF(D8="", Parameters!$B$2, D8)/Parameters!$B$6, 0) -> 1100627.3 | G8: =F8*IF(E8="", Parameters!$B$2, E8) -> 1.7610036e+09 | H8: =G8*Parameters!$B$4 -> 45786094 | I8: =1/POWER(1+Parameters!$B$5, A8) -> 0.51315812 | J8: =H8*I8 -> 23495506 | K8: =SUM($G$2:G8) -> 1.2327025e+10 | L8: =F8*0.95 -> 1045595.9 | M8: =L8*IF(E8="",Parameters!$B$2,E8) -> 1.6729534e+09 | N8: =M8*0.0251 -> 41991131 | O8: =N8*I8 -> 21548090
A9: 8 | B9: 21000000 | C9: 1.988 | D9: 0.82 | E9: 1600 | F9: =IFERROR(B9*C9*IF(D9="", Parameters!$B$2, D9)/Parameters!$B$6, 0) -> 1100627.3 | G9: =F9*IF(E9="", Parameters!$B$2, E9) -> 1.7610036e+09 | H9: =G9*Parameters!$B$4 -> 45786094 | I9: =1/POWER(1+Parameters!$B$5, A9) -> 0.46650738 | J9: =H9*I9 -> 21359551 | K9: =SUM($G$2:G9) -> 1.4088029e+10 | L9: =F9*0.95 -> 1045595.9 | M9: =L9*IF(E9="",Parameters!$B$2,E9) -> 1.6729534e+09 | N9: =M9*0.0251 -> 41991131 | O9: =N9*I9 -> 19589173
A10: 9 | B10: 21000000 | C10: 1.988 | D10: 0.82 | E10: 1600 | F10: =IFERROR(B10*C10*IF(D10="", Parameters!$B$2, D10)/Parameters!$B$6, 0) -> 1100627.3 | G10: =F10*IF(E10="", Parameters!$B$2, E10) -> 1.7610036e+09 | H10: =G10*Parameters!$B$4 -> 45786094 | I10: =1/POWER(1+Parameters!$B$5, A10) -> 0.42409762 | J10: =H10*I10 -> 19417773 | K10: =SUM($G$2:G10) -> 1.5849033e+10 | L10: =F10*0.95 -> 1045595.9 | M10: =L10*IF(E10="",Parameters!$B$2,E10) -> 1.6729534e+09 | N10: =M10*0.0251 -> 41991131 | O10: =N10*I10 -> 17808339
A11: 10 | B11: 21000000 | C11: 1.988 | D11: 0.82 | E11: 1600 | F11: =IFERROR(B11*C11*IF(D11="", Parameters!$B$2, D11)/Parameters!$B$6, 0) -> 1100627.3 | G11: =F11*IF(E11="", Parameters!$B$2, E11) -> 1.7610036e+09 | H11: =G11*Parameters!$B$4 -> 45786094 | I11: =1/POWER(1+Parameters!$B$5, A11) -> 0.38554329 | J11: =H11*I11 -> 17652521 | K11: =SUM($G$2:G11) -> 1.7610036e+10 | L11: =F11*0.95 -> 1045595.9 | M11: =L11*IF(E11="",Parameters!$B$2,E11) -> 1.6729534e+09 | N11: =M11*0.0251 -> 41991131 | O11: =N11*I11 -> 16189399
A12: 11 | B12: 21000000 | C12: 1.988 | D12: 0.82 | E12: 1600 | F12: =IFERROR(B12*C12*IF(D12="", Parameters!$B$2, D12)/Parameters!$B$6, 0) -> 1100627.3 | G12: =F12*IF(E12="", Parameters!$B$2, E12) -> 1.7610036e+09 | H12: =G12*Parameters!$B$4 -> 45786094 | I12: =1/POWER(1+Parameters!$B$5, A12) -> 0.3504939 | J12: =H12*I12 -> 16047747 | K12: =SUM($G$2:G12) -> 1.937104e+10 | L12: =F12*0.95 -> 1045595.9 | M12: =L12*IF(E12="",Parameters!$B$2,E12) -> 1.6729534e+09 | N12: =M12*0.0251 -> 41991131 | O12: =N12*I12 -> 14717635
A13: 12 | B13: 21000000 | C13: 1.988 | D13: 0.82 | E13: 1600 | F13: =IFERROR(B13*C13*IF(D13="", Parameters!$B$2, D13)/Parameters!$B$6, 0) -> 1100627.3 | G13: =F13*IF(E13="", Parameters!$B$2, E13) -> 1.7610036e+09 | H13: =G13*Parameters!$B$4 -> 45786094 | I13: =1/POWER(1+Parameters!$B$5, A13) -> 0.31863082 | J13: =H13*I13 -> 14588861 | K13: =SUM($G$2:G13) -> 2.1132043e+10 | L13: =F13*0.95 -> 1045595.9 | M13: =L13*IF(E13="",Parameters!$B$2,E13) -> 1.6729534e+09 | N13: =M13*0.0251 -> 41991131 | O13: =N13*I13 -> 13379668
... A22: 21 | B22: 21000000 | C22: 1.988 | D22: 0.82 | E22: 1600 | F22: =IFERROR(B22*C22*IF(D22="", Parameters!$B$2, D22)/Parameters!$B$6, 0) -> 1100627.3 | G22: =F22*IF(E22="", Parameters!$B$2, E22) -> 1.7610036e+09 | H22: =G22*Parameters!$B$4 -> 45786094 | I22: =1/POWER(1+Parameters!$B$5, A22) -> 0.13513057 | J22: =H22*I22 -> 6187101 | K22: =SUM($G$2:G22) -> 3.6981076e+10 | L22: =F22*0.95 -> 1045595.9 | M22: =L22*IF(E22="",Parameters!$B$2,E22) -> 1.6729534e+09 | N22: =M22*0.0251 -> 41991131 | O22: =N22*I22 -> 5674285.5
F39: Totals / Key Outputs | G39: =SUM(G2:G33) -> 3.6981076e+10 | H39: =SUM(H2:H33) -> 9.6150797e+08 | J39: =SUM(J2:J22) -> 3.9598993e+08 | O39: =SUM(O2:O22) -> 3.6316846e+08
F40: Total Revenue (USD) | G40: =G39 -> 3.6981076e+10
F41: Total Severance Tax (USD) | G41: =H39 -> 9.6150797e+08
F42: PV(Severance Tax) (USD) | G42: =J39 -> 3.9598993e+08

Sheet schedule_12
A1: Year | B1: Ore (t) | C1: Grade (g/t) | D1: Recovery (override, optional) | E1: Metal Price (override, optional) | F1: Metal Produced (oz) | G1: Revenue (USD) | H1: Severance Tax (USD) | I1: Discount Factor | J1: PV(Severance Tax) (USD) | K1: Cumulative Revenue (USD) | L1: Payable Metal (oz) | M1: NSR ($) | N1: Royalty ($) | O1: PV(Royalty)
A2: 1 | B2: 15000000 | C2: 2.044 | D2: 0.82 | E2: 1600 | F2: =IFERROR(B2*C2*IF(D2="", Parameters!$B$2, D2)/Parameters!$B$6, 0) -> 808307.75 | G2: =F2*IF(E2="", Parameters!$B$2, E2) -> 1.2932924e+09 | H2: =G2*Parameters!$B$4 -> 33625602 | I2: =1/POWER(1+Parameters!$B$5, A2) -> 0.90909091 | J2: =H2*I2 -> 30568729 | K2: =SUM($G$2:G2) -> 1.2932924e+09 | L2: =F2*0.95 -> 767892.36 | M2: =L2*IF(E2="",Parameters!$B$2,E2) -> 1.2286278e+09 | N2: =M2*0.0251 -> 30838557 | O2: =N2*I2 -> 28035052
A3: 2 | B3: 15000000 | C3: 2.044 | D3: 0.82 | E3: 1600 | F3: =IFERROR(B3*C3*IF(D3="", Parameters!$B$2, D3)/Parameters!$B$6, 0) -> 808307.75 | G3: =F3*IF(E3="", Parameters!$B$2, E3) -> 1.2932924e+09 | H3: =G3*Parameters!$B$4 -> 33625602 | I3: =1/POWER(1+Parameters!$B$5, A3) -> 0.82644628 | J3: =H3*I3 -> 27789754 | K3: =SUM($G$2:G3) -> 2.5865848e+09 | L3: =F3*0.95 -> 767892.36 | M3: =L3*IF(E3="",Parameters!$B$2,E3) -> 1.2286278e+09 | N3: =M3*0.0251 -> 30838557 | O3: =N3*I3 -> 25486411
A4: 3 | B4: 15000000 | C4: 2.044 | D4: 0.82 | E4: 1600 | F4: =IFERROR(B4*C4*IF(D4="", Parameters!$B$2, D4)/Parameters!$B$6, 0) -> 808307.75 | G4: =F4*IF(E4="", Parameters!$B$2, E4) -> 1.2932924e+09 | H4: =G4*Parameters!$B$4 -> 33625602 | I4: =1/POWER(1+Parameters!$B$5, A4) -> 0.7513148 | J4: =H4*I4 -> 25263413 | K4: =SUM($G$2:G4) -> 3.8798772e+09 | L4: =F4*0.95 -> 767892.36 | M4: =L4*IF(E4="",Parameters!$B$2,E4) -> 1.2286278e+09 | N4: =M4*0.0251 -> 30838557 | O4: =N4*I4 -> 23169464
A5: 4 | B5: 15000000 | C5: 2.044 | D5: 0.82 | E5: 1600 | F5: =IFERROR(B5*C5*IF(D5="", Parameters!$B$2, D5)/Parameters!$B$6, 0) -> 808307.75 | G5: =F5*IF(E5="", Parameters!$B$2, E5) -> 1.2932924e+09 | H5: =G5*Parameters!$B$4 -> 33625602 | I5: =1/POWER(1+Parameters!$B$5, A5) -> 0.68301346 | J5: =H5*I5 -> 22966739 | K5: =SUM($G$2:G5) -> 5.1731696e+09 | L5: =F5*0.95 -> 767892.36 | M5: =L5*IF(E5="",Parameters!$B$2,E5) -> 1.2286278e+09 | N5: =M5*0.0251 -> 30838557 | O5: =N5*I5 -> 21063149
A6: 5 | B6: 15000000 | C6: 2.044 | D6: 0.82 | E6: 1600 | F6: =IFERROR(B6*C6*IF(D6="", Parameters!$B$2, D6)/Parameters!$B$6, 0) -> 808307.75 | G6: =F6*IF(E6="", Parameters!$B$2, E6) -> 1.2932924e+09 | H6: =G6*Parameters!$B$4 -> 33625602 | I6: =1/POWER(1+Parameters!$B$5, A6) -> 0.62092132 | J6: =H6*I6 -> 20878853 | K6: =SUM($G$2:G6) -> 6.466462e+09 | L6: =F6*0.95 -> 767892.36 | M6: =L6*IF(E6="",Parameters!$B$2,E6) -> 1.2286278e+09 | N6: =M6*0.0251 -> 30838557 | O6: =N6*I6 -> 19148318
A7: 6 | B7: 15000000 | C7: 2.044 | D7: 0.82 | E7: 1600 | F7: =IFERROR(B7*C7*IF(D7="", Parameters!$B$2, D7)/Parameters!$B$6, 0) -> 808307.75 | G7: =F7*IF(E7="", Parameters!$B$2, E7) -> 1.2932924e+09 | H7: =G7*Parameters!$B$4 -> 33625602 | I7: =1/POWER(1+Parameters!$B$5, A7) -> 0.56447393 | J7: =H7*I7 -> 18980776 | K7: =SUM($G$2:G7) -> 7.7597544e+09 | L7: =F7*0.95 -> 767892.36 | M7: =L7*IF(E7="",Parameters!$B$2,E7) -> 1.2286278e+09 | N7: =M7*0.0251 -> 30838557 | O7: =N7*I7 -> 17407562
A8: 7 | B8: 15000000 | C8: 2.044 | D8: 0.82 | E8: 1600 | F8: =IFERROR(B8*C8*IF(D8="", Parameters!$B$2, D8)/Parameters!$B$6, 0) -> 808307.75 | G8: =F8*IF(E8="", Parameters!$B$2, E8) -> 1.2932924e+09 | H8: =G8*Parameters!$B$4 -> 33625602 | I8: =1/POWER(1+Parameters!$B$5, A8) -> 0.51315812 | J8: =H8*I8 -> 17255251 | K8: =SUM($G$2:G8) -> 9.0530468e+09 | L8: =F8*0.95 -> 767892.36 | M8: =L8*IF(E8="",Parameters!$B$2,E8) -> 1.2286278e+09 | N8: =M8*0.0251 -> 30838557 | O8: =N8*I8 -> 15825056
A9: 8 | B9: 15000000 | C9: 2.044 | D9: 0.82 | E9: 1600 | F9: =IFERROR(B9*C9*IF(D9="", Parameters!$B$2, D9)/Parameters!$B$6, 0) -> 808307.75 | G9: =F9*IF(E9="", Parameters!$B$2, E9) -> 1.2932924e+09 | H9: =G9*Parameters!$B$4 -> 33625602 | I9: =1/POWER(1+Parameters!$B$5, A9) -> 0.46650738 | J9: =H9*I9 -> 15686592 | K9: =SUM($G$2:G9) -> 1.0346339e+10 | L9: =F9*0.95 -> 767892.36 | M9: =L9*IF(E9="",Parameters!$B$2,E9) -> 1.2286278e+09 | N9: =M9*0.0251 -> 30838557 | O9: =N9*I9 -> 14386415
A10: 9 | B10: 15000000 | C10: 2.044 | D10: 0.82 | E10: 1600 | F10: =IFERROR(B10*C10*IF(D10="", Parameters!$B$2, D10)/Parameters!$B$6, 0) -> 808307.75 | G10: =F10*IF(E10="", Parameters!$B$2, E10) -> 1.2932924e+09 | H10: =G10*Parameters!$B$4 -> 33625602 | I10: =1/POWER(1+Parameters!$B$5, A10) -> 0.42409762 | J10: =H10*I10 -> 14260538 | K10: =SUM($G$2:G10) -> 1.1639632e+10 | L10: =F10*0.95 -> 767892.36 | M10: =L10*IF(E10="",Parameters!$B$2,E10) -> 1.2286278e+09 | N10: =M10*0.0251 -> 30838557 | O10: =N10*I10 -> 13078559
A11: 10 | B11: 15000000 | C11: 2.044 | D11: 0.82 | E11: 1600 | F11: =IFERROR(B11*C11*IF(D11="", Parameters!$B$2, D11)/Parameters!$B$6, 0) -> 808307.75 | G11: =F11*IF(E11="", Parameters!$B$2, E11) -> 1.2932924e+09 | H11: =G11*Parameters!$B$4 -> 33625602 | I11: =1/POWER(1+Parameters!$B$5, A11) -> 0.38554329 | J11: =H11*I11 -> 12964125 | K11: =SUM($G$2:G11) -> 1.2932924e+10 | L11: =F11*0.95 -> 767892.36 | M11: =L11*IF(E11="",Parameters!$B$2,E11) -> 1.2286278e+09 | N11: =M11*0.0251 -> 30838557 | O11: =N11*I11 -> 11889599
A12: 11 | B12: 15000000 | C12: 2.044 | D12: 0.82 | E12: 1600 | F12: =IFERROR(B12*C12*IF(D12="", Parameters!$B$2, D12)/Parameters!$B$6, 0) -> 808307.75 | G12: =F12*IF(E12="", Parameters!$B$2, E12) -> 1.2932924e+09 | H12: =G12*Parameters!$B$4 -> 33625602 | I12: =1/POWER(1+Parameters!$B$5, A12) -> 0.3504939 | J12: =H12*I12 -> 11785568 | K12: =SUM($G$2:G12) -> 1.4226216e+10 | L12: =F12*0.95 -> 767892.36 | M12: =L12*IF(E12="",Parameters!$B$2,E12) -> 1.2286278e+09 | N12: =M12*0.0251 -> 30838557 | O12: =N12*I12 -> 10808726
A13: 12 | B13: 15000000 | C13: 2.044 | D13: 0.82 | E13: 1600 | F13: =IFERROR(B13*C13*IF(D13="", Parameters!$B$2, D13)/Parameters!$B$6, 0) -> 808307.75 | G13: =F13*IF(E13="", Parameters!$B$2, E13) -> 1.2932924e+09 | H13: =G13*Parameters!$B$4 -> 33625602 | I13: =1/POWER(1+Parameters!$B$5, A13) -> 0.31863082 | J13: =H13*I13 -> 10714153 | K13: =SUM($G$2:G13) -> 1.5519509e+10 | L13: =F13*0.95 -> 767892.36 | M13: =L13*IF(E13="",Parameters!$B$2,E13) -> 1.2286278e+09 | N13: =M13*0.0251 -> 30838557 | O13: =N13*I13 -> 9826114.7
... A27: 26 | B27: 15000000 | C27: 2.044 | D27: 0.82 | E27: 1600 | F27: =IFERROR(B27*C27*IF(D27="", Parameters!$B$2, D27)/Parameters!$B$6, 0) -> 808307.75 | G27: =F27*IF(E27="", Parameters!$B$2, E27) -> 1.2932924e+09 | H27: =G27*Parameters!$B$4 -> 33625602 | I27: =1/POWER(1+Parameters!$B$5, A27) -> 0.083905453 | J27: =H27*I27 -> 2821371.4 | K27: =SUM($G$2:G27) -> 3.3625602e+10 | L27: =F27*0.95 -> 767892.36 | M27: =L27*IF(E27="",Parameters!$B$2,E27) -> 1.2286278e+09 | N27: =M27*0.0251 -> 30838557 | O27: =N27*I27 -> 2587523.1
F39: Totals / Key Outputs | G39: =SUM(G2:G33) -> 3.3625602e+10 | H39: =SUM(H2:H33) -> 8.7426566e+08 | J39: =SUM(J2:J27) -> 3.0804231e+08 | O39: =SUM(O2:O27) -> 2.8251034e+08
F40: Total Revenue (USD) | G40: =G39 -> 3.3625602e+10
F41: Total Severance Tax (USD) | G41: =H39 -> 8.7426566e+08
F42: PV(Severance Tax) (USD) | G42: =J39 -> 3.0804231e+08

Sheet schedule_13
A1: Year | B1: Ore (t) | C1: Grade (g/t) | D1: Recovery (override, optional) | E1: Metal Price (override, optional) | F1: Metal Produced (oz) | G1: Revenue (USD) | H1: Severance Tax (USD) | I1: Discount Factor | J1: PV(Severance Tax) (USD) | K1: Cumulative Revenue (USD) | L1: Payable Metal (oz) | M1: NSR ($) | N1: Royalty ($) | O1: PV(Royalty)
A2: 1 | B2: 22000000 | C2: 1.948 | D2: 0.82 | E2: 1600 | F2: =IFERROR(B2*C2*IF(D2="", Parameters!$B$2, D2)/Parameters!$B$6, 0) -> 1129838.1 | G2: =F2*IF(E2="", Parameters!$B$2, E2) -> 1.807741e+09 | H2: =G2*Parameters!$B$4 -> 47001266 | I2: =1/POWER(1+Parameters!$B$5, A2) -> 0.90909091 | J2: =H2*I2 -> 42728423 | K2: =SUM($G$2:G2) -> 1.807741e+09 | L2: =F2*0.95 -> 1073346.2 | M2: =L2*IF(E2="",Parameters!$B$2,E2) -> 1.7173539e+09 | N2: =M2*0.0251 -> 43105584 | O2: =N2*I2 -> 39186895
A3: 2 | B3: 22000000 | C3: 1.948 | D3: 0.82 | E3: 1600 | F3: =IFERROR(B3*C3*IF(D3="", Parameters!$B$2, D3)/Parameters!$B$6, 0) -> 1129838.1 | G3: =F3*IF(E3="", Parameters!$B$2, E3) -> 1.807741e+09 | H3: =G3*Parameters!$B$4 -> 47001266 | I3: =1/POWER(1+Parameters!$B$5, A3) -> 0.82644628 | J3: =H3*I3 -> 38844021 | K3: =SUM($G$2:G3) -> 3.615482e+09 | L3: =F3*0.95 -> 1073346.2 | M3: =L3*IF(E3="",Parameters!$B$2,E3) -> 1.7173539e+09 | N3: =M3*0.0251 -> 43105584 | O3: =N3*I3 -> 35624450
A4: 3 | B4: 22000000 | C4: 1.948 | D4: 0.82 | E4: 1600 | F4: =IFERROR(B4*C4*IF(D4="", Parameters!$B$2, D4)/Parameters!$B$6, 0) -> 1129838.1 | G4: =F4*IF(E4="", Parameters!$B$2, E4) -> 1.807741e+09 | H4: =G4*Parameters!$B$4 -> 47001266 | I4: =1/POWER(1+Parameters!$B$5, A4) -> 0.7513148 | J4: =H4*I4 -> 35312747 | K4: =SUM($G$2:G4) -> 5.423223e+09 | L4: =F4*0.95 -> 1073346.2 | M4: =L4*IF(E4="",Parameters!$B$2,E4) -> 1.7173539e+09 | N4: =M4*0.0251 -> 43105584 | O4: =N4*I4 -> 32385863
A5: 4 | B5: 22000000 | C5: 1.948 | D5: 0.82 | E5: 1600 | F5: =IFERROR(B5*C5*IF(D5="", Parameters!$B$2, D5)/Parameters!$B$6, 0) -> 1129838.1 | G5: =F5*IF(E5="", Parameters!$B$2, E5) -> 1.807741e+09 | H5: =G5*Parameters!$B$4 -> 47001266 | I5: =1/POWER(1+Parameters!$B$5, A5) -> 0.68301346 | J5: =H5*I5 -> 32102497 | K5: =SUM($G$2:G5) -> 7.230964e+09 | L5: =F5*0.95 -> 1073346.2 | M5: =L5*IF(E5="",Parameters!$B$2,E5) -> 1.7173539e+09 | N5: =M5*0.0251 -> 43105584 | O5: =N5*I5 -> 29441694
A6: 5 | B6: 22000000 | C6: 1.948 | D6: 0.82 | E6: 1600 | F6: =IFERROR(B6*C6*IF(D6="", Parameters!$B$2, D6)/Parameters!$B$6, 0) -> 1129838.1 | G6: =F6*IF(E6="", Parameters!$B$2, E6) -> 1.807741e+09 | H6: =G6*Parameters!$B$4 -> 47001266 | I6: =1/POWER(1+Parameters!$B$5, A6) -> 0.62092132 | J6: =H6*I6 -> 29184088 | K6: =SUM($G$2:G6) -> 9.038705e+09 | L6: =F6*0.95 -> 1073346.2 | M6: =L6*IF(E6="",Parameters!$B$2,E6) -> 1.7173539e+09 | N6: =M6*0.0251 -> 43105584 | O6: =N6*I6 -> 26765176
A7: 6 | B7: 22000000 | C7: 1.948 | D7: 0.82 | E7: 1600 | F7: =IFERROR(B7*C7*IF(D7="", Parameters!$B$2, D7)/Parameters!$B$6, 0) -> 1129838.1 | G7: =F7*IF(E7="", Parameters!$B$2, E7) -> 1.807741e+09 | H7: =G7*Parameters!$B$4 -> 47001266 | I7: =1/POWER(1+Parameters!$B$5, A7) -> 0.56447393 | J7: =H7*I7 -> 26530989 | K7: =SUM($G$2:G7) -> 1.0846446e+10 | L7: =F7*0.95 -> 1073346.2 | M7: =L7*IF(E7="",Parameters!$B$2,E7) -> 1.7173539e+09 | N7: =M7*0.0251 -> 43105584 | O7: =N7*I7 -> 24331978
A8: 7 | B8: 22000000 | C8: 1.948 | D8: 0.82 | E8: 1600 | F8: =IFERROR(B8*C8*IF(D8="", Parameters!$B$2, D8)/Parameters!$B$6, 0) -> 1129838.1 | G8: =F8*IF(E8="", Parameters!$B$2, E8) -> 1.807741e+09 | H8: =G8*Parameters!$B$4 -> 47001266 | I8: =1/POWER(1+Parameters!$B$5, A8) -> 0.51315812 | J8: =H8*I8 -> 24119081 | K8: =SUM($G$2:G8) -> 1.2654187e+10 | L8: =F8*0.95 -> 1073346.2 | M8: =L8*IF(E8="",Parameters!$B$2,E8) -> 1.7173539e+09 | N8: =M8*0.0251 -> 43105584 | O8: =N8*I8 -> 22119980
A9: 8 | B9: 22000000 | C9: 1.948 | D9: 0.82 | E9: 1600 | F9: =IFERROR(B9*C9*IF(D9="", Parameters!$B$2, D9)/Parameters!$B$6, 0) -> 1129838.1 | G9: =F9*IF(E9="", Parameters!$B$2, E9) -> 1.807741e+09 | H9: =G9*Parameters!$B$4 -> 47001266 | I9: =1/POWER(1+Parameters!$B$5, A9) -> 0.46650738 | J9: =H9*I9 -> 21926437 | K9: =SUM($G$2:G9) -> 1.4461928e+10 | L9: =F9*0.95 -> 1073346.2 | M9: =L9*IF(E9="",Parameters!$B$2,E9) -> 1.7173539e+09 | N9: =M9*0.0251 -> 43105584 | O9: =N9*I9 -> 20109073
A10: 9 | B10: 22000000 | C10: 1.948 | D10: 0.82 | E10: 1600 | F10: =IFERROR(B10*C10*IF(D10="", Parameters!$B$2, D10)/Parameters!$B$6, 0) -> 1129838.1 | G10: =F10*IF(E10="", Parameters!$B$2, E10) -> 1.807741e+09 | H10: =G10*Parameters!$B$4 -> 47001266 | I10: =1/POWER(1+Parameters!$B$5, A10) -> 0.42409762 | J10: =H10*I10 -> 19933125 | K10: =SUM($G$2:G10) -> 1.6269669e+10 | L10: =F10*0.95 -> 1073346.2 | M10: =L10*IF(E10="",Parameters!$B$2,E10) -> 1.7173539e+09 | N10: =M10*0.0251 -> 43105584 | O10: =N10*I10 -> 18280976
A11: 10 | B11: 22000000 | C11: 1.948 | D11: 0.82 | E11: 1600 | F11: =IFERROR(B11*C11*IF(D11="", Parameters!$B$2, D11)/Parameters!$B$6, 0) -> 1129838.1 | G11: =F11*IF(E11="", Parameters!$B$2, E11) -> 1.807741e+09 | H11: =G11*Parameters!$B$4 -> 47001266 | I11: =1/POWER(1+Parameters!$B$5, A11) -> 0.38554329 | J11: =H11*I11 -> 18121023 | K11: =SUM($G$2:G11) -> 1.807741e+10 | L11: =F11*0.95 -> 1073346.2 | M11: =L11*IF(E11="",Parameters!$B$2,E11) -> 1.7173539e+09 | N11: =M11*0.0251 -> 43105584 | O11: =N11*I11 -> 16619069
A12: 11 | B12: 22000000 | C12: 1.948 | D12: 0.82 | E12: 1600 | F12: =IFERROR(B12*C12*IF(D12="", Parameters!$B$2, D12)/Parameters!$B$6, 0) -> 1129838.1 | G12: =F12*IF(E12="", Parameters!$B$2, E12) -> 1.807741e+09 | H12: =G12*Parameters!$B$4 -> 47001266 | I12: =1/POWER(1+Parameters!$B$5, A12) -> 0.3504939 | J12: =H12*I12 -> 16473657 | K12: =SUM($G$2:G12) -> 1.9885151e+10 | L12: =F12*0.95 -> 1073346.2 | M12: =L12*IF(E12="",Parameters!$B$2,E12) -> 1.7173539e+09 | N12: =M12*0.0251 -> 43105584 | O12: =N12*I12 -> 15108244
A13: 12 | B13: 22000000 | C13: 1.948 | D13: 0.82 | E13: 1600 | F13: =IFERROR(B13*C13*IF(D13="", Parameters!$B$2, D13)/Parameters!$B$6, 0) -> 1129838.1 | G13: =F13*IF(E13="", Parameters!$B$2, E13) -> 1.807741e+09 | H13: =G13*Parameters!$B$4 -> 47001266 | I13: =1/POWER(1+Parameters!$B$5, A13) -> 0.31863082 | J13: =H13*I13 -> 14976052 | K13: =SUM($G$2:G13) -> 2.1692892e+10 | L13: =F13*0.95 -> 1073346.2 | M13: =L13*IF(E13="",Parameters!$B$2,E13) -> 1.7173539e+09 | N13: =M13*0.0251 -> 43105584 | O13: =N13*I13 -> 13734767
... A22: 21 | B22: 22000000 | C22: 1.948 | D22: 0.82 | E22: 1600 | F22: =IFERROR(B22*C22*IF(D22="", Parameters!$B$2, D22)/Parameters!$B$6, 0) -> 1129838.1 | G22: =F22*IF(E22="", Parameters!$B$2, E22) -> 1.807741e+09 | H22: =G22*Parameters!$B$4 -> 47001266 | I22: =1/POWER(1+Parameters!$B$5, A22) -> 0.13513057 | J22: =H22*I22 -> 6351307.9 | K22: =SUM($G$2:G22) -> 3.7962561e+10 | L22: =F22*0.95 -> 1073346.2 | M22: =L22*IF(E22="",Parameters!$B$2,E22) -> 1.7173539e+09 | N22: =M22*0.0251 -> 43105584 | O22: =N22*I22 -> 5824882.2
F39: Totals / Key Outputs | G39: =SUM(G2:G33) -> 3.7962561e+10 | H39: =SUM(H2:H33) -> 9.8702658e+08 | J39: =SUM(J2:J22) -> 4.0649958e+08 | O39: =SUM(O2:O22) -> 3.7280702e+08
F40: Total Revenue (USD) | G40: =G39 -> 3.7962561e+10
F41: Total Severance Tax (USD) | G41: =H39 -> 9.8702658e+08
F42: PV(Severance Tax) (USD) | G42: =J39 -> 4.0649958e+08

Sheet schedule_14
A1: Year | B1: Ore (t) | C1: Grade (g/t) | D1: Recovery (override, optional) | E1: Metal Price (override, optional) | F1: Metal Produced (oz) | G1: Revenue (USD) | H1: Severance Tax (USD) | I1: Discount Factor | J1: PV(Severance Tax) (USD) | K1: Cumulative Revenue (USD) | L1: Payable Metal (oz) | M1: NSR ($) | N1: Royalty ($) | O1: PV(Royalty)
A2: 1 | B2: 24000000 | C2: 1.871 | D2: 0.82 | E2: 1600 | F2: =IFERROR(B2*C2*IF(D2="", Parameters!$B$2, D2)/Parameters!$B$6, 0) -> 1183830.8 | G2: =F2*IF(E2="", Parameters!$B$2, E2) -> 1.8941292e+09 | H2: =G2*Parameters!$B$4 -> 49247360 | I2: =1/POWER(1+Parameters!$B$5, A2) -> 0.90909091 | J2: =H2*I2 -> 44770327 | K2: =SUM($G$2:G2) -> 1.8941292e+09 | L2: =F2*0.95 -> 1124639.2 | M2: =L2*IF(E2="",Parameters!$B$2,E2) -> 1.7994228e+09 | N2: =M2*0.0251 -> 45165511 | O2: =N2*I2 -> 41059556
A3: 2 | B3: 24000000 | C3: 1.871 | D3: 0.82 | E3: 1600 | F3: =IFERROR(B3*C3*IF(D3="", Parameters!$B$2, D3)/Parameters!$B$6, 0) -> 1183830.8 | G3: =F3*IF(E3="", Parameters!$B$2, E3) -> 1.8941292e+09 | H3: =G3*Parameters!$B$4 -> 49247360 | I3: =1/POWER(1+Parameters!$B$5, A3) -> 0.82644628 | J3: =H3*I3 -> 40700297 | K3: =SUM($G$2:G3) -> 3.7882584e+09 | L3: =F3*0.95 -> 1124639.2 | M3: =L3*IF(E3="",Parameters!$B$2,E3) -> 1.7994228e+09 | N3: =M3*0.0251 -> 45165511 | O3: =N3*I3 -> 37326869
A4: 3 | B4: 24000000 | C4: 1.871 | D4: 0.82 | E4: 1600 | F4: =IFERROR(B4*C4*IF(D4="", Parameters!$B$2, D4)/Parameters!$B$6, 0) -> 1183830.8 | G4: =F4*IF(E4="", Parameters!$B$2, E4) -> 1.8941292e+09 | H4: =G4*Parameters!$B$4 -> 49247360 | I4: =1/POWER(1+Parameters!$B$5, A4) -> 0.7513148 | J4: =H4*I4 -> 37000270 | K4: =SUM($G$2:G4) -> 5.6823876e+09 | L4: =F4*0.95 -> 1124639.2 | M4: =L4*IF(E4="",Parameters!$B$2,E4) -> 1.7994228e+09 | N4: =M4*0.0251 -> 45165511 | O4: =N4*I4 -> 33933517
A5: 4 | B5: 24000000 | C5: 1.871 | D5: 0.82 | E5: 1600 | F5: =IFERROR(B5*C5*IF(D5="", Parameters!$B$2, D5)/Parameters!$B$6, 0) -> 1183830.8 | G5: =F5*IF(E5="", Parameters!$B$2, E5) -> 1.8941292e+09 | H5: =G5*Parameters!$B$4 -> 49247360 | I5: =1/POWER(1+Parameters!$B$5, A5) -> 0.68301346 | J5: =H5*I5 -> 33636609 | K5: =SUM($G$2:G5) -> 7.5765169e+09 | L5: =F5*0.95 -> 1124639.2 | M5: =L5*IF(E5="",Parameters!$B$2,E5) -> 1.7994228e+09 | N5: =M5*0.0251 -> 45165511 | O5: =N5*I5 -> 30848652
A6: 5 | B6: 24000000 | C6: 1.871 | D6: 0.82 | E6: 1600 | F6: =IFERROR(B6*C6*IF(D6="", Parameters!$B$2, D6)/Parameters!$B$6, 0) -> 1183830.8 | G6: =F6*IF(E6="", Parameters!$B$2, E6) -> 1.8941292e+09 | H6: =G6*Parameters!$B$4 -> 49247360 | I6: =1/POWER(1+Parameters!$B$5, A6) -> 0.62092132 | J6: =H6*I6 -> 30578736 | K6: =SUM($G$2:G6) -> 9.4706461e+09 | L6: =F6*0.95 -> 1124639.2 | M6: =L6*IF(E6="",Parameters!$B$2,E6) -> 1.7994228e+09 | N6: =M6*0.0251 -> 45165511 | O6: =N6*I6 -> 28044229
A7: 6 | B7: 24000000 | C7: 1.871 | D7: 0.82 | E7: 1600 | F7: =IFERROR(B7*C7*IF(D7="", Parameters!$B$2, D7)/Parameters!$B$6, 0) -> 1183830.8 | G7: =F7*IF(E7="", Parameters!$B$2, E7) -> 1.8941292e+09 | H7: =G7*Parameters!$B$4 -> 49247360 | I7: =1/POWER(1+Parameters!$B$5, A7) -> 0.56447393 | J7: =H7*I7 -> 27798851 | K7: =SUM($G$2:G7) -> 1.1364775e+10 | L7: =F7*0.95 -> 1124639.2 | M7: =L7*IF(E7="",Parameters!$B$2,E7) -> 1.7994228e+09 | N7: =M7*0.0251 -> 45165511 | O7: =N7*I7 -> 25494754
A8: 7 | B8: 24000000 | C8: 1.871 | D8: 0.82 | E8: 1600 | F8: =IFERROR(B8*C8*IF(D8="", Parameters!$B$2, D8)/Parameters!$B$6, 0) -> 1183830.8 | G8: =F8*IF(E8="", Parameters!$B$2, E8) -> 1.8941292e+09 | H8: =G8*Parameters!$B$4 -> 49247360 | I8: =1/POWER(1+Parameters!$B$5, A8) -> 0.51315812 | J8: =H8*I8 -> 25271682 | K8: =SUM($G$2:G8) -> 1.3258904e+10 | L8: =F8*0.95 -> 1124639.2 | M8: =L8*IF(E8="",Parameters!$B$2,E8) -> 1.7994228e+09 | N8: =M8*0.0251 -> 45165511 | O8: =N8*I8 -> 23177049
A9: 8 | B9: 24000000 | C9: 1.871 | D9: 0.82 | E9: 1600 | F9: =IFERROR(B9*C9*IF(D9="", Parameters!$B$2, D9)/Parameters!$B$6, 0) -> 1183830.8 | G9: =F9*IF(E9="", Parameters!$B$2, E9) -> 1.8941292e+09 | H9: =G9*Parameters!$B$4 -> 49247360 | I9: =1/POWER(1+Parameters!$B$5, A9) -> 0.46650738 | J9: =H9*I9 -> 22974257 | K9: =SUM($G$2:G9) -> 1.5153034e+10 | L9: =F9*0.95 -> 1124639.2 | M9: =L9*IF(E9="",Parameters!$B$2,E9) -> 1.7994228e+09 | N9: =M9*0.0251 -> 45165511 | O9: =N9*I9 -> 21070044
A10: 9 | B10: 24000000 | C10: 1.871 | D10: 0.82 | E10: 1600 | F10: =IFERROR(B10*C10*IF(D10="", Parameters!$B$2, D10)/Parameters!$B$6, 0) -> 1183830.8 | G10: =F10*IF(E10="", Parameters!$B$2, E10) -> 1.8941292e+09 | H10: =G10*Parameters!$B$4 -> 49247360 | I10: =1/POWER(1+Parameters!$B$5, A10) -> 0.42409762 | J10: =H10*I10 -> 20885688 | K10: =SUM($G$2:G10) -> 1.7047163e+10 | L10: =F10*0.95 -> 1124639.2 | M10: =L10*IF(E10="",Parameters!$B$2,E10) -> 1.7994228e+09 | N10: =M10*0.0251 -> 45165511 | O10: =N10*I10 -> 19154586
A11: 10 | B11: 24000000 | C11: 1.871 | D11: 0.82 | E11: 1600 | F11: =IFERROR(B11*C11*IF(D11="", Parameters!$B$2, D11)/Parameters!$B$6, 0) -> 1183830.8 | G11: =F11*IF(E11="", Parameters!$B$2, E11) -> 1.8941292e+09 | H11: =G11*Parameters!$B$4 -> 49247360 | I11: =1/POWER(1+Parameters!$B$5, A11) -> 0.38554329 | J11: =H11*I11 -> 18986989 | K11: =SUM($G$2:G11) -> 1.8941292e+10 | L11: =F11*0.95 -> 1124639.2 | M11: =L11*IF(E11="",Parameters!$B$2,E11) -> 1.7994228e+09 | N11: =M11*0.0251 -> 45165511 | O11: =N11*I11 -> 17413260
A12: 11 | B12: 24000000 | C12: 1.871 | D12: 0.82 | E12: 1600 | F12: =IFERROR(B12*C12*IF(D12="", Parameters!$B$2, D12)/Parameters!$B$6, 0) -> 1183830.8 | G12: =F12*IF(E12="", Parameters!$B$2, E12) -> 1.8941292e+09 | H12: =G12*Parameters!$B$4 -> 49247360 | I12: =1/POWER(1+Parameters!$B$5, A12) -> 0.3504939 | J12: =H12*I12 -> 17260899 | K12: =SUM($G$2:G12) -> 2.0835421e+10 | L12: =F12*0.95 -> 1124639.2 | M12: =L12*IF(E12="",Parameters!$B$2,E12) -> 1.7994228e+09 | N12: =M12*0.0251 -> 45165511 | O12: =N12*I12 -> 15830236
A13: 12 | B13: 24000000 | C13: 1.871 | D13: 0.82 | E13: 1600 | F13: =IFERROR(B13*C13*IF(D13="", Parameters!$B$2, D13)/Parameters!$B$6, 0) -> 1183830.8 | G13: =F13*IF(E13="", Parameters!$B$2, E13) -> 1.8941292e+09 | H13: =G13*Parameters!$B$4 -> 49247360 | I13: =1/POWER(1+Parameters!$B$5, A13) -> 0.31863082 | J13: =H13*I13 -> 15691726 | K13: =SUM($G$2:G13) -> 2.2729551e+10 | L13: =F13*0.95 -> 1124639.2 | M13: =L13*IF(E13="",Parameters!$B$2,E13) -> 1.7994228e+09 | N13: =M13*0.0251 -> 45165511 | O13: =N13*I13 -> 14391124
... A24: 23 | B24: 24000000 | C24: 1.871 | D24: 0.82 | E24: 1600 | F24: =IFERROR(B24*C24*IF(D24="", Parameters!$B$2, D24)/Parameters!$B$6, 0) -> 1183830.8 | G24: =F24*IF(E24="", Parameters!$B$2, E24) -> 1.8941292e+09 | H24: =G24*Parameters!$B$4 -> 49247360 | I24: =1/POWER(1+Parameters!$B$5, A24) -> 0.11167816 | J24: =H24*I24 -> 5499854.4 | K24: =SUM($G$2:G24) -> 4.3564972e+10 | L24: =F24*0.95 -> 1124639.2 | M24: =L24*IF(E24="",Parameters!$B$2,E24) -> 1.7994228e+09 | N24: =M24*0.0251 -> 45165511 | O24: =N24*I24 -> 5044001.1
F39: Totals / Key Outputs | G39: =SUM(G2:G33) -> 4.3564972e+10 | H39: =SUM(H2:H33) -> 1.1326893e+09 | J39: =SUM(J2:J24) -> 4.3747505e+08 | O39: =SUM(O2:O24) -> 4.012151e+08
F40: Total Revenue (USD) | G40: =G39 -> 4.3564972e+10
F41: Total Severance Tax (USD) | G41: =H39 -> 1.1326893e+09
F42: PV(Severance Tax) (USD) | G42: =J39 -> 4.3747505e+08

Sheet schedule_15
A1: Year | B1: Ore (t) | C1: Grade (g/t) | D1: Recovery (override, optional) | E1: Metal Price (override, optional) | F1: Metal Produced (oz) | G1: Revenue (USD) | H1: Severance Tax (USD) | I1: Discount Factor | J1: PV(Severance Tax) (USD) | K1: Cumulative Revenue (USD) | L1: Payable Metal (oz) | M1: NSR ($) | N1: Royalty ($) | O1: PV(Royalty)
A2: 1 | B2: 18000000 | C2: 1.896 | D2: 0.82 | E2: 1600 | F2: =IFERROR(B2*C2*IF(D2="", Parameters!$B$2, D2)/Parameters!$B$6, 0) -> 899736.69 | G2: =F2*IF(E2="", Parameters!$B$2, E2) -> 1.4395787e+09 | H2: =G2*Parameters!$B$4 -> 37429046 | I2: =1/POWER(1+Parameters!$B$5, A2) -> 0.90909091 | J2: =H2*I2 -> 34026406 | K2: =SUM($G$2:G2) -> 1.4395787e+09 | L2: =F2*0.95 -> 854749.85 | M2: =L2*IF(E2="",Parameters!$B$2,E2) -> 1.3675998e+09 | N2: =M2*0.0251 -> 34326754 | O2: =N2*I2 -> 31206140
A3: 2 | B3: 18000000 | C3: 1.896 | D3: 0.82 | E3: 1600 | F3: =IFERROR(B3*C3*IF(D3="", Parameters!$B$2, D3)/Parameters!$B$6, 0) -> 899736.69 | G3: =F3*IF(E3="", Parameters!$B$2, E3) -> 1.4395787e+09 | H3: =G3*Parameters!$B$4 -> 37429046 | I3: =1/POWER(1+Parameters!$B$5, A3) -> 0.82644628 | J3: =H3*I3 -> 30933096 | K3: =SUM($G$2:G3) -> 2.8791574e+09 | L3: =F3*0.95 -> 854749.85 | M3: =L3*IF(E3="",Parameters!$B$2,E3) -> 1.3675998e+09 | N3: =M3*0.0251 -> 34326754 | O3: =N3*I3 -> 28369218
A4: 3 | B4: 18000000 | C4: 1.896 | D4: 0.82 | E4: 1600 | F4: =IFERROR(B4*C4*IF(D4="", Parameters!$B$2, D4)/Parameters!$B$6, 0) -> 899736.69 | G4: =F4*IF(E4="", Parameters!$B$2, E4) -> 1.4395787e+09 | H4: =G4*Parameters!$B$4 -> 37429046 | I4: =1/POWER(1+Parameters!$B$5, A4) -> 0.7513148 | J4: =H4*I4 -> 28120996 | K4: =SUM($G$2:G4) -> 4.3187361e+09 | L4: =F4*0.95 -> 854749.85 | M4: =L4*IF(E4="",Parameters!$B$2,E4) -> 1.3675998e+09 | N4: =M4*0.0251 -> 34326754 | O4: =N4*I4 -> 25790198
A5: 4 | B5: 18000000 | C5: 1.896 | D5: 0.82 | E5: 1600 | F5: =IFERROR(B5*C5*IF(D5="", Parameters!$B$2, D5)/Parameters!$B$6, 0) -> 899736.69 | G5: =F5*IF(E5="", Parameters!$B$2, E5) -> 1.4395787e+09 | H5: =G5*Parameters!$B$4 -> 37429046 | I5: =1/POWER(1+Parameters!$B$5, A5) -> 0.68301346 | J5: =H5*I5 -> 25564542 | K5: =SUM($G$2:G5) -> 5.7583148e+09 | L5: =F5*0.95 -> 854749.85 | M5: =L5*IF(E5="",Parameters!$B$2,E5) -> 1.3675998e+09 | N5: =M5*0.0251 -> 34326754 | O5: =N5*I5 -> 23445635
A6: 5 | B6: 18000000 | C6: 1.896 | D6: 0.82 | E6: 1600 | F6: =IFERROR(B6*C6*IF(D6="", Parameters!$B$2, D6)/Parameters!$B$6, 0) -> 899736.69 | G6: =F6*IF(E6="", Parameters!$B$2, E6) -> 1.4395787e+09 | H6: =G6*Parameters!$B$4 -> 37429046 | I6: =1/POWER(1+Parameters!$B$5, A6) -> 0.62092132 | J6: =H6*I6 -> 23240493 | K6: =SUM($G$2:G6) -> 7.1978935e+09 | L6: =F6*0.95 -> 854749.85 | M6: =L6*IF(E6="",Parameters!$B$2,E6) -> 1.3675998e+09 | N6: =M6*0.0251 -> 34326754 | O6: =N6*I6 -> 21314214
A7: 6 | B7: 18000000 | C7: 1.896 | D7: 0.82 | E7: 1600 | F7: =IFERROR(B7*C7*IF(D7="", Parameters!$B$2, D7)/Parameters!$B$6, 0) -> 899736.69 | G7: =F7*IF(E7="", Parameters!$B$2, E7) -> 1.4395787e+09 | H7: =G7*Parameters!$B$4 -> 37429046 | I7: =1/POWER(1+Parameters!$B$5, A7) -> 0.56447393 | J7: =H7*I7 -> 21127721 | K7: =SUM($G$2:G7) -> 8.6374722e+09 | L7: =F7*0.95 -> 854749.85 | M7: =L7*IF(E7="",Parameters!$B$2,E7) -> 1.3675998e+09 | N7: =M7*0.0251 -> 34326754 | O7: =N7*I7 -> 19376558
A8: 7 | B8: 18000000 | C8: 1.896 | D8: 0.82 | E8: 1600 | F8: =IFERROR(B8*C8*IF(D8="", Parameters!$B$2, D8)/Parameters!$B$6, 0) -> 899736.69 | G8: =F8*IF(E8="", Parameters!$B$2, E8) -> 1.4395787e+09 | H8: =G8*Parameters!$B$4 -> 37429046 | I8: =1/POWER(1+Parameters!$B$5, A8) -> 0.51315812 | J8: =H8*I8 -> 19207019 | K8: =SUM($G$2:G8) -> 1.0077051e+10 | L8: =F8*0.95 -> 854749.85 | M8: =L8*IF(E8="",Parameters!$B$2,E8) -> 1.3675998e+09 | N8: =M8*0.0251 -> 34326754 | O8: =N8*I8 -> 17615053
A9: 8 | B9: 18000000 | C9: 1.896 | D9: 0.82 | E9: 1600 | F9: =IFERROR(B9*C9*IF(D9="", Parameters!$B$2, D9)/Parameters!$B$6, 0) -> 899736.69 | G9: =F9*IF(E9="", Parameters!$B$2, E9) -> 1.4395787e+09 | H9: =G9*Parameters!$B$4 -> 37429046 | I9: =1/POWER(1+Parameters!$B$5, A9) -> 0.46650738 | J9: =H9*I9 -> 17460926 | K9: =SUM($G$2:G9) -> 1.151663e+10 | L9: =F9*0.95 -> 854749.85 | M9: =L9*IF(E9="",Parameters!$B$2,E9) -> 1.3675998e+09 | N9: =M9*0.0251 -> 34326754 | O9: =N9*I9 -> 16013684
A10: 9 | B10: 18000000 | C10: 1.896 | D10: 0.82 | E10: 1600 | F10: =IFERROR(B10*C10*IF(D10="", Parameters!$B$2, D10)/Parameters!$B$6, 0) -> 899736.69 | G10: =F10*IF(E10="", Parameters!$B$2, E10) -> 1.4395787e+09 | H10: =G10*Parameters!$B$4 -> 37429046 | I10: =1/POWER(1+Parameters!$B$5, A10) -> 0.42409762 | J10: =H10*I10 -> 15873569 | K10: =SUM($G$2:G10) -> 1.2956208e+10 | L10: =F10*0.95 -> 854749.85 | M10: =L10*IF(E10="",Parameters!$B$2,E10) -> 1.3675998e+09 | N10: =M10*0.0251 -> 34326754 | O10: =N10*I10 -> 14557895
A11: 10 | B11: 18000000 | C11: 1.896 | D11: 0.82 | E11: 1600 | F11: =IFERROR(B11*C11*IF(D11="", Parameters!$B$2, D11)/Parameters!$B$6, 0) -> 899736.69 | G11: =F11*IF(E11="", Parameters!$B$2, E11) -> 1.4395787e+09 | H11: =G11*Parameters!$B$4 -> 37429046 | I11: =1/POWER(1+Parameters!$B$5, A11) -> 0.38554329 | J11: =H11*I11 -> 14430518 | K11: =SUM($G$2:G11) -> 1.4395787e+10 | L11: =F11*0.95 -> 854749.85 | M11: =L11*IF(E11="",Parameters!$B$2,E11) -> 1.3675998e+09 | N11: =M11*0.0251 -> 34326754 | O11: =N11*I11 -> 13234450
A12: 11 | B12: 18000000 | C12: 1.896 | D12: 0.82 | E12: 1600 | F12: =IFERROR(B12*C12*IF(D12="", Parameters!$B$2, D12)/Parameters!$B$6, 0) -> 899736.69 | G12: =F12*IF(E12="", Parameters!$B$2, E12) -> 1.4395787e+09 | H12: =G12*Parameters!$B$4 -> 37429046 | I12: =1/POWER(1+Parameters!$B$5, A12) -> 0.3504939 | J12: =H12*I12 -> 13118652 | K12: =SUM($G$2:G12) -> 1.5835366e+10 | L12: =F12*0.95 -> 854749.85 | M12: =L12*IF(E12="",Parameters!$B$2,E12) -> 1.3675998e+09 | N12: =M12*0.0251 -> 34326754 | O12: =N12*I12 -> 12031318
A13: 12 | B13: 18000000 | C13: 1.896 | D13: 0.82 | E13: 1600 | F13: =IFERROR(B13*C13*IF(D13="", Parameters!$B$2, D13)/Parameters!$B$6, 0) -> 899736.69 | G13: =F13*IF(E13="", Parameters!$B$2, E13) -> 1.4395787e+09 | H13: =G13*Parameters!$B$4 -> 37429046 | I13: =1/POWER(1+Parameters!$B$5, A13) -> 0.31863082 | J13: =H13*I13 -> 11926048 | K13: =SUM($G$2:G13) -> 1.7274944e+10 | L13: =F13*0.95 -> 854749.85 | M13: =L13*IF(E13="",Parameters!$B$2,E13) -> 1.3675998e+09 | N13: =M13*0.0251 -> 34326754 | O13: =N13*I13 -> 10937562
... A32: 31 | B32: 18000000 | C32: 1.896 | D32: 0.82 | E32: 1600 | F32: =IFERROR(B32*C32*IF(D32="", Parameters!$B$2, D32)/Parameters!$B$6, 0) -> 899736.69 | G32: =F32*IF(E32="", Parameters!$B$2, E32) -> 1.4395787e+09 | H32: =G32*Parameters!$B$4 -> 37429046 | I32: =1/POWER(1+Parameters!$B$5, A32) -> 0.052098685 | J32: =H32*I32 -> 1950004.1 | K32: =SUM($G$2:G32) -> 4.462694e+10 | L32: =F32*0.95 -> 854749.85 | M32: =L32*IF(E32="",Parameters!$B$2,E32) -> 1.3675998e+09 | N32: =M32*0.0251 -> 34326754 | O32: =N32*I32 -> 1788378.7
F39: Totals / Key Outputs | G39: =SUM(G2:G33) -> 4.462694e+10 | H39: =SUM(H2:H33) -> 1.1603004e+09 | J39: =SUM(J2:J32) -> 3.5479042e+08 | O39: =SUM(O2:O32) -> 3.2538375e+08
F40: Total Revenue (USD) | G40: =G39 -> 4.462694e+10
F41: Total Severance Tax (USD) | G41: =H39 -> 1.1603004e+09
F42: PV(Severance Tax) (USD) | G42: =J39 -> 3.5479042e+08

Sheet schedule_16
A1: Year | B1: Ore (t) | C1: Grade (g/t) | D1: Recovery (override, optional) | E1: Metal Price (override, optional) | F1: Metal Produced (oz) | G1: Revenue (USD) | H1: Severance Tax (USD) | I1: Discount Factor | J1: PV(Severance Tax) (USD) | K1: Cumulative Revenue (USD) | L1: Payable Metal (oz) | M1: NSR ($) | N1: Royalty ($) | O1: PV(Royalty)
A2: 1 | B2: 24000000 | C2: 1.941 | D2: 0.82 | E2: 1600 | F2: =IFERROR(B2*C2*IF(D2="", Parameters!$B$2, D2)/Parameters!$B$6, 0) -> 1228121.6 | G2: =F2*IF(E2="", Parameters!$B$2, E2) -> 1.9649946e+09 | H2: =G2*Parameters!$B$4 -> 51089858 | I2: =1/POWER(1+Parameters!$B$5, A2) -> 0.90909091 | J2: =H2*I2 -> 46445326 | K2: =SUM($G$2:G2) -> 1.9649946e+09 | L2: =F2*0.95 -> 1166715.5 | M2: =L2*IF(E2="",Parameters!$B$2,E2) -> 1.8667448e+09 | N2: =M2*0.0251 -> 46855295 | O2: =N2*I2 -> 42595723
A3: 2 | B3: 24000000 | C3: 1.941 | D3: 0.82 | E3: 1600 | F3: =IFERROR(B3*C3*IF(D3="", Parameters!$B$2, D3)/Parameters!$B$6, 0) -> 1228121.6 | G3: =F3*IF(E3="", Parameters!$B$2, E3) -> 1.9649946e+09 | H3: =G3*Parameters!$B$4 -> 51089858 | I3: =1/POWER(1+Parameters!$B$5, A3) -> 0.82644628 | J3: =H3*I3 -> 42223023 | K3: =SUM($G$2:G3) -> 3.9299891e+09 | L3: =F3*0.95 -> 1166715.5 | M3: =L3*IF(E3="",Parameters!$B$2,E3) -> 1.8667448e+09 | N3: =M3*0.0251 -> 46855295 | O3: =N3*I3 -> 38723384
A4: 3 | B4: 24000000 | C4: 1.941 | D4: 0.82 | E4: 1600 | F4: =IFERROR(B4*C4*IF(D4="", Parameters!$B$2, D4)/Parameters!$B$6, 0) -> 1228121.6 | G4: =F4*IF(E4="", Parameters!$B$2, E4) -> 1.9649946e+09 | H4: =G4*Parameters!$B$4 -> 51089858 | I4: =1/POWER(1+Parameters!$B$5, A4) -> 0.7513148 | J4: =H4*I4 -> 38384567 | K4: =SUM($G$2:G4) -> 5.8949837e+09 | L4: =F4*0.95 -> 1166715.5 | M4: =L4*IF(E4="",Parameters!$B$2,E4) -> 1.8667448e+09 | N4: =M4*0.0251 -> 46855295 | O4: =N4*I4 -> 35203077
A5: 4 | B5: 24000000 | C5: 1.941 | D5: 0.82 | E5: 1600 | F5: =IFERROR(B5*C5*IF(D5="", Parameters!$B$2, D5)/Parameters!$B$6, 0) -> 1228121.6 | G5: =F5*IF(E5="", Parameters!$B$2, E5) -> 1.9649946e+09 | H5: =G5*Parameters!$B$4 -> 51089858 | I5: =1/POWER(1+Parameters!$B$5, A5) -> 0.68301346 | J5: =H5*I5 -> 34895061 | K5: =SUM($G$2:G5) -> 7.8599782e+09 | L5: =F5*0.95 -> 1166715.5 | M5: =L5*IF(E5="",Parameters!$B$2,E5) -> 1.8667448e+09 | N5: =M5*0.0251 -> 46855295 | O5: =N5*I5 -> 32002797
A6: 5 | B6: 24000000 | C6: 1.941 | D6: 0.82 | E6: 1600 | F6: =IFERROR(B6*C6*IF(D6="", Parameters!$B$2, D6)/Parameters!$B$6, 0) -> 1228121.6 | G6: =F6*IF(E6="", Parameters!$B$2, E6) -> 1.9649946e+09 | H6: =G6*Parameters!$B$4 -> 51089858 | I6: =1/POWER(1+Parameters!$B$5, A6) -> 0.62092132 | J6: =H6*I6 -> 31722782 | K6: =SUM($G$2:G6) -> 9.8249728e+09 | L6: =F6*0.95 -> 1166715.5 | M6: =L6*IF(E6="",Parameters!$B$2,E6) -> 1.8667448e+09 | N6: =M6*0.0251 -> 46855295 | O6: =N6*I6 -> 29093452
A7: 6 | B7: 24000000 | C7: 1.941 | D7: 0.82 | E7: 1600 | F7: =IFERROR(B7*C7*IF(D7="", Parameters!$B$2, D7)/Parameters!$B$6, 0) -> 1228121.6 | G7: =F7*IF(E7="", Parameters!$B$2, E7) -> 1.9649946e+09 | H7: =G7*Parameters!$B$4 -> 51089858 | I7: =1/POWER(1+Parameters!$B$5, A7) -> 0.56447393 | J7: =H7*I7 -> 28838893 | K7: =SUM($G$2:G7) -> 1.1789967e+10 | L7: =F7*0.95 -> 1166715.5 | M7: =L7*IF(E7="",Parameters!$B$2,E7) -> 1.8667448e+09 | N7: =M7*0.0251 -> 46855295 | O7: =N7*I7 -> 26448593
A8: 7 | B8: 24000000 | C8: 1.941 | D8: 0.82 | E8: 1600 | F8: =IFERROR(B8*C8*IF(D8="", Parameters!$B$2, D8)/Parameters!$B$6, 0) -> 1228121.6 | G8: =F8*IF(E8="", Parameters!$B$2, E8) -> 1.9649946e+09 | H8: =G8*Parameters!$B$4 -> 51089858 | I8: =1/POWER(1+Parameters!$B$5, A8) -> 0.51315812 | J8: =H8*I8 -> 26217176 | K8: =SUM($G$2:G8) -> 1.3754962e+10 | L8: =F8*0.95 -> 1166715.5 | M8: =L8*IF(E8="",Parameters!$B$2,E8) -> 1.8667448e+09 | N8: =M8*0.0251 -> 46855295 | O8: =N8*I8 -> 24044175
A9: 8 | B9: 24000000 | C9: 1.941 | D9: 0.82 | E9: 1600 | F9: =IFERROR(B9*C9*IF(D9="", Parameters!$B$2, D9)/Parameters!$B$6, 0) -> 1228121.6 | G9: =F9*IF(E9="", Parameters!$B$2, E9) -> 1.9649946e+09 | H9: =G9*Parameters!$B$4 -> 51089858 | I9: =1/POWER(1+Parameters!$B$5, A9) -> 0.46650738 | J9: =H9*I9 -> 23833796 | K9: =SUM($G$2:G9) -> 1.5719956e+10 | L9: =F9*0.95 -> 1166715.5 | M9: =L9*IF(E9="",Parameters!$B$2,E9) -> 1.8667448e+09 | N9: =M9*0.0251 -> 46855295 | O9: =N9*I9 -> 21858341
A10: 9 | B10: 24000000 | C10: 1.941 | D10: 0.82 | E10: 1600 | F10: =IFERROR(B10*C10*IF(D10="", Parameters!$B$2, D10)/Parameters!$B$6, 0) -> 1228121.6 | G10: =F10*IF(E10="", Parameters!$B$2, E10) -> 1.9649946e+09 | H10: =G10*Parameters!$B$4 -> 51089858 | I10: =1/POWER(1+Parameters!$B$5, A10) -> 0.42409762 | J10: =H10*I10 -> 21667087 | K10: =SUM($G$2:G10) -> 1.7684951e+10 | L10: =F10*0.95 -> 1166715.5 | M10: =L10*IF(E10="",Parameters!$B$2,E10) -> 1.8667448e+09 | N10: =M10*0.0251 -> 46855295 | O10: =N10*I10 -> 19871219
A11: 10 | B11: 24000000 | C11: 1.941 | D11: 0.82 | E11: 1600 | F11: =IFERROR(B11*C11*IF(D11="", Parameters!$B$2, D11)/Parameters!$B$6, 0) -> 1228121.6 | G11: =F11*IF(E11="", Parameters!$B$2, E11) -> 1.9649946e+09 | H11: =G11*Parameters!$B$4 -> 51089858 | I11: =1/POWER(1+Parameters!$B$5, A11) -> 0.38554329 | J11: =H11*I11 -> 19697352 | K11: =SUM($G$2:G11) -> 1.9649946e+10 | L11: =F11*0.95 -> 1166715.5 | M11: =L11*IF(E11="",Parameters!$B$2,E11) -> 1.8667448e+09 | N11: =M11*0.0251 -> 46855295 | O11: =N11*I11 -> 18064745
A12: 11 | B12: 24000000 | C12: 1.941 | D12: 0.82 | E12: 1600 | F12: =IFERROR(B12*C12*IF(D12="", Parameters!$B$2, D12)/Parameters!$B$6, 0) -> 1228121.6 | G12: =F12*IF(E12="", Parameters!$B$2, E12) -> 1.9649946e+09 | H12: =G12*Parameters!$B$4 -> 51089858 | I12: =1/POWER(1+Parameters!$B$5, A12) -> 0.3504939 | J12: =H12*I12 -> 17906684 | K12: =SUM($G$2:G12) -> 2.161494e+10 | L12: =F12*0.95 -> 1166715.5 | M12: =L12*IF(E12="",Parameters!$B$2,E12) -> 1.8667448e+09 | N12: =M12*0.0251 -> 46855295 | O12: =N12*I12 -> 16422495
A13: 12 | B13: 24000000 | C13: 1.941 | D13: 0.82 | E13: 1600 | F13: =IFERROR(B13*C13*IF(D13="", Parameters!$B$2, D13)/Parameters!$B$6, 0) -> 1228121.6 | G13: =F13*IF(E13="", Parameters!$B$2, E13) -> 1.9649946e+09 | H13: =G13*Parameters!$B$4 -> 51089858 | I13: =1/POWER(1+Parameters!$B$5, A13) -> 0.31863082 | J13: =H13*I13 -> 16278803 | K13: =SUM($G$2:G13) -> 2.3579935e+10 | L13: =F13*0.95 -> 1166715.5 | M13: =L13*IF(E13="",Parameters!$B$2,E13) -> 1.8667448e+09 | N13: =M13*0.0251 -> 46855295 | O13: =N13*I13 -> 14929541
... A21: 20 | B21: 24000000 | C21: 1.941 | D21: 0.82 | E21: 1600 | F21: =IFERROR(B21*C21*IF(D21="", Parameters!$B$2, D21)/Parameters!$B$6, 0) -> 1228121.6 | G21: =F21*IF(E21="", Parameters!$B$2, E21) -> 1.9649946e+09 | H21: =G21*Parameters!$B$4 -> 51089858 | I21: =1/POWER(1+Parameters!$B$5, A21) -> 0.14864363 | J21: =H21*I21 -> 7594181.9 | K21: =SUM($G$2:G21) -> 3.9299891e+10 | L21: =F21*0.95 -> 1166715.5 | M21: =L21*IF(E21="",Parameters!$B$2,E21) -> 1.8667448e+09 | N21: =M21*0.0251 -> 46855295 | O21: =N21*I21 -> 6964741
F39: Totals / Key Outputs | G39: =SUM(G2:G33) -> 3.9299891e+10 | H39: =SUM(H2:H33) -> 1.0217972e+09 | J39: =SUM(J2:J21) -> 4.3495676e+08 | O39: =SUM(O2:O21) -> 3.9890554e+08
F40: Total Revenue (USD) | G40: =G39 -> 3.9299891e+10
F41: Total Severance Tax (USD) | G41: =H39 -> 1.0217972e+09
F42: PV(Severance Tax) (USD) | G42: =J39 -> 4.3495676e+08

Sheet schedule_17
A1: Year | B1: Ore (t) | C1: Grade (g/t) | D1: Recovery (override, optional) | E1: Metal Price (override, optional) | F1: Metal Produced (oz) | G1: Revenue (USD) | H1: Severance Tax (USD) | I1: Discount Factor | J1: PV(Severance Tax) (USD) | K1: Cumulative Revenue (USD) | L1: Payable Metal (oz) | M1: NSR ($) | N1: Royalty ($) | O1: PV(Royalty)
A2: 1 | B2: 17000000 | C2: 1.943 | D2: 0.82 | E2: 1600 | F2: =IFERROR(B2*C2*IF(D2="", Parameters!$B$2, D2)/Parameters!$B$6, 0) -> 870815.82 | G2: =F2*IF(E2="", Parameters!$B$2, E2) -> 1.3933053e+09 | H2: =G2*Parameters!$B$4 -> 36225938 | I2: =1/POWER(1+Parameters!$B$5, A2) -> 0.90909091 | J2: =H2*I2 -> 32932671 | K2: =SUM($G$2:G2) -> 1.3933053e+09 | L2: =F2*0.95 -> 827275.03 | M2: =L2*IF(E2="",Parameters!$B$2,E2) -> 1.3236401e+09 | N2: =M2*0.0251 -> 33223365 | O2: =N2*I2 -> 30203059
A3: 2 | B3: 17000000 | C3: 1.943 | D3: 0.82 | E3: 1600 | F3: =IFERROR(B3*C3*IF(D3="", Parameters!$B$2, D3)/Parameters!$B$6, 0) -> 870815.82 | G3: =F3*IF(E3="", Parameters!$B$2, E3) -> 1.3933053e+09 | H3: =G3*Parameters!$B$4 -> 36225938 | I3: =1/POWER(1+Parameters!$B$5, A3) -> 0.82644628 | J3: =H3*I3 -> 29938792 | K3: =SUM($G$2:G3) -> 2.7866106e+09 | L3: =F3*0.95 -> 827275.03 | M3: =L3*IF(E3="",Parameters!$B$2,E3) -> 1.3236401e+09 | N3: =M3*0.0251 -> 33223365 | O3: =N3*I3 -> 27457327
A4: 3 | B4: 17000000 | C4: 1.943 | D4: 0.82 | E4: 1600 | F4: =IFERROR(B4*C4*IF(D4="", Parameters!$B$2, D4)/Parameters!$B$6, 0) -> 870815.82 | G4: =F4*IF(E4="", Parameters!$B$2, E4) -> 1.3933053e+09 | H4: =G4*Parameters!$B$4 -> 36225938 | I4: =1/POWER(1+Parameters!$B$5, A4) -> 0.7513148 | J4: =H4*I4 -> 27217084 | K4: =SUM($G$2:G4) -> 4.179916e+09 | L4: =F4*0.95 -> 827275.03 | M4: =L4*IF(E4="",Parameters!$B$2,E4) -> 1.3236401e+09 | N4: =M4*0.0251 -> 33223365 | O4: =N4*I4 -> 24961206
A5: 4 | B5: 17000000 | C5: 1.943 | D5: 0.82 | E5: 1600 | F5: =IFERROR(B5*C5*IF(D5="", Parameters!$B$2, D5)/Parameters!$B$6, 0) -> 870815.82 | G5: =F5*IF(E5="", Parameters!$B$2, E5) -> 1.3933053e+09 | H5: =G5*Parameters!$B$4 -> 36225938 | I5: =1/POWER(1+Parameters!$B$5, A5) -> 0.68301346 | J5: =H5*I5 -> 24742803 | K5: =SUM($G$2:G5) -> 5.5732213e+09 | L5: =F5*0.95 -> 827275.03 | M5: =L5*IF(E5="",Parameters!$B$2,E5) -> 1.3236401e+09 | N5: =M5*0.0251 -> 33223365 | O5: =N5*I5 -> 22692006
A6: 5 | B6: 17000000 | C6: 1.943 | D6: 0.82 | E6: 1600 | F6: =IFERROR(B6*C6*IF(D6="", Parameters!$B$2, D6)/Parameters!$B$6, 0) -> 870815.82 | G6: =F6*IF(E6="", Parameters!$B$2, E6) -> 1.3933053e+09 | H6: =G6*Parameters!$B$4 -> 36225938 | I6: =1/POWER(1+Parameters!$B$5, A6) -> 0.62092132 | J6: =H6*I6 -> 22493458 | K6: =SUM($G$2:G6) -> 6.9665266e+09 | L6: =F6*0.95 -> 827275.03 | M6: =L6*IF(E6="",Parameters!$B$2,E6) -> 1.3236401e+09 | N6: =M6*0.0251 -> 33223365 | O6: =N6*I6 -> 20629096
A7: 6 | B7: 17000000 | C7: 1.943 | D7: 0.82 | E7: 1600 | F7: =IFERROR(B7*C7*IF(D7="", Parameters!$B$2, D7)/Parameters!$B$6, 0) -> 870815.82 | G7: =F7*IF(E7="", Parameters!$B$2, E7) -> 1.3933053e+09 | H7: =G7*Parameters!$B$4 -> 36225938 | I7: =1/POWER(1+Parameters!$B$5, A7) -> 0.56447393 | J7: =H7*I7 -> 20448598 | K7: =SUM($G$2:G7) -> 8.3598319e+09 | L7: =F7*0.95 -> 827275.03 | M7: =L7*IF(E7="",Parameters!$B$2,E7) -> 1.3236401e+09 | N7: =M7*0.0251 -> 33223365 | O7: =N7*I7 -> 18753724
A8: 7 | B8: 17000000 | C8: 1.943 | D8: 0.82 | E8: 1600 | F8: =IFERROR(B8*C8*IF(D8="", Parameters!$B$2, D8)/Parameters!$B$6, 0) -> 870815.82 | G8: =F8*IF(E8="", Parameters!$B$2, E8) -> 1.3933053e+09 | H8: =G8*Parameters!$B$4 -> 36225938 | I8: =1/POWER(1+Parameters!$B$5, A8) -> 0.51315812 | J8: =H8*I8 -> 18589634 | K8: =SUM($G$2:G8) -> 9.7531372e+09 | L8: =F8*0.95 -> 827275.03 | M8: =L8*IF(E8="",Parameters!$B$2,E8) -> 1.3236401e+09 | N8: =M8*0.0251 -> 33223365 | O8: =N8*I8 -> 17048840
A9: 8 | B9: 17000000 | C9: 1.943 | D9: 0.82 | E9: 1600 | F9: =IFERROR(B9*C9*IF(D9="", Parameters!$B$2, D9)/Parameters!$B$6, 0) -> 870815.82 | G9: =F9*IF(E9="", Parameters!$B$2, E9) -> 1.3933053e+09 | H9: =G9*Parameters!$B$4 -> 36225938 | I9: =1/POWER(1+Parameters!$B$5, A9) -> 0.46650738 | J9: =H9*I9 -> 16899668 | K9: =SUM($G$2:G9) -> 1.1146443e+10 | L9: =F9*0.95 -> 827275.03 | M9: =L9*IF(E9="",Parameters!$B$2,E9) -> 1.3236401e+09 | N9: =M9*0.0251 -> 33223365 | O9: =N9*I9 -> 15498945
A10: 9 | B10: 17000000 | C10: 1.943 | D10: 0.82 | E10: 1600 | F10: =IFERROR(B10*C10*IF(D10="", Parameters!$B$2, D10)/Parameters!$B$6, 0) -> 870815.82 | G10: =F10*IF(E10="", Parameters!$B$2, E10) -> 1.3933053e+09 | H10: =G10*Parameters!$B$4 -> 36225938 | I10: =1/POWER(1+Parameters!$B$5, A10) -> 0.42409762 | J10: =H10*I10 -> 15363334 | K10: =SUM($G$2:G10) -> 1.2539748e+10 | L10: =F10*0.95 -> 827275.03 | M10: =L10*IF(E10="",Parameters!$B$2,E10) -> 1.3236401e+09 | N10: =M10*0.0251 -> 33223365 | O10: =N10*I10 -> 14089950
A11: 10 | B11: 17000000 | C11: 1.943 | D11: 0.82 | E11: 1600 | F11: =IFERROR(B11*C11*IF(D11="", Parameters!$B$2, D11)/Parameters!$B$6, 0) -> 870815.82 | G11: =F11*IF(E11="", Parameters!$B$2, E11) -> 1.3933053e+09 | H11: =G11*Parameters!$B$4 -> 36225938 | I11: =1/POWER(1+Parameters!$B$5, A11) -> 0.38554329 | J11: =H11*I11 -> 13966667 | K11: =SUM($G$2:G11) -> 1.3933053e+10 | L11: =F11*0.95 -> 827275.03 | M11: =L11*IF(E11="",Parameters!$B$2,E11) -> 1.3236401e+09 | N11: =M11*0.0251 -> 33223365 | O11: =N11*I11 -> 12809046
A12: 11 | B12: 17000000 | C12: 1.943 | D12: 0.82 | E12: 1600 | F12: =IFERROR(B12*C12*IF(D12="", Parameters!$B$2, D12)/Parameters!$B$6, 0) -> 870815.82 | G12: =F12*IF(E12="", Parameters!$B$2, E12) -> 1.3933053e+09 | H12: =G12*Parameters!$B$4 -> 36225938 | I12: =1/POWER(1+Parameters!$B$5, A12) -> 0.3504939 | J12: =H12*I12 -> 12696970 | K12: =SUM($G$2:G12) -> 1.5326359e+10 | L12: =F12*0.95 -> 827275.03 | M12: =L12*IF(E12="",Parameters!$B$2,E12) -> 1.3236401e+09 | N12: =M12*0.0251 -> 33223365 | O12: =N12*I12 -> 11644587
A13: 12 | B13: 17000000 | C13: 1.943 | D13: 0.82 | E13: 1600 | F13: =IFERROR(B13*C13*IF(D13="", Parameters!$B$2, D13)/Parameters!$B$6, 0) -> 870815.82 | G13: =F13*IF(E13="", Parameters!$B$2, E13) -> 1.3933053e+09 | H13: =G13*Parameters!$B$4 -> 36225938 | I13: =1/POWER(1+Parameters!$B$5, A13) -> 0.31863082 | J13: =H13*I13 -> 11542700 | K13: =SUM($G$2:G13) -> 1.6719664e+10 | L13: =F13*0.95 -> 827275.03 | M13: =L13*IF(E13="",Parameters!$B$2,E13) -> 1.3236401e+09 | N13: =M13*0.0251 -> 33223365 | O13: =N13*I13 -> 10585988
... A29: 28 | B29: 17000000 | C29: 1.943 | D29: 0.82 | E29: 1600 | F29: =IFERROR(B29*C29*IF(D29="", Parameters!$B$2, D29)/Parameters!$B$6, 0) -> 870815.82 | G29: =F29*IF(E29="", Parameters!$B$2, E29) -> 1.3933053e+09 | H29: =G29*Parameters!$B$4 -> 36225938 | I29: =1/POWER(1+Parameters!$B$5, A29) -> 0.069343349 | J29: =H29*I29 -> 2512027.9 | K29: =SUM($G$2:G29) -> 3.9012549e+10 | L29: =F29*0.95 -> 827275.03 | M29: =L29*IF(E29="",Parameters!$B$2,E29) -> 1.3236401e+09 | N29: =M29*0.0251 -> 33223365 | O29: =N29*I29 -> 2303819.4
F39: Totals / Key Outputs | G39: =SUM(G2:G33) -> 3.9012549e+10 | H39: =SUM(H2:H33) -> 1.0143263e+09 | J39: =SUM(J2:J29) -> 3.371391e+08 | O39: =SUM(O2:O29) -> 3.0919546e+08
F40: Total Revenue (USD) | G40: =G39 -> 3.9012549e+10
F41: Total Severance Tax (USD) | G41: =H39 -> 1.0143263e+09
F42: PV(Severance Tax) (USD) | G42: =J39 -> 3.371391e+08

Sheet schedule_18
A1: Year | B1: Ore (t) | C1: Grade (g/t) | D1: Recovery (override, optional) | E1: Metal Price (override, optional) | F1: Metal Produced (oz) | G1: Revenue (USD) | H1: Severance Tax (USD) | I1: Discount Factor | J1: PV(Severance Tax) (USD) | K1: Cumulative Revenue (USD) | L1: Payable Metal (oz) | M1: NSR ($) | N1: Royalty ($) | O1: PV(Royalty)
A2: 1 | B2: 18000000 | C2: 1.859 | D2: 0.82 | E2: 1600 | F2: =IFERROR(B2*C2*IF(D2="", Parameters!$B$2, D2)/Parameters!$B$6, 0) -> 882178.53 | G2: =F2*IF(E2="", Parameters!$B$2, E2) -> 1.4114857e+09 | H2: =G2*Parameters!$B$4 -> 36698627 | I2: =1/POWER(1+Parameters!$B$5, A2) -> 0.90909091 | J2: =H2*I2 -> 33362388 | K2: =SUM($G$2:G2) -> 1.4114857e+09 | L2: =F2*0.95 -> 838069.61 | M2: =L2*IF(E2="",Parameters!$B$2,E2) -> 1.3409114e+09 | N2: =M2*0.0251 -> 33656875 | O2: =N2*I2 -> 30597159
A3: 2 | B3: 18000000 | C3: 1.859 | D3: 0.82 | E3: 1600 | F3: =IFERROR(B3*C3*IF(D3="", Parameters!$B$2, D3)/Parameters!$B$6, 0) -> 882178.53 | G3: =F3*IF(E3="", Parameters!$B$2, E3) -> 1.4114857e+09 | H3: =G3*Parameters!$B$4 -> 36698627 | I3: =1/POWER(1+Parameters!$B$5, A3) -> 0.82644628 | J3: =H3*I3 -> 30329444 | K3: =SUM($G$2:G3) -> 2.8229713e+09 | L3: =F3*0.95 -> 838069.61 | M3: =L3*IF(E3="",Parameters!$B$2,E3) -> 1.3409114e+09 | N3: =M3*0.0251 -> 33656875 | O3: =N3*I3 -> 27815599
A4: 3 | B4: 18000000 | C4: 1.859 | D4: 0.82 | E4: 1600 | F4: =IFERROR(B4*C4*IF(D4="", Parameters!$B$2, D4)/Parameters!$B$6, 0) -> 882178.53 | G4: =F4*IF(E4="", Parameters!$B$2, E4) -> 1.4114857e+09 | H4: =G4*Parameters!$B$4 -> 36698627 | I4: =1/POWER(1+Parameters!$B$5, A4) -> 0.7513148 | J4: =H4*I4 -> 27572222 | K4: =SUM($G$2:G4) -> 4.234457e+09 | L4: =F4*0.95 -> 838069.61 | M4: =L4*IF(E4="",Parameters!$B$2,E4) -> 1.3409114e+09 | N4: =M4*0.0251 -> 33656875 | O4: =N4*I4 -> 25286909
A5: 4 | B5: 18000000 | C5: 1.859 | D5: 0.82 | E5: 1600 | F5: =IFERROR(B5*C5*IF(D5="", Parameters!$B$2, D5)/Parameters!$B$6, 0) -> 882178.53 | G5: =F5*IF(E5="", Parameters!$B$2, E5) -> 1.4114857e+09 | H5: =G5*Parameters!$B$4 -> 36698627 | I5: =1/POWER(1+Parameters!$B$5, A5) -> 0.68301346 | J5: =H5*I5 -> 25065656 | K5: =SUM($G$2:G5) -> 5.6459426e+09 | L5: =F5*0.95 -> 838069.61 | M5: =L5*IF(E5="",Parameters!$B$2,E5) -> 1.3409114e+09 | N5: =M5*0.0251 -> 33656875 | O5: =N5*I5 -> 22988099
A6: 5 | B6: 18000000 | C6: 1.859 | D6: 0.82 | E6: 1600 | F6: =IFERROR(B6*C6*IF(D6="", Parameters!$B$2, D6)/Parameters!$B$6, 0) -> 882178.53 | G6: =F6*IF(E6="", Parameters!$B$2, E6) -> 1.4114857e+09 | H6: =G6*Parameters!$B$4 -> 36698627 | I6: =1/POWER(1+Parameters!$B$5, A6) -> 0.62092132 | J6: =H6*I6 -> 22786960 | K6: =SUM($G$2:G6) -> 7.0574283e+09 | L6: =F6*0.95 -> 838069.61 | M6: =L6*IF(E6="",Parameters!$B$2,E6) -> 1.3409114e+09 | N6: =M6*0.0251 -> 33656875 | O6: =N6*I6 -> 20898272
A7: 6 | B7: 18000000 | C7: 1.859 | D7: 0.82 | E7: 1600 | F7: =IFERROR(B7*C7*IF(D7="", Parameters!$B$2, D7)/Parameters!$B$6, 0) -> 882178.53 | G7: =F7*IF(E7="", Parameters!$B$2, E7) -> 1.4114857e+09 | H7: =G7*Parameters!$B$4 -> 36698627 | I7: =1/POWER(1+Parameters!$B$5, A7) -> 0.56447393 | J7: =H7*I7 -> 20715418 | K7: =SUM($G$2:G7) -> 8.4689139e+09 | L7: =F7*0.95 -> 838069.61 | M7: =L7*IF(E7="",Parameters!$B$2,E7) -> 1.3409114e+09 | N7: =M7*0.0251 -> 33656875 | O7: =N7*I7 -> 18998429
A8: 7 | B8: 18000000 | C8: 1.859 | D8: 0.82 | E8: 1600 | F8: =IFERROR(B8*C8*IF(D8="", Parameters!$B$2, D8)/Parameters!$B$6, 0) -> 882178.53 | G8: =F8*IF(E8="", Parameters!$B$2, E8) -> 1.4114857e+09 | H8: =G8*Parameters!$B$4 -> 36698627 | I8: =1/POWER(1+Parameters!$B$5, A8) -> 0.51315812 | J8: =H8*I8 -> 18832198 | K8: =SUM($G$2:G8) -> 9.8803996e+09 | L8: =F8*0.95 -> 838069.61 | M8: =L8*IF(E8="",Parameters!$B$2,E8) -> 1.3409114e+09 | N8: =M8*0.0251 -> 33656875 | O8: =N8*I8 -> 17271299
A9: 8 | B9: 18000000 | C9: 1.859 | D9: 0.82 | E9: 1600 | F9: =IFERROR(B9*C9*IF(D9="", Parameters!$B$2, D9)/Parameters!$B$6, 0) -> 882178.53 | G9: =F9*IF(E9="", Parameters!$B$2, E9) -> 1.4114857e+09 | H9: =G9*Parameters!$B$4 -> 36698627 | I9: =1/POWER(1+Parameters!$B$5, A9) -> 0.46650738 | J9: =H9*I9 -> 17120180 | K9: =SUM($G$2:G9) -> 1.1291885e+10 | L9: =F9*0.95 -> 838069.61 | M9: =L9*IF(E9="",Parameters!$B$2,E9) -> 1.3409114e+09 | N9: =M9*0.0251 -> 33656875 | O9: =N9*I9 -> 15701181
A10: 9 | B10: 18000000 | C10: 1.859 | D10: 0.82 | E10: 1600 | F10: =IFERROR(B10*C10*IF(D10="", Parameters!$B$2, D10)/Parameters!$B$6, 0) -> 882178.53 | G10: =F10*IF(E10="", Parameters!$B$2, E10) -> 1.4114857e+09 | H10: =G10*Parameters!$B$4 -> 36698627 | I10: =1/POWER(1+Parameters!$B$5, A10) -> 0.42409762 | J10: =H10*I10 -> 15563800 | K10: =SUM($G$2:G10) -> 1.2703371e+10 | L10: =F10*0.95 -> 838069.61 | M10: =L10*IF(E10="",Parameters!$B$2,E10) -> 1.3409114e+09 | N10: =M10*0.0251 -> 33656875 | O10: =N10*I10 -> 14273801
A11: 10 | B11: 18000000 | C11: 1.859 | D11: 0.82 | E11: 1600 | F11: =IFERROR(B11*C11*IF(D11="", Parameters!$B$2, D11)/Parameters!$B$6, 0) -> 882178.53 | G11: =F11*IF(E11="", Parameters!$B$2, E11) -> 1.4114857e+09 | H11: =G11*Parameters!$B$4 -> 36698627 | I11: =1/POWER(1+Parameters!$B$5, A11) -> 0.38554329 | J11: =H11*I11 -> 14148909 | K11: =SUM($G$2:G11) -> 1.4114857e+10 | L11: =F11*0.95 -> 838069.61 | M11: =L11*IF(E11="",Parameters!$B$2,E11) -> 1.3409114e+09 | N11: =M11*0.0251 -> 33656875 | O11: =N11*I11 -> 12976182
A12: 11 | B12: 18000000 | C12: 1.859 | D12: 0.82 | E12: 1600 | F12: =IFERROR(B12*C12*IF(D12="", Parameters!$B$2, D12)/Parameters!$B$6, 0) -> 882178.53 | G12: =F12*IF(E12="", Parameters!$B$2, E12) -> 1.4114857e+09 | H12: =G12*Parameters!$B$4 -> 36698627 | I12: =1/POWER(1+Parameters!$B$5, A12) -> 0.3504939 | J12: =H12*I12 -> 12862645 | K12: =SUM($G$2:G12) -> 1.5526342e+10 | L12: =F12*0.95 -> 838069.61 | M12: =L12*IF(E12="",Parameters!$B$2,E12) -> 1.3409114e+09 | N12: =M12*0.0251 -> 33656875 | O12: =N12*I12 -> 11796529
A13: 12 | B13: 18000000 | C13: 1.859 | D13: 0.82 | E13: 1600 | F13: =IFERROR(B13*C13*IF(D13="", Parameters!$B$2, D13)/Parameters!$B$6, 0) -> 882178.53 | G13: =F13*IF(E13="", Parameters!$B$2, E13) -> 1.4114857e+09 | H13: =G13*Parameters!$B$4 -> 36698627 | I13: =1/POWER(1+Parameters!$B$5, A13) -> 0.31863082 | J13: =H13*I13 -> 11693314 | K13: =SUM($G$2:G13) -> 1.6937828e+10 | L13: =F13*0.95 -> 838069.61 | M13: =L13*IF(E13="",Parameters!$B$2,E13) -> 1.3409114e+09 | N13: =M13*0.0251 -> 33656875 | O13: =N13*I13 -> 10724118
... A35: 34 | B35: 18000000 | C35: 1.859 | D35: 0.82 | E35: 1600 | F35: =IFERROR(B35*C35*IF(D35="", Parameters!$B$2, D35)/Parameters!$B$6, 0) -> 882178.53 | G35: =F35*IF(E35="", Parameters!$B$2, E35) -> 1.4114857e+09 | H35: =G35*Parameters!$B$4 -> 36698627 | I35: =1/POWER(1+Parameters!$B$5, A35) -> 0.039142513 | J35: =H35*I35 -> 1436476.5 | K35: =SUM($G$2:G35) -> 4.7990512e+10 | L35: =F35*0.95 -> 838069.61 | M35: =L35*IF(E35="",Parameters!$B$2,E35) -> 1.3409114e+09 | N35: =M35*0.0251 -> 33656875 | O35: =N35*I35 -> 1317414.7
F39: Totals / Key Outputs | G39: =SUM(G2:G35) -> 4.7990512e+10 | H39: =SUM(H2:H35) -> 1.2477533e+09 | J39: =SUM(J2:J35) -> 3.526215e+08 | O39: =SUM(O2:O35) -> 3.2339461e+08
F40: Total Revenue (USD) | G40: =G39 -> 4.7990512e+10
F41: Total Severance Tax (USD) | G41: =H39 -> 1.2477533e+09
F42: PV(Severance Tax) (USD) | G42: =J39 -> 3.526215e+08

Sheet schedule_19
A1: Year | B1: Ore (t) | C1: Grade (g/t) | D1: Recovery (override, optional) | E1: Metal Price (override, optional) | F1: Metal Produced (oz) | G1: Revenue (USD) | H1: Severance Tax (USD) | I1: Discount Factor | J1: PV(Severance Tax) (USD) | K1: Cumulative Revenue (USD) | L1: Payable Metal (oz) | M1: NSR ($) | N1: Royalty ($) | O1: PV(Royalty)
A2: 1 | B2: 19000000 | C2: 1.933 | D2: 0.82 | E2: 1600 | F2: =IFERROR(B2*C2*IF(D2="", Parameters!$B$2, D2)/Parameters!$B$6, 0) -> 968255.66 | G2: =F2*IF(E2="", Parameters!$B$2, E2) -> 1.5492091e+09 | H2: =G2*Parameters!$B$4 -> 40279436 | I2: =1/POWER(1+Parameters!$B$5, A2) -> 0.90909091 | J2: =H2*I2 -> 36617669 | K2: =SUM($G$2:G2) -> 1.5492091e+09 | L2: =F2*0.95 -> 919842.88 | M2: =L2*IF(E2="",Parameters!$B$2,E2) -> 1.4717486e+09 | N2: =M2*0.0251 -> 36940890 | O2: =N2*I2 -> 33582627
A3: 2 | B3: 19000000 | C3: 1.933 | D3: 0.82 | E3: 1600 | F3: =IFERROR(B3*C3*IF(D3="", Parameters!$B$2, D3)/Parameters!$B$6, 0) -> 968255.66 | G3: =F3*IF(E3="", Parameters!$B$2, E3) -> 1.5492091e+09 | H3: =G3*Parameters!$B$4 -> 40279436 | I3: =1/POWER(1+Parameters!$B$5, A3) -> 0.82644628 | J3: =H3*I3 -> 33288790 | K3: =SUM($G$2:G3) -> 3.0984181e+09 | L3: =F3*0.95 -> 919842.88 | M3: =L3*IF(E3="",Parameters!$B$2,E3) -> 1.4717486e+09 | N3: =M3*0.0251 -> 36940890 | O3: =N3*I3 -> 30529661
A4: 3 | B4: 19000000 | C4: 1.933 | D4: 0.82 | E4: 1600 | F4: =IFERROR(B4*C4*IF(D4="", Parameters!$B$2, D4)/Parameters!$B$6, 0) -> 968255.66 | G4: =F4*IF(E4="", Parameters!$B$2, E4) -> 1.5492091e+09 | H4: =G4*Parameters!$B$4 -> 40279436 | I4: =1/POWER(1+Parameters!$B$5, A4) -> 0.7513148 | J4: =H4*I4 -> 30262536 | K4: =SUM($G$2:G4) -> 4.6476272e+09 | L4: =F4*0.95 -> 919842.88 | M4: =L4*IF(E4="",Parameters!$B$2,E4) -> 1.4717486e+09 | N4: =M4*0.0251 -> 36940890 | O4: =N4*I4 -> 27754237
A5: 4 | B5: 19000000 | C5: 1.933 | D5: 0.82 | E5: 1600 | F5: =IFERROR(B5*C5*IF(D5="", Parameters!$B$2, D5)/Parameters!$B$6, 0) -> 968255.66 | G5: =F5*IF(E5="", Parameters!$B$2, E5) -> 1.5492091e+09 | H5: =G5*Parameters!$B$4 -> 40279436 | I5: =1/POWER(1+Parameters!$B$5, A5) -> 0.68301346 | J5: =H5*I5 -> 27511396 | K5: =SUM($G$2:G5) -> 6.1968362e+09 | L5: =F5*0.95 -> 919842.88 | M5: =L5*IF(E5="",Parameters!$B$2,E5) -> 1.4717486e+09 | N5: =M5*0.0251 -> 36940890 | O5: =N5*I5 -> 25231125
A6: 5 | B6: 19000000 | C6: 1.933 | D6: 0.82 | E6: 1600 | F6: =IFERROR(B6*C6*IF(D6="", Parameters!$B$2, D6)/Parameters!$B$6, 0) -> 968255.66 | G6: =F6*IF(E6="", Parameters!$B$2, E6) -> 1.5492091e+09 | H6: =G6*Parameters!$B$4 -> 40279436 | I6: =1/POWER(1+Parameters!$B$5, A6) -> 0.62092132 | J6: =H6*I6 -> 25010360 | K6: =SUM($G$2:G6) -> 7.7460453e+09 | L6: =F6*0.95 -> 919842.88 | M6: =L6*IF(E6="",Parameters!$B$2,E6) -> 1.4717486e+09 | N6: =M6*0.0251 -> 36940890 | O6: =N6*I6 -> 22937386
A7: 6 | B7: 19000000 | C7: 1.933 | D7: 0.82 | E7: 1600 | F7: =IFERROR(B7*C7*IF(D7="", Parameters!$B$2, D7)/Parameters!$B$6, 0) -> 968255.66 | G7: =F7*IF(E7="", Parameters!$B$2, E7) -> 1.5492091e+09 | H7: =G7*Parameters!$B$4 -> 40279436 | I7: =1/POWER(1+Parameters!$B$5, A7) -> 0.56447393 | J7: =H7*I7 -> 22736691 | K7: =SUM($G$2:G7) -> 9.2952544e+09 | L7: =F7*0.95 -> 919842.88 | M7: =L7*IF(E7="",Parameters!$B$2,E7) -> 1.4717486e+09 | N7: =M7*0.0251 -> 36940890 | O7: =N7*I7 -> 20852169
A8: 7 | B8: 19000000 | C8: 1.933 | D8: 0.82 | E8: 1600 | F8: =IFERROR(B8*C8*IF(D8="", Parameters!$B$2, D8)/Parameters!$B$6, 0) -> 968255.66 | G8: =F8*IF(E8="", Parameters!$B$2, E8) -> 1.5492091e+09 | H8: =G8*Parameters!$B$4 -> 40279436 | I8: =1/POWER(1+Parameters!$B$5, A8) -> 0.51315812 | J8: =H8*I8 -> 20669719 | K8: =SUM($G$2:G8) -> 1.0844463e+10 | L8: =F8*0.95 -> 919842.88 | M8: =L8*IF(E8="",Parameters!$B$2,E8) -> 1.4717486e+09 | N8: =M8*0.0251 -> 36940890 | O8: =N8*I8 -> 18956518
A9: 8 | B9: 19000000 | C9: 1.933 | D9: 0.82 | E9: 1600 | F9: =IFERROR(B9*C9*IF(D9="", Parameters!$B$2, D9)/Parameters!$B$6, 0) -> 968255.66 | G9: =F9*IF(E9="", Parameters!$B$2, E9) -> 1.5492091e+09 | H9: =G9*Parameters!$B$4 -> 40279436 | I9: =1/POWER(1+Parameters!$B$5, A9) -> 0.46650738 | J9: =H9*I9 -> 18790654 | K9: =SUM($G$2:G9) -> 1.2393672e+10 | L9: =F9*0.95 -> 919842.88 | M9: =L9*IF(E9="",Parameters!$B$2,E9) -> 1.4717486e+09 | N9: =M9*0.0251 -> 36940890 | O9: =N9*I9 -> 17233198
A10: 9 | B10: 19000000 | C10: 1.933 | D10: 0.82 | E10: 1600 | F10: =IFERROR(B10*C10*IF(D10="", Parameters!$B$2, D10)/Parameters!$B$6, 0) -> 968255.66 | G10: =F10*IF(E10="", Parameters!$B$2, E10) -> 1.5492091e+09 | H10: =G10*Parameters!$B$4 -> 40279436 | I10: =1/POWER(1+Parameters!$B$5, A10) -> 0.42409762 | J10: =H10*I10 -> 17082413 | K10: =SUM($G$2:G10) -> 1.3942882e+10 | L10: =F10*0.95 -> 919842.88 | M10: =L10*IF(E10="",Parameters!$B$2,E10) -> 1.4717486e+09 | N10: =M10*0.0251 -> 36940890 | O10: =N10*I10 -> 15666543
A11: 10 | B11: 19000000 | C11: 1.933 | D11: 0.82 | E11: 1600 | F11: =IFERROR(B11*C11*IF(D11="", Parameters!$B$2, D11)/Parameters!$B$6, 0) -> 968255.66 | G11: =F11*IF(E11="", Parameters!$B$2, E11) -> 1.5492091e+09 | H11: =G11*Parameters!$B$4 -> 40279436 | I11: =1/POWER(1+Parameters!$B$5, A11) -> 0.38554329 | J11: =H11*I11 -> 15529466 | K11: =SUM($G$2:G11) -> 1.5492091e+10 | L11: =F11*0.95 -> 919842.88 | M11: =L11*IF(E11="",Parameters!$B$2,E11) -> 1.4717486e+09 | N11: =M11*0.0251 -> 36940890 | O11: =N11*I11 -> 14242312
A12: 11 | B12: 19000000 | C12: 1.933 | D12: 0.82 | E12: 1600 | F12: =IFERROR(B12*C12*IF(D12="", Parameters!$B$2, D12)/Parameters!$B$6, 0) -> 968255.66 | G12: =F12*IF(E12="", Parameters!$B$2, E12) -> 1.5492091e+09 | H12: =G12*Parameters!$B$4 -> 40279436 | I12: =1/POWER(1+Parameters!$B$5, A12) -> 0.3504939 | J12: =H12*I12 -> 14117696 | K12: =SUM($G$2:G12) -> 1.70413e+10 | L12: =F12*0.95 -> 919842.88 | M12: =L12*IF(E12="",Parameters!$B$2,E12) -> 1.4717486e+09 | N12: =M12*0.0251 -> 36940890 | O12: =N12*I12 -> 12947557
A13: 12 | B13: 19000000 | C13: 1.933 | D13: 0.82 | E13: 1600 | F13: =IFERROR(B13*C13*IF(D13="", Parameters!$B$2, D13)/Parameters!$B$6, 0) -> 968255.66 | G13: =F13*IF(E13="", Parameters!$B$2, E13) -> 1.5492091e+09 | H13: =G13*Parameters!$B$4 -> 40279436 | I13: =1/POWER(1+Parameters!$B$5, A13) -> 0.31863082 | J13: =H13*I13 -> 12834269 | K13: =SUM($G$2:G13) -> 1.8590509e+10 | L13: =F13*0.95 -> 919842.88 | M13: =L13*IF(E13="",Parameters!$B$2,E13) -> 1.4717486e+09 | N13: =M13*0.0251 -> 36940890 | O13: =N13*I13 -> 11770506
... A27: 26 | B27: 19000000 | C27: 1.933 | D27: 0.82 | E27: 1600 | F27: =IFERROR(B27*C27*IF(D27="", Parameters!$B$2, D27)/Parameters!$B$6, 0) -> 968255.66 | G27: =F27*IF(E27="", Parameters!$B$2, E27) -> 1.5492091e+09 | H27: =G27*Parameters!$B$4 -> 40279436 | I27: =1/POWER(1+Parameters!$B$5, A27) -> 0.083905453 | J27: =H27*I27 -> 3379664.3 | K27: =SUM($G$2:G27) -> 4.0279436e+10 | L27: =F27*0.95 -> 919842.88 | M27: =L27*IF(E27="",Parameters!$B$2,E27) -> 1.4717486e+09 | N27: =M27*0.0251 -> 36940890 | O27: =N27*I27 -> 3099542.1
F39: Totals / Key Outputs | G39: =SUM(G2:G27) -> 4.0279436e+10 | H39: =SUM(H2:H33) -> 1.0472653e+09 | J39: =SUM(J2:J27) -> 3.6899771e+08 | O39: =SUM(O2:O27) -> 3.3841348e+08
F40: Total Revenue (USD) | G40: =G39 -> 4.0279436e+10
F41: Total Severance Tax (USD) | G41: =H39 -> 1.0472653e+09
F42: PV(Severance Tax) (USD) | G42: =J39 -> 3.6899771e+08

Sheet schedule_20
A1: Year | B1: Ore (t) | C1: Grade (g/t) | D1: Recovery (override, optional) | E1: Metal Price (override, optional) | F1: Metal Produced (oz) | G1: Revenue (USD) | H1: Severance Tax (USD) | I1: Discount Factor | J1: PV(Severance Tax) (USD) | K1: Cumulative Revenue (USD) | L1: Payable Metal (oz) | M1: NSR ($) | N1: Royalty ($) | O1: PV(Royalty)
A2: 1 | B2: 16000000 | C2: 1.921 | D2: 0.82 | E2: 1600 | F2: =IFERROR(B2*C2*IF(D2="", Parameters!$B$2, D2)/Parameters!$B$6, 0) -> 810311.38 | G2: =F2*IF(E2="", Parameters!$B$2, E2) -> 1.2964982e+09 | H2: =G2*Parameters!$B$4 -> 33708953 | I2: =1/POWER(1+Parameters!$B$5, A2) -> 0.90909091 | J2: =H2*I2 -> 30644503 | K2: =SUM($G$2:G2) -> 1.2964982e+09 | L2: =F2*0.95 -> 769795.81 | M2: =L2*IF(E2="",Parameters!$B$2,E2) -> 1.2316733e+09 | N2: =M2*0.0251 -> 30915000 | O2: =N2*I2 -> 28104545
A3: 2 | B3: 16000000 | C3: 1.921 | D3: 0.82 | E3: 1600 | F3: =IFERROR(B3*C3*IF(D3="", Parameters!$B$2, D3)/Parameters!$B$6, 0) -> 810311.38 | G3: =F3*IF(E3="", Parameters!$B$2, E3) -> 1.2964982e+09 | H3: =G3*Parameters!$B$4 -> 33708953 | I3: =1/POWER(1+Parameters!$B$5, A3) -> 0.82644628 | J3: =H3*I3 -> 27858639 | K3: =SUM($G$2:G3) -> 2.5929964e+09 | L3: =F3*0.95 -> 769795.81 | M3: =L3*IF(E3="",Parameters!$B$2,E3) -> 1.2316733e+09 | N3: =M3*0.0251 -> 30915000 | O3: =N3*I3 -> 25549587
A4: 3 | B4: 16000000 | C4: 1.921 | D4: 0.82 | E4: 1600 | F4: =IFERROR(B4*C4*IF(D4="", Parameters!$B$2, D4)/Parameters!$B$6, 0) -> 810311.38 | G4: =F4*IF(E4="", Parameters!$B$2, E4) -> 1.2964982e+09 | H4: =G4*Parameters!$B$4 -> 33708953 | I4: =1/POWER(1+Parameters!$B$5, A4) -> 0.7513148 | J4: =H4*I4 -> 25326036 | K4: =SUM($G$2:G4) -> 3.8894946e+09 | L4: =F4*0.95 -> 769795.81 | M4: =L4*IF(E4="",Parameters!$B$2,E4) -> 1.2316733e+09 | N4: =M4*0.0251 -> 30915000 | O4: =N4*I4 -> 23226897
A5: 4 | B5: 16000000 | C5: 1.921 | D5: 0.82 | E5: 1600 | F5: =IFERROR(B5*C5*IF(D5="", Parameters!$B$2, D5)/Parameters!$B$6, 0) -> 810311.38 | G5: =F5*IF(E5="", Parameters!$B$2, E5) -> 1.2964982e+09 | H5: =G5*Parameters!$B$4 -> 33708953 | I5: =1/POWER(1+Parameters!$B$5, A5) -> 0.68301346 | J5: =H5*I5 -> 23023669 | K5: =SUM($G$2:G5) -> 5.1859928e+09 | L5: =F5*0.95 -> 769795.81 | M5: =L5*IF(E5="",Parameters!$B$2,E5) -> 1.2316733e+09 | N5: =M5*0.0251 -> 30915000 | O5: =N5*I5 -> 21115361
A6: 5 | B6: 16000000 | C6: 1.921 | D6: 0.82 | E6: 1600 | F6: =IFERROR(B6*C6*IF(D6="", Parameters!$B$2, D6)/Parameters!$B$6, 0) -> 810311.38 | G6: =F6*IF(E6="", Parameters!$B$2, E6) -> 1.2964982e+09 | H6: =G6*Parameters!$B$4 -> 33708953 | I6: =1/POWER(1+Parameters!$B$5, A6) -> 0.62092132 | J6: =H6*I6 -> 20930608 | K6: =SUM($G$2:G6) -> 6.482491e+09 | L6: =F6*0.95 -> 769795.81 | M6: =L6*IF(E6="",Parameters!$B$2,E6) -> 1.2316733e+09 | N6: =M6*0.0251 -> 30915000 | O6: =N6*I6 -> 19195783
A7: 6 | B7: 16000000 | C7: 1.921 | D7: 0.82 | E7: 1600 | F7: =IFERROR(B7*C7*IF(D7="", Parameters!$B$2, D7)/Parameters!$B$6, 0) -> 810311.38 | G7: =F7*IF(E7="", Parameters!$B$2, E7) -> 1.2964982e+09 | H7: =G7*Parameters!$B$4 -> 33708953 | I7: =1/POWER(1+Parameters!$B$5, A7) -> 0.56447393 | J7: =H7*I7 -> 19027825 | K7: =SUM($G$2:G7) -> 7.7789892e+09 | L7: =F7*0.95 -> 769795.81 | M7: =L7*IF(E7="",Parameters!$B$2,E7) -> 1.2316733e+09 | N7: =M7*0.0251 -> 30915000 | O7: =N7*I7 -> 17450711
A8: 7 | B8: 16000000 | C8: 1.921 | D8: 0.82 | E8: 1600 | F8: =IFERROR(B8*C8*IF(D8="", Parameters!$B$2, D8)/Parameters!$B$6, 0) -> 810311.38 | G8: =F8*IF(E8="", Parameters!$B$2, E8) -> 1.2964982e+09 | H8: =G8*Parameters!$B$4 -> 33708953 | I8: =1/POWER(1+Parameters!$B$5, A8) -> 0.51315812 | J8: =H8*I8 -> 17298023 | K8: =SUM($G$2:G8) -> 9.0754875e+09 | L8: =F8*0.95 -> 769795.81 | M8: =L8*IF(E8="",Parameters!$B$2,E8) -> 1.2316733e+09 | N8: =M8*0.0251 -> 30915000 | O8: =N8*I8 -> 15864283
A9: 8 | B9: 16000000 | C9: 1.921 | D9: 0.82 | E9: 1600 | F9: =IFERROR(B9*C9*IF(D9="", Parameters!$B$2, D9)/Parameters!$B$6, 0) -> 810311.38 | G9: =F9*IF(E9="", Parameters!$B$2, E9) -> 1.2964982e+09 | H9: =G9*Parameters!$B$4 -> 33708953 | I9: =1/POWER(1+Parameters!$B$5, A9) -> 0.46650738 | J9: =H9*I9 -> 15725476 | K9: =SUM($G$2:G9) -> 1.0371986e+10 | L9: =F9*0.95 -> 769795.81 | M9: =L9*IF(E9="",Parameters!$B$2,E9) -> 1.2316733e+09 | N9: =M9*0.0251 -> 30915000 | O9: =N9*I9 -> 14422076
A10: 9 | B10: 16000000 | C10: 1.921 | D10: 0.82 | E10: 1600 | F10: =IFERROR(B10*C10*IF(D10="", Parameters!$B$2, D10)/Parameters!$B$6, 0) -> 810311.38 | G10: =F10*IF(E10="", Parameters!$B$2, E10) -> 1.2964982e+09 | H10: =G10*Parameters!$B$4 -> 33708953 | I10: =1/POWER(1+Parameters!$B$5, A10) -> 0.42409762 | J10: =H10*I10 -> 14295887 | K10: =SUM($G$2:G10) -> 1.1668484e+10 | L10: =F10*0.95 -> 769795.81 | M10: =L10*IF(E10="",Parameters!$B$2,E10) -> 1.2316733e+09 | N10: =M10*0.0251 -> 30915000 | O10: =N10*I10 -> 13110978
A11: 10 | B11: 16000000 | C11: 1.921 | D11: 0.82 | E11: 1600 | F11: =IFERROR(B11*C11*IF(D11="", Parameters!$B$2, D11)/Parameters!$B$6, 0) -> 810311.38 | G11: =F11*IF(E11="", Parameters!$B$2, E11) -> 1.2964982e+09 | H11: =G11*Parameters!$B$4 -> 33708953 | I11: =1/POWER(1+Parameters!$B$5, A11) -> 0.38554329 | J11: =H11*I11 -> 12996261 | K11: =SUM($G$2:G11) -> 1.2964982e+10 | L11: =F11*0.95 -> 769795.81 | M11: =L11*IF(E11="",Parameters!$B$2,E11) -> 1.2316733e+09 | N11: =M11*0.0251 -> 30915000 | O11: =N11*I11 -> 11919071
A12: 11 | B12: 16000000 | C12: 1.921 | D12: 0.82 | E12: 1600 | F12: =IFERROR(B12*C12*IF(D12="", Parameters!$B$2, D12)/Parameters!$B$6, 0) -> 810311.38 | G12: =F12*IF(E12="", Parameters!$B$2, E12) -> 1.2964982e+09 | H12: =G12*Parameters!$B$4 -> 33708953 | I12: =1/POWER(1+Parameters!$B$5, A12) -> 0.3504939 | J12: =H12*I12 -> 11814783 | K12: =SUM($G$2:G12) -> 1.426148e+10 | L12: =F12*0.95 -> 769795.81 | M12: =L12*IF(E12="",Parameters!$B$2,E12) -> 1.2316733e+09 | N12: =M12*0.0251 -> 30915000 | O12: =N12*I12 -> 10835519
A13: 12 | B13: 16000000 | C13: 1.921 | D13: 0.82 | E13: 1600 | F13: =IFERROR(B13*C13*IF(D13="", Parameters!$B$2, D13)/Parameters!$B$6, 0) -> 810311.38 | G13: =F13*IF(E13="", Parameters!$B$2, E13) -> 1.2964982e+09 | H13: =G13*Parameters!$B$4 -> 33708953 | I13: =1/POWER(1+Parameters!$B$5, A13) -> 0.31863082 | J13: =H13*I13 -> 10740711 | K13: =SUM($G$2:G13) -> 1.5557978e+10 | L13: =F13*0.95 -> 769795.81 | M13: =L13*IF(E13="",Parameters!$B$2,E13) -> 1.2316733e+09 | N13: =M13*0.0251 -> 30915000 | O13: =N13*I13 -> 9850471.7
... A32: 31 | B32: 16000000 | C32: 1.921 | D32: 0.82 | E32: 1600 | F32: =IFERROR(B32*C32*IF(D32="", Parameters!$B$2, D32)/Parameters!$B$6, 0) -> 810311.38 | G32: =F32*IF(E32="", Parameters!$B$2, E32) -> 1.2964982e+09 | H32: =G32*Parameters!$B$4 -> 33708953 | I32: =1/POWER(1+Parameters!$B$5, A32) -> 0.052098685 | J32: =H32*I32 -> 1756192.1 | K32: =SUM($G$2:G32) -> 4.0191444e+10 | L32: =F32*0.95 -> 769795.81 | M32: =L32*IF(E32="",Parameters!$B$2,E32) -> 1.2316733e+09 | N32: =M32*0.0251 -> 30915000 | O32: =N32*I32 -> 1610630.8
F39: Totals / Key Outputs | G39: =SUM(G2:G32) -> 4.0191444e+10 | H39: =SUM(H2:H32) -> 1.0449776e+09 | J39: =SUM(J2:J32) -> 3.1952761e+08 | O39: =SUM(O2:O32) -> 2.9304369e+08
F40: Total Revenue (USD) | G40: =G39 -> 4.0191444e+10
F41: Total Severance Tax (USD) | G41: =H39 -> 1.0449776e+09
F42: PV(Severance Tax) (USD) | G42: =J39 -> 3.1952761e+08

Sheet Parameters
A1: Parameter | B1: Value
A2: Metal Price (USD/oz) | B2: 1600
A3: Metallurgical Recovery (decimal) | B3: 0.82
A4: Severance Tax Rate (decimal) | B4: 0.026
A5: Discount Rate (decimal) | B5: 0.1
A6: Grams per Troy Ounce | B6: 31.1035
A7: Royalty Type (note) | B7: NSR
A8: NSR Rate (decimal) | B8: 0.0251
A9: Payability (decimal) | B9: 0.95

Sheet ReadMe
A1: Severance Tax & Royalty Calculator
A3: How to use this template:
A4: 1) Paste your yearly schedule from Whittle into the 'Data' sheet:
A5: - Year, Ore (t), Grade (g/t).
A6: - Optional: enter 'Recovery (override)' or 'Metal Price (override)' per year if they differ from base assumptions.
A7: 2) Adjust base assumptions in the 'Parameters' sheet:
A8: - Metal Price (USD/oz)
A9: - Metallurgical Recovery (decimal, e.g., 0.90)
A10: - Severance Tax Rate (decimal, e.g., 0.026 for Utah)
A11: - Discount Rate (decimal, e.g., 0.08)
A12: - Grams per Troy Ounce (31.1035 for gold).
A13: 3) Outputs per year:
... A21: Note: For multi-schedule comparisons, duplicate the 'Data' sheet per schedule (Schedule_1..Schedule_20) and keep one shared 'Parameters' tab.
